Workbook

Sheet Read Me
A1: ALL Claims 2026-S1 - Master
A3: ="Every one of the "&COUNTA('All Claims'!$D$2:$D$2000)&" claims for 2026 S1, all specialties and all six months in one place, on the 'All Claims' tab." -> Every one of the 476 claims for 2026 S1, all specialties and all six months in one place, on the 'All Claims' tab.
A5: Row order - timely filing deadline
A6: Sorted by Days Until Deadline, most urgent first, except that Finalized claims with a Latest Date Worked are moved to the bottom (still in deadline order among themselves). A negative number means the filing window has already closed; a blank means no limit is on file. The counts below update automatically (Finalized claims with a Latest Date Worked have their deadline cells left empty and are not counted), and the row order is a snapshot - to bring it up to date, sort ascending on Days Until Deadline and then move the Finalized rows with a Latest Date Worked back to the bottom.
A7: =" 1 - Due in 5 days or less: "&COUNTIFS('All Claims'!$L$2:$L$2000,">=0",'All Claims'!$L$2:$L$2000,"<=5") -> 1 - Due in 5 days or less: 0
A8: =" 2 - Due in 6-30 days: "&COUNTIFS('All Claims'!$L$2:$L$2000,">5",'All Claims'!$L$2:$L$2000,"<=30") -> 2 - Due in 6-30 days: 5
A9: =" 3 - Due in 31+ days: "&COUNTIFS('All Claims'!$L$2:$L$2000,">30") -> 3 - Due in 31+ days: 123
A10: =" 4 - Past deadline: "&COUNTIFS('All Claims'!$L$2:$L$2000,"<0") -> 4 - Past deadline: 210
A11: =" 5 - No limit on file: "&SUMPRODUCT(('All Claims'!$D$2:$D$2000<>"")*('All Claims'!$L$2:$L$2000="")*(1-(TRIM('All Claims'!$A$2:$A$2000)="Finalized")*('All Claims'!$K$2:$K$2000<>""))) -> 5 - No limit on file: 42
A13: Filing Deadline is the date of service plus the primary payer's limit, from 'Carrier_Timely_Filing_Reference.xlsx'. Days Until Deadline is a live formula; the row order is a snapshot taken on 12 August 2026. Check Filing Limit and Limit Carrier for the figure applied - where a payer had two possible limits the shorter one was used.
A15: Four columns are live links - do not type in them
A16: Claim Status, Notes, Processed Date and Latest Date Worked (shaded pale green) are formulas. Each one looks up its claim by Primary Claim ID in the matching specialty sheet of the matching monthly workbook and returns whatever is entered there. Edit any of the four in a monthly file, save it, and this file shows the change.
A17: Typing directly into these four columns here replaces the formula and breaks the link for that row. Make every edit in the monthly workbooks.
A18: Processed Date and Latest Date Worked are shown MM/DD/YYYY, the same as every other date column. Processed Date was seeded from the date in the Notes where there was one and from the Insurance Check Date otherwise.
A19: Days Until Corrected Claim Deadline and Days Until Appeal Deadline are live formulas counted from whichever date each carrier uses - see Corrected Claim From and Appeal From. They are not links, so they recalculate here from this file's own Processed Date, which is itself linked to the monthly workbook.
A21: Refreshing
A22: Keep all seven files together in this folder and do not rename them. When you open this file, Excel asks whether to update links - choose Enable Content / Update. To refresh while it is open: Data > Queries & Connections > Edit Links > Update Values. Values are also cached, so the last known status and notes appear even if you decline the update.
A24: Linked source files
A25: [1] SPC26S1 - 01 January v3.xlsx
A26: [2] SPC26S1 - 02 February v3.xlsx
A27: [3] SPC26S1 - 03 March v3.xlsx
... A46: Any other status is left unshaded.

Sheet All Claims
A1: Claim Status | B1: Notes | C1: Processed Date | D1: Primary Claim ID | E1: Chart Number | F1: Date of Service | G1: Responsible Payer | H1: Primary Payer Name | I1: Secondary Payer Name | J1: Procedure Code | K1: Latest Date Worked | L1: Days Until Deadline | M1: Days Until Corrected Claim Deadline | N1: Days Until Appeal Deadline | O1: Filing Deadline | P1: Filing Limit | Q1: Limit Carrier | R1: Corrected Claim Limit | S1: Corrected Claim From | T1: Appeal Limit | U1: Appeal From | V1: Service Month | W1: Specialty | X1: Modifier 1 | Y1: Modifier 2 | Z1: Modifier 3 | AA1: Units | AB1: Charge Amount | AC1: Adjustment | AD1: Insurance Payment | AE1: Insurance Check Date | AF1: Insurance Balance | AG1: AR Age by Service Date | AH1: Diagnosis Code 1 | AI1: Diagnosis Code 2 | AJ1: Diagnosis Code 3 | AK1: Diagnosis Code 4 | AL1: Secondary Claim ID | AM1: Rendering Provider | AN1: Location Name | AO1: Created Date
A2: =IFERROR(IF(INDEX([1]ORTHO!$A$2:$A$10,MATCH($D2,[1]ORTHO!$D$2:$D$10,0))="","",INDEX([1]ORTHO!$A$2:$A$10,MATCH($D2,[1]ORTHO!$D$2:$D$10,0))),"") | B2: =IFERROR(IF(INDEX([1]ORTHO!$B$2:$B$10,MATCH($D2,[1]ORTHO!$D$2:$D$10,0))="","",INDEX([1]ORTHO!$B$2:$B$10,MATCH($D2,[1]ORTHO!$D$2:$D$10,0))),"") | C2: =IFERROR(IF(INDEX([1]ORTHO!$C$2:$C$10,MATCH($D2,[1]ORTHO!$D$2:$D$10,0))="","",INDEX([1]ORTHO!$C$2:$C$10,MATCH($D2,[1]ORTHO!$D$2:$D$10,0))),"") | D2: 557028860 | E2: HF527306886 | F2: 46037 | G2: Arizona Priority Care Plus | H2: Arizona Priority Care Plus | I2: No Payer | J2: 63685 x1 | K2: =IFERROR(IF(INDEX([1]ORTHO!$K$2:$K$10,MATCH($D2,[1]ORTHO!$D$2:$D$10,0))="","",INDEX([1]ORTHO!$K$2:$K$10,MATCH($D2,[1]ORTHO!$D$2:$D$10,0))),"") | L2: =IF($O2="","",$O2-TODAY()) -> -207 | M2: =IF(AND(TRIM($A2)="Finalized",$K2<>""),"",IF($C2="","",$C2+365-TODAY())) | N2: =IF(AND(TRIM($A2)="Finalized",$K2<>""),"",IF($C2="","",$C2+365-TODAY())) | O2: =IF(AND(TRIM($A2)="Finalized",$K2<>""),"",DATE(2026,3,16)) -> 46097 | P2: 60 days | Q2: AZ PRIORITY CARE | R2: 365 days | S2: Processed date | T2: 365 days | U2: Processed date | V2: 2026-01 January | W2: ORTHO | AA2: 1 | AB2: 2493.33 | AC2: 0 | AD2: 0 | AF2: 2493.33 | AG2: 205 | AH2: M961 | AI2: M5416 | AM2: KALLGREN, MARK | AN2: Premier Endoscopy Center, LLC | AO2: 46048
A3: =IFERROR(IF(INDEX([1]DME!$A$2:$A$8,MATCH($D3,[1]DME!$D$2:$D$8,0))="","",INDEX([1]DME!$A$2:$A$8,MATCH($D3,[1]DME!$D$2:$D$8,0))),"") -> Pending | B3: =IFERROR(IF(INDEX([1]DME!$B$2:$B$8,MATCH($D3,[1]DME!$D$2:$D$8,0))="","",INDEX([1]DME!$B$2:$B$8,MATCH($D3,[1]DME!$D$2:$D$8,0))),"") -> secondary - I need to crossover claim - Corrected adjustments, and resubmitted | C3: =IFERROR(IF(INDEX([1]DME!$C$2:$C$8,MATCH($D3,[1]DME!$D$2:$D$8,0))="","",INDEX([1]DME!$C$2:$C$8,MATCH($D3,[1]DME!$D$2:$D$8,0))),"") -> 46089 | D3: 546184427 | E3: HF503610126 | F3: 46027 | G3: Tricare for Life (All Regions) | H3: Humana | I3: Tricare for Life (All Regions) | J3: A6023+A2 x20 | K3: =IFERROR(IF(INDEX([1]DME!$K$2:$K$8,MATCH($D3,[1]DME!$D$2:$D$8,0))="","",INDEX([1]DME!$K$2:$K$8,MATCH($D3,[1]DME!$D$2:$D$8,0))),"") -> 46141 | L3: =IF($O3="","",$O3-TODAY()) -> -187 | M3: =IF(AND(TRIM($A3)="Finalized",$K3<>""),"",IF($F3="","",$F3+90-TODAY())) -> -187 | N3: =IF(AND(TRIM($A3)="Finalized",$K3<>""),"",IF($C3="","",$C3+60-TODAY())) -> -155 | O3: =IF(AND(TRIM($A3)="Finalized",$K3<>""),"",DATE(2026,4,5)) -> 46117 | P3: 90 days | Q3: HUMANA COMMERCIAL | R3: 90 days | S3: Date of service | T3: 60 days | U3: Processed date | V3: 2026-01 January | W3: DME | X3: A2 | AA3: 20 | AB3: 36353.8 | AC3: 33154.53 | AD3: 2833.13 | AE3: 46089 | AF3: 366.14 | AG3: 215 | AH3: G894 | AI3: G90513 | AJ3: M961 | AL3: 557644876 | AM3: MCMURDIE, TODD | AN3: ASAP - Surprise - Reems | AO3: 46036
A4: =IFERROR(IF(INDEX([1]GAE!$A$2:$A$12,MATCH($D4,[1]GAE!$D$2:$D$12,0))="","",INDEX([1]GAE!$A$2:$A$12,MATCH($D4,[1]GAE!$D$2:$D$12,0))),"") | B4: =IFERROR(IF(INDEX([1]GAE!$B$2:$B$12,MATCH($D4,[1]GAE!$D$2:$D$12,0))="","",INDEX([1]GAE!$B$2:$B$12,MATCH($D4,[1]GAE!$D$2:$D$12,0))),"") | C4: =IFERROR(IF(INDEX([1]GAE!$C$2:$C$12,MATCH($D4,[1]GAE!$D$2:$D$12,0))="","",INDEX([1]GAE!$C$2:$C$12,MATCH($D4,[1]GAE!$D$2:$D$12,0))),"") -> 46121 | D4: 548877808 | E4: HF540310616 | F4: 46027 | G4: Humana Gold Plus HMO | H4: Humana Gold Plus HMO | I4: No Payer | J4: 36246+59+RT x1; 36245+59 x1; 37242 x1; 36248+59 x3 | K4: =IFERROR(IF(INDEX([1]GAE!$K$2:$K$12,MATCH($D4,[1]GAE!$D$2:$D$12,0))="","",INDEX([1]GAE!$K$2:$K$12,MATCH($D4,[1]GAE!$D$2:$D$12,0))),"") | L4: =IF($O4="","",$O4-TODAY()) -> -187 | M4: =IF(AND(TRIM($A4)="Finalized",$K4<>""),"",IF($F4="","",$F4+90-TODAY())) -> -187 | N4: =IF(AND(TRIM($A4)="Finalized",$K4<>""),"",IF($C4="","",$C4+540-TODAY())) -> 357 | O4: =IF(AND(TRIM($A4)="Finalized",$K4<>""),"",DATE(2026,4,5)) -> 46117 | P4: 90 days | Q4: HUMANA MA | R4: 90 days | S4: Date of service | T4: 540 days | U4: Processed date | V4: 2026-01 January | W4: GAE | X4: 59 | Y4: RT | AA4: 1, 3 | AB4: 65892.82 | AC4: 0 | AD4: 0 | AE4: 46121 | AF4: 65892.82 | AG4: 215 | AH4: M1711 | AI4: I798 | AJ4: M25561 | AM4: HUNTER, DREW | AN4: ASAP Surgery Centers North Valley LLC | AO4: 46062
A5: =IFERROR(IF(INDEX([1]GAE!$A$2:$A$12,MATCH($D5,[1]GAE!$D$2:$D$12,0))="","",INDEX([1]GAE!$A$2:$A$12,MATCH($D5,[1]GAE!$D$2:$D$12,0))),"") | B5: =IFERROR(IF(INDEX([1]GAE!$B$2:$B$12,MATCH($D5,[1]GAE!$D$2:$D$12,0))="","",INDEX([1]GAE!$B$2:$B$12,MATCH($D5,[1]GAE!$D$2:$D$12,0))),"") | C5: =IFERROR(IF(INDEX([1]GAE!$C$2:$C$12,MATCH($D5,[1]GAE!$D$2:$D$12,0))="","",INDEX([1]GAE!$C$2:$C$12,MATCH($D5,[1]GAE!$D$2:$D$12,0))),"") -> 46142 | D5: 554116779 | E5: HF479029623 | F5: 46027 | G5: Humana Gold Plus HMO | H5: Humana Gold Plus HMO | I5: No Payer | J5: 36248+59 x2; 37242 x1; 36246+59+RT x1; 36245+59 x1 | K5: =IFERROR(IF(INDEX([1]GAE!$K$2:$K$12,MATCH($D5,[1]GAE!$D$2:$D$12,0))="","",INDEX([1]GAE!$K$2:$K$12,MATCH($D5,[1]GAE!$D$2:$D$12,0))),"") | L5: =IF($O5="","",$O5-TODAY()) -> -187 | M5: =IF(AND(TRIM($A5)="Finalized",$K5<>""),"",IF($F5="","",$F5+90-TODAY())) -> -187 | N5: =IF(AND(TRIM($A5)="Finalized",$K5<>""),"",IF($C5="","",$C5+540-TODAY())) -> 378 | O5: =IF(AND(TRIM($A5)="Finalized",$K5<>""),"",DATE(2026,4,5)) -> 46117 | P5: 90 days | Q5: HUMANA MA | R5: 90 days | S5: Date of service | T5: 540 days | U5: Processed date | V5: 2026-01 January | W5: GAE | X5: 59 | Y5: RT | AA5: 2, 1 | AB5: 65085.23 | AC5: 0 | AD5: 0 | AE5: 46142 | AF5: 65085.23 | AG5: 215 | AH5: M1711 | AI5: I798 | AJ5: M25561 | AM5: HUNTER, DREW | AN5: ASAP Surgery Centers North Valley LLC | AO5: 46062
A6: =IFERROR(IF(INDEX([1]BH!$A$2:$A$17,MATCH($D6,[1]BH!$D$2:$D$17,0))="","",INDEX([1]BH!$A$2:$A$17,MATCH($D6,[1]BH!$D$2:$D$17,0))),"") -> Denied | B6: =IFERROR(IF(INDEX([1]BH!$B$2:$B$17,MATCH($D6,[1]BH!$D$2:$D$17,0))="","",INDEX([1]BH!$B$2:$B$17,MATCH($D6,[1]BH!$D$2:$D$17,0))),"") -> Uploaded MR - PIQ-82135368 | C6: =IFERROR(IF(INDEX([1]BH!$C$2:$C$17,MATCH($D6,[1]BH!$D$2:$D$17,0))="","",INDEX([1]BH!$C$2:$C$17,MATCH($D6,[1]BH!$D$2:$D$17,0))),"") -> 46142 | D6: 545332485 | E6: HF532613047 | F6: 46028 | G6: United Healthcare | H6: United Healthcare | I6: No Payer | J6: 99494 x1 | K6: =IFERROR(IF(INDEX([1]BH!$K$2:$K$17,MATCH($D6,[1]BH!$D$2:$D$17,0))="","",INDEX([1]BH!$K$2:$K$17,MATCH($D6,[1]BH!$D$2:$D$17,0))),"") -> 46122 | L6: =IF($O6="","",$O6-TODAY()) -> -186 | M6: =IF(AND(TRIM($A6)="Finalized",$K6<>""),"",IF($C6="","",$C6+180-TODAY())) -> 18 | N6: =IF(AND(TRIM($A6)="Finalized",$K6<>""),"",IF($C6="","",$C6+365-TODAY())) -> 203 | O6: =IF(AND(TRIM($A6)="Finalized",$K6<>""),"",DATE(2026,4,6)) -> 46118 | P6: 90 days | Q6: UHC COMMERCIAL | R6: 180 days | S6: Processed date | T6: 365 days | U6: Processed date | V6: 2026-01 January | W6: BH | AA6: 1 | AB6: 396.27 | AC6: 0 | AD6: 0 | AE6: 46142 | AF6: 396.27 | AG6: 214 | AH6: F4320 | AM6: MEARS, CHAD | AN6: ASAP Peoria | AO6: 46057
A7: =IFERROR(IF(INDEX([1]BH!$A$2:$A$17,MATCH($D7,[1]BH!$D$2:$D$17,0))="","",INDEX([1]BH!$A$2:$A$17,MATCH($D7,[1]BH!$D$2:$D$17,0))),"") -> Denied | B7: =IFERROR(IF(INDEX([1]BH!$B$2:$B$17,MATCH($D7,[1]BH!$D$2:$D$17,0))="","",INDEX([1]BH!$B$2:$B$17,MATCH($D7,[1]BH!$D$2:$D$17,0))),"") -> Jess uploaded MR | C7: =IFERROR(IF(INDEX([1]BH!$C$2:$C$17,MATCH($D7,[1]BH!$D$2:$D$17,0))="","",INDEX([1]BH!$C$2:$C$17,MATCH($D7,[1]BH!$D$2:$D$17,0))),"") -> 46063 | D7: 545484752 | E7: HF331360774 | F7: 46029 | G7: Blue Cross Blue Shield of Arizona (BCBS AZ) | H7: Blue Cross Blue Shield of Arizona (BCBS AZ) | I7: No Payer | J7: 99494 x1; 99492 x1 | K7: =IFERROR(IF(INDEX([1]BH!$K$2:$K$17,MATCH($D7,[1]BH!$D$2:$D$17,0))="","",INDEX([1]BH!$K$2:$K$17,MATCH($D7,[1]BH!$D$2:$D$17,0))),"") | L7: =IF($O7="","",$O7-TODAY()) -> -185 | M7: =IF(AND(TRIM($A7)="Finalized",$K7<>""),"",IF($F7="","",$F7+90-TODAY())) -> -185 | N7: =IF(AND(TRIM($A7)="Finalized",$K7<>""),"",IF($C7="","",$C7+365-TODAY())) -> 124 | O7: =IF(AND(TRIM($A7)="Finalized",$K7<>""),"",DATE(2026,4,7)) -> 46119 | P7: 90 days | Q7: BCBS | R7: 90 days | S7: Date of service | T7: 365 days | U7: Processed date | V7: 2026-01 January | W7: BH | AA7: 1 | AB7: 1426.25 | AC7: 0 | AD7: 0 | AE7: 46063 | AF7: 1426.25 | AG7: 213 | AH7: F4320 | AM7: SARKAR, AWNIK | AN7: ASAP Peoria | AO7: 46057
A8: =IFERROR(IF(INDEX([1]US!$A$2:$A$8,MATCH($D8,[1]US!$D$2:$D$8,0))="","",INDEX([1]US!$A$2:$A$8,MATCH($D8,[1]US!$D$2:$D$8,0))),"") -> Received | B8: =IFERROR(IF(INDEX([1]US!$B$2:$B$8,MATCH($D8,[1]US!$D$2:$D$8,0))="","",INDEX([1]US!$B$2:$B$8,MATCH($D8,[1]US!$D$2:$D$8,0))),"") | C8: =IFERROR(IF(INDEX([1]US!$C$2:$C$8,MATCH($D8,[1]US!$D$2:$D$8,0))="","",INDEX([1]US!$C$2:$C$8,MATCH($D8,[1]US!$D$2:$D$8,0))),"") -> 46199 | D8: 555109108 | E8: HF537320032 | F8: 46030 | G8: Humana Gold Plus HMO | H8: Humana Gold Plus HMO | I8: No Payer | J8: 93925 x1 | K8: =IFERROR(IF(INDEX([1]US!$K$2:$K$8,MATCH($D8,[1]US!$D$2:$D$8,0))="","",INDEX([1]US!$K$2:$K$8,MATCH($D8,[1]US!$D$2:$D$8,0))),"") | L8: =IF($O8="","",$O8-TODAY()) -> -184 | M8: =IF(AND(TRIM($A8)="Finalized",$K8<>""),"",IF($F8="","",$F8+90-TODAY())) -> -184 | N8: =IF(AND(TRIM($A8)="Finalized",$K8<>""),"",IF($C8="","",$C8+540-TODAY())) -> 435 | O8: =IF(AND(TRIM($A8)="Finalized",$K8<>""),"",DATE(2026,4,8)) -> 46120 | P8: 90 days | Q8: HUMANA MA | R8: 90 days | S8: Date of service | T8: 540 days | U8: Processed date | V8: 2026-01 January | W8: US | AA8: 1 | AB8: 1649.2 | AC8: 1468.48 | AD8: 291.98 | AE8: 46199 | AF8: -111.26 | AG8: 212 | AH8: I739 | AM8: TURLEY, TODD | AN8: ASAP - DEER VALLEY | AO8: 46048
A9: =IFERROR(IF(INDEX([1]US!$A$2:$A$8,MATCH($D9,[1]US!$D$2:$D$8,0))="","",INDEX([1]US!$A$2:$A$8,MATCH($D9,[1]US!$D$2:$D$8,0))),"") | B9: =IFERROR(IF(INDEX([1]US!$B$2:$B$8,MATCH($D9,[1]US!$D$2:$D$8,0))="","",INDEX([1]US!$B$2:$B$8,MATCH($D9,[1]US!$D$2:$D$8,0))),"") | C9: =IFERROR(IF(INDEX([1]US!$C$2:$C$8,MATCH($D9,[1]US!$D$2:$D$8,0))="","",INDEX([1]US!$C$2:$C$8,MATCH($D9,[1]US!$D$2:$D$8,0))),"") | D9: 557356991 | E9: HF536495012 | F9: 46030 | G9: Optum Care Medical Network of Arizona, Utah, & Washington (LifePrint) | H9: Optum Care Medical Network of Arizona, Utah, & Washington (LifePrint) | I9: No Payer | J9: 93970 x1 | K9: =IFERROR(IF(INDEX([1]US!$K$2:$K$8,MATCH($D9,[1]US!$D$2:$D$8,0))="","",INDEX([1]US!$K$2:$K$8,MATCH($D9,[1]US!$D$2:$D$8,0))),"") | L9: =IF($O9="","",$O9-TODAY()) -> -184 | M9: =IF(AND(TRIM($A9)="Finalized",$K9<>""),"",IF($C9="","",$C9+365-TODAY())) | N9: =IF(AND(TRIM($A9)="Finalized",$K9<>""),"",IF($C9="","",$C9+365-TODAY())) | O9: =IF(AND(TRIM($A9)="Finalized",$K9<>""),"",DATE(2026,4,8)) -> 46120 | P9: 90 days | Q9: OPTUM | R9: 365 days | S9: Processed date | T9: 365 days | U9: Processed date | V9: 2026-01 January | W9: US | AA9: 1 | AB9: 1294.23 | AC9: 0 | AD9: 0 | AF9: 1294.23 | AG9: 212 | AH9: R600 | AI9: M79605 | AJ9: M79604 | AM9: TURLEY, TODD | AN9: ASAP - DEER VALLEY | AO9: 46048
A10: =IFERROR(IF(INDEX([1]BH!$A$2:$A$17,MATCH($D10,[1]BH!$D$2:$D$17,0))="","",INDEX([1]BH!$A$2:$A$17,MATCH($D10,[1]BH!$D$2:$D$17,0))),"") -> Denied | B10: =IFERROR(IF(INDEX([1]BH!$B$2:$B$17,MATCH($D10,[1]BH!$D$2:$D$17,0))="","",INDEX([1]BH!$B$2:$B$17,MATCH($D10,[1]BH!$D$2:$D$17,0))),"") -> Jess uploaded MR | C10: =IFERROR(IF(INDEX([1]BH!$C$2:$C$17,MATCH($D10,[1]BH!$D$2:$D$17,0))="","",INDEX([1]BH!$C$2:$C$17,MATCH($D10,[1]BH!$D$2:$D$17,0))),"") -> 46141 | D10: 545748574 | E10: HF537684538 | F10: 46031 | G10: United Healthcare | H10: United Healthcare | I10: No Payer | J10: 99494 x1; 99492 x1 | K10: =IFERROR(IF(INDEX([1]BH!$K$2:$K$17,MATCH($D10,[1]BH!$D$2:$D$17,0))="","",INDEX([1]BH!$K$2:$K$17,MATCH($D10,[1]BH!$D$2:$D$17,0))),"") | L10: =IF($O10="","",$O10-TODAY()) -> -183 | M10: =IF(AND(TRIM($A10)="Finalized",$K10<>""),"",IF($C10="","",$C10+180-TODAY())) -> 17 | N10: =IF(AND(TRIM($A10)="Finalized",$K10<>""),"",IF($C10="","",$C10+365-TODAY())) -> 202 | O10: =IF(AND(TRIM($A10)="Finalized",$K10<>""),"",DATE(2026,4,9)) -> 46121 | P10: 90 days | Q10: UHC COMMERCIAL | R10: 180 days | S10: Processed date | T10: 365 days | U10: Processed date | V10: 2026-01 January | W10: BH | AA10: 1 | AB10: 1426.25 | AC10: 0 | AD10: 0 | AE10: 46141 | AF10: 1426.25 | AG10: 211 | AH10: F4320 | AM10: TURLEY, TODD | AN10: ASAP Peoria | AO10: 46057
A11: =IFERROR(IF(INDEX([1]ORTHO!$A$2:$A$10,MATCH($D11,[1]ORTHO!$D$2:$D$10,0))="","",INDEX([1]ORTHO!$A$2:$A$10,MATCH($D11,[1]ORTHO!$D$2:$D$10,0))),"") -> Received | B11: =IFERROR(IF(INDEX([1]ORTHO!$B$2:$B$10,MATCH($D11,[1]ORTHO!$D$2:$D$10,0))="","",INDEX([1]ORTHO!$B$2:$B$10,MATCH($D11,[1]ORTHO!$D$2:$D$10,0))),"") | C11: =IFERROR(IF(INDEX([1]ORTHO!$C$2:$C$10,MATCH($D11,[1]ORTHO!$D$2:$D$10,0))="","",INDEX([1]ORTHO!$C$2:$C$10,MATCH($D11,[1]ORTHO!$D$2:$D$10,0))),"") -> 46112 | D11: 545934422 | E11: HF533641085 | F11: 46031 | G11: CIGNA | H11: CIGNA | I11: No Payer | J11: 63047 x1 | K11: =IFERROR(IF(INDEX([1]ORTHO!$K$2:$K$10,MATCH($D11,[1]ORTHO!$D$2:$D$10,0))="","",INDEX([1]ORTHO!$K$2:$K$10,MATCH($D11,[1]ORTHO!$D$2:$D$10,0))),"") | L11: =IF($O11="","",$O11-TODAY()) -> -183 | M11: =IF(AND(TRIM($A11)="Finalized",$K11<>""),"",IF($F11="","",$F11+90-TODAY())) -> -183 | N11: =IF(AND(TRIM($A11)="Finalized",$K11<>""),"",IF($C11="","",$C11+180-TODAY())) -> -12 | O11: =IF(AND(TRIM($A11)="Finalized",$K11<>""),"",DATE(2026,4,9)) -> 46121 | P11: 90 days | Q11: CIGNA / CIGNA MEDICARE | R11: 90 days | S11: Date of service | T11: 180 days | U11: Processed date | V11: 2026-01 January | W11: ORTHO | AA11: 1 | AB11: 7623.07 | AC11: 0 | AD11: 0 | AE11: 46112 | AF11: 7623.07 | AG11: 211 | AH11: M48062 | AM11: O'NEIL, ROY | AN11: ASAP Surgery Centers North Valley LLC | AO11: 46037
A12: =IFERROR(IF(INDEX([1]ORTHO!$A$2:$A$10,MATCH($D12,[1]ORTHO!$D$2:$D$10,0))="","",INDEX([1]ORTHO!$A$2:$A$10,MATCH($D12,[1]ORTHO!$D$2:$D$10,0))),"") -> Finalized | B12: =IFERROR(IF(INDEX([1]ORTHO!$B$2:$B$10,MATCH($D12,[1]ORTHO!$D$2:$D$10,0))="","",INDEX([1]ORTHO!$B$2:$B$10,MATCH($D12,[1]ORTHO!$D$2:$D$10,0))),"") | C12: =IFERROR(IF(INDEX([1]ORTHO!$C$2:$C$10,MATCH($D12,[1]ORTHO!$D$2:$D$10,0))="","",INDEX([1]ORTHO!$C$2:$C$10,MATCH($D12,[1]ORTHO!$D$2:$D$10,0))),"") -> 46156 | D12: 545934840 | E12: HF456567442 | F12: 46031 | G12: UnitedHealthcare Community Plan / Arizona Long Term Care | H12: United Healthcare | I12: UnitedHealthcare Community Plan / Arizona Long Term Care | J12: 63685 x1 | K12: =IFERROR(IF(INDEX([1]ORTHO!$K$2:$K$10,MATCH($D12,[1]ORTHO!$D$2:$D$10,0))="","",INDEX([1]ORTHO!$K$2:$K$10,MATCH($D12,[1]ORTHO!$D$2:$D$10,0))),"") | L12: =IF($O12="","",$O12-TODAY()) -> -183 | M12: =IF(AND(TRIM($A12)="Finalized",$K12<>""),"",IF($C12="","",$C12+180-TODAY())) -> 32 | N12: =IF(AND(TRIM($A12)="Finalized",$K12<>""),"",IF($C12="","",$C12+365-TODAY())) -> 217 | O12: =IF(AND(TRIM($A12)="Finalized",$K12<>""),"",DATE(2026,4,9)) -> 46121 | P12: 90 days | Q12: UHC COMMERCIAL | R12: 180 days | S12: Processed date | T12: 365 days | U12: Processed date | V12: 2026-01 January | W12: ORTHO | AA12: 1 | AB12: 2493.33 | AC12: 2322.61 | AD12: 18.5 | AE12: 46156 | AF12: 152.22 | AG12: 211 | AH12: G90523 | AL12: 556916920 | AM12: O'NEIL, ROY | AN12: ASAP Surgery Centers North Valley LLC | AO12: 46037
A13: =IFERROR(IF(INDEX([1]ORTHO!$A$2:$A$10,MATCH($D13,[1]ORTHO!$D$2:$D$10,0))="","",INDEX([1]ORTHO!$A$2:$A$10,MATCH($D13,[1]ORTHO!$D$2:$D$10,0))),"") | B13: =IFERROR(IF(INDEX([1]ORTHO!$B$2:$B$10,MATCH($D13,[1]ORTHO!$D$2:$D$10,0))="","",INDEX([1]ORTHO!$B$2:$B$10,MATCH($D13,[1]ORTHO!$D$2:$D$10,0))),"") | C13: =IFERROR(IF(INDEX([1]ORTHO!$C$2:$C$10,MATCH($D13,[1]ORTHO!$D$2:$D$10,0))="","",INDEX([1]ORTHO!$C$2:$C$10,MATCH($D13,[1]ORTHO!$D$2:$D$10,0))),"") -> 46045 | D13: 546049607 | E13: HF491900072 | F13: 46035 | G13: UnitedHealthcare Community Plan / Arizona Long Term Care | H13: UnitedHealthcare Community Plan / Arizona Long Term Care | I13: No Payer | J13: 63047+LT x1 | K13: =IFERROR(IF(INDEX([1]ORTHO!$K$2:$K$10,MATCH($D13,[1]ORTHO!$D$2:$D$10,0))="","",INDEX([1]ORTHO!$K$2:$K$10,MATCH($D13,[1]ORTHO!$D$2:$D$10,0))),"") | L13: =IF($O13="","",$O13-TODAY()) -> -179 | M13: =IF(AND(TRIM($A13)="Finalized",$K13<>""),"",IF($C13="","",$C13+180-TODAY())) -> -79 | N13: =IF(AND(TRIM($A13)="Finalized",$K13<>""),"",IF($C13="","",$C13+365-TODAY())) -> 106 | O13: =IF(AND(TRIM($A13)="Finalized",$K13<>""),"",DATE(2026,4,13)) -> 46125 | P13: 90 days | Q13: UHC COMMUNITY | R13: 180 days | S13: Processed date | T13: 365 days | U13: Processed date | V13: 2026-01 January | W13: ORTHO | X13: LT | AA13: 1 | AB13: 7623.07 | AC13: 0 | AD13: 0 | AE13: 46045 | AF13: 7623.07 | AG13: 207 | AH13: M48062 | AM13: KRAUSE, JEFFREY | AN13: ASAP Surgery Centers North Valley LLC | AO13: 46037
A14: =IFERROR(IF(INDEX([1]US!$A$2:$A$8,MATCH($D14,[1]US!$D$2:$D$8,0))="","",INDEX([1]US!$A$2:$A$8,MATCH($D14,[1]US!$D$2:$D$8,0))),"") -> Received | B14: =IFERROR(IF(INDEX([1]US!$B$2:$B$8,MATCH($D14,[1]US!$D$2:$D$8,0))="","",INDEX([1]US!$B$2:$B$8,MATCH($D14,[1]US!$D$2:$D$8,0))),"") | C14: =IFERROR(IF(INDEX([1]US!$C$2:$C$8,MATCH($D14,[1]US!$D$2:$D$8,0))="","",INDEX([1]US!$C$2:$C$8,MATCH($D14,[1]US!$D$2:$D$8,0))),"") -> 46069 | D14: 548717876 | E14: HF442148430 | F14: 46035 | G14: Cigna Medicare Advantage | H14: Cigna Medicare Advantage | I14: No Payer | J14: 93925 x1 | K14: =IFERROR(IF(INDEX([1]US!$K$2:$K$8,MATCH($D14,[1]US!$D$2:$D$8,0))="","",INDEX([1]US!$K$2:$K$8,MATCH($D14,[1]US!$D$2:$D$8,0))),"") | L14: =IF($O14="","",$O14-TODAY()) -> -179 | M14: =IF(AND(TRIM($A14)="Finalized",$K14<>""),"",IF($F14="","",$F14+90-TODAY())) -> -179 | N14: =IF(AND(TRIM($A14)="Finalized",$K14<>""),"",IF($C14="","",$C14+180-TODAY())) -> -55 | O14: =IF(AND(TRIM($A14)="Finalized",$K14<>""),"",DATE(2026,4,13)) -> 46125 | P14: 90 days | Q14: CIGNA / CIGNA MEDICARE | R14: 90 days | S14: Date of service | T14: 180 days | U14: Processed date | V14: 2026-01 January | W14: US | AA14: 1 | AB14: 1649.2 | AC14: 1478.03 | AD14: 390.24 | AE14: 46069 | AF14: -219.07 | AG14: 207 | AH14: I739 | AM14: LEATHEM, JARRETT | AN14: ASAP - Gilbert | AO14: 46051
A15: =IFERROR(IF(INDEX([1]BH!$A$2:$A$17,MATCH($D15,[1]BH!$D$2:$D$17,0))="","",INDEX([1]BH!$A$2:$A$17,MATCH($D15,[1]BH!$D$2:$D$17,0))),"") -> Denied | B15: =IFERROR(IF(INDEX([1]BH!$B$2:$B$17,MATCH($D15,[1]BH!$D$2:$D$17,0))="","",INDEX([1]BH!$B$2:$B$17,MATCH($D15,[1]BH!$D$2:$D$17,0))),"") -> Added Date of Current Illness, claim note, and resubmitted | C15: =IFERROR(IF(INDEX([1]BH!$C$2:$C$17,MATCH($D15,[1]BH!$D$2:$D$17,0))="","",INDEX([1]BH!$C$2:$C$17,MATCH($D15,[1]BH!$D$2:$D$17,0))),"") -> 46133 | D15: 556348109 | E15: HF434792716 | F15: 46036 | G15: Optum Care Medical Network of Arizona, Utah, & Washington (LifePrint) | H15: Optum Care Medical Network of Arizona, Utah, & Washington (LifePrint) | I15: No Payer | J15: 99493 x1 | K15: =IFERROR(IF(INDEX([1]BH!$K$2:$K$17,MATCH($D15,[1]BH!$D$2:$D$17,0))="","",INDEX([1]BH!$K$2:$K$17,MATCH($D15,[1]BH!$D$2:$D$17,0))),"") -> 46129 | L15: =IF($O15="","",$O15-TODAY()) -> -178 | M15: =IF(AND(TRIM($A15)="Finalized",$K15<>""),"",IF($C15="","",$C15+365-TODAY())) -> 194 | N15: =IF(AND(TRIM($A15)="Finalized",$K15<>""),"",IF($C15="","",$C15+365-TODAY())) -> 194 | O15: =IF(AND(TRIM($A15)="Finalized",$K15<>""),"",DATE(2026,4,14)) -> 46126 | P15: 90 days | Q15: OPTUM | R15: 365 days | S15: Processed date | T15: 365 days | U15: Processed date | V15: 2026-01 January | W15: BH | AA15: 1 | AB15: 976.64 | AC15: 0 | AD15: 0 | AE15: 46133 | AF15: 976.64 | AG15: 206 | AH15: F1190 | AM15: LEATHEM, JARRETT | AN15: ASAP - Gilbert | AO15: 46057
A16: =IFERROR(IF(INDEX([1]US!$A$2:$A$8,MATCH($D16,[1]US!$D$2:$D$8,0))="","",INDEX([1]US!$A$2:$A$8,MATCH($D16,[1]US!$D$2:$D$8,0))),"") -> Received | B16: =IFERROR(IF(INDEX([1]US!$B$2:$B$8,MATCH($D16,[1]US!$D$2:$D$8,0))="","",INDEX([1]US!$B$2:$B$8,MATCH($D16,[1]US!$D$2:$D$8,0))),"") | C16: =IFERROR(IF(INDEX([1]US!$C$2:$C$8,MATCH($D16,[1]US!$D$2:$D$8,0))="","",INDEX([1]US!$C$2:$C$8,MATCH($D16,[1]US!$D$2:$D$8,0))),"") -> 46160 | D16: 547451314 | E16: HF494223308 | F16: 46036 | G16: Cigna Medicare Advantage | H16: Cigna Medicare Advantage | I16: No Payer | J16: 93925 x1 | K16: =IFERROR(IF(INDEX([1]US!$K$2:$K$8,MATCH($D16,[1]US!$D$2:$D$8,0))="","",INDEX([1]US!$K$2:$K$8,MATCH($D16,[1]US!$D$2:$D$8,0))),"") | L16: =IF($O16="","",$O16-TODAY()) -> -178 | M16: =IF(AND(TRIM($A16)="Finalized",$K16<>""),"",IF($F16="","",$F16+90-TODAY())) -> -178 | N16: =IF(AND(TRIM($A16)="Finalized",$K16<>""),"",IF($C16="","",$C16+180-TODAY())) -> 36 | O16: =IF(AND(TRIM($A16)="Finalized",$K16<>""),"",DATE(2026,4,14)) -> 46126 | P16: 90 days | Q16: CIGNA / CIGNA MEDICARE | R16: 90 days | S16: Date of service | T16: 180 days | U16: Processed date | V16: 2026-01 January | W16: US | AA16: 1 | AB16: 1649.2 | AC16: -227.03 | AD16: 227.03 | AE16: 46160 | AF16: 1649.2 | AG16: 206 | AH16: M79604 | AI16: M79605 | AJ16: M25551 | AK16: M25552 | AM16: BURGHER, ABRAM | AN16: ASAP - Surprise - Reems | AO16: 46048
A17: =IFERROR(IF(INDEX([1]ORTHO!$A$2:$A$10,MATCH($D17,[1]ORTHO!$D$2:$D$10,0))="","",INDEX([1]ORTHO!$A$2:$A$10,MATCH($D17,[1]ORTHO!$D$2:$D$10,0))),"") | B17: =IFERROR(IF(INDEX([1]ORTHO!$B$2:$B$10,MATCH($D17,[1]ORTHO!$D$2:$D$10,0))="","",INDEX([1]ORTHO!$B$2:$B$10,MATCH($D17,[1]ORTHO!$D$2:$D$10,0))),"") | C17: =IFERROR(IF(INDEX([1]ORTHO!$C$2:$C$10,MATCH($D17,[1]ORTHO!$D$2:$D$10,0))="","",INDEX([1]ORTHO!$C$2:$C$10,MATCH($D17,[1]ORTHO!$D$2:$D$10,0))),"") | D17: 548591390 | E17: HF383758253 | F17: 46036 | G17: Blue Cross Blue Shield of Arizona (BCBS AZ) | H17: Blue Cross Blue Shield of Arizona (BCBS AZ) | I17: No Payer | J17: 63047 x1 | K17: =IFERROR(IF(INDEX([1]ORTHO!$K$2:$K$10,MATCH($D17,[1]ORTHO!$D$2:$D$10,0))="","",INDEX([1]ORTHO!$K$2:$K$10,MATCH($D17,[1]ORTHO!$D$2:$D$10,0))),"") | L17: =IF($O17="","",$O17-TODAY()) -> -178 | M17: =IF(AND(TRIM($A17)="Finalized",$K17<>""),"",IF($F17="","",$F17+90-TODAY())) -> -178 | N17: =IF(AND(TRIM($A17)="Finalized",$K17<>""),"",IF($C17="","",$C17+365-TODAY())) | O17: =IF(AND(TRIM($A17)="Finalized",$K17<>""),"",DATE(2026,4,14)) -> 46126 | P17: 90 days | Q17: BCBS | R17: 90 days | S17: Date of service | T17: 365 days | U17: Processed date | V17: 2026-01 January | W17: ORTHO | AA17: 1 | AB17: 7623.07 | AC17: 0 | AD17: 0 | AF17: 7623.07 | AG17: 206 | AH17: M48061 | AI17: M5416 | AM17: MAYURAN, VIKRAM | AN17: ASAP Surgery Centers North Valley LLC | AO17: 46042
A18: =IFERROR(IF(INDEX([1]US!$A$2:$A$8,MATCH($D18,[1]US!$D$2:$D$8,0))="","",INDEX([1]US!$A$2:$A$8,MATCH($D18,[1]US!$D$2:$D$8,0))),"") | B18: =IFERROR(IF(INDEX([1]US!$B$2:$B$8,MATCH($D18,[1]US!$D$2:$D$8,0))="","",INDEX([1]US!$B$2:$B$8,MATCH($D18,[1]US!$D$2:$D$8,0))),"") | C18: =IFERROR(IF(INDEX([1]US!$C$2:$C$8,MATCH($D18,[1]US!$D$2:$D$8,0))="","",INDEX([1]US!$C$2:$C$8,MATCH($D18,[1]US!$D$2:$D$8,0))),"") -> 46163 | D18: 547465291 | E18: HF526889546 | F18: 46037 | G18: United Healthcare | H18: United Healthcare | I18: No Payer | J18: 93970 x1 | K18: =IFERROR(IF(INDEX([1]US!$K$2:$K$8,MATCH($D18,[1]US!$D$2:$D$8,0))="","",INDEX([1]US!$K$2:$K$8,MATCH($D18,[1]US!$D$2:$D$8,0))),"") | L18: =IF($O18="","",$O18-TODAY()) -> -177 | M18: =IF(AND(TRIM($A18)="Finalized",$K18<>""),"",IF($C18="","",$C18+180-TODAY())) -> 39 | N18: =IF(AND(TRIM($A18)="Finalized",$K18<>""),"",IF($C18="","",$C18+365-TODAY())) -> 224 | O18: =IF(AND(TRIM($A18)="Finalized",$K18<>""),"",DATE(2026,4,15)) -> 46127 | P18: 90 days | Q18: UHC COMMERCIAL | R18: 180 days | S18: Processed date | T18: 365 days | U18: Processed date | V18: 2026-01 January | W18: US | AA18: 1 | AB18: 1294.23 | AC18: 0 | AD18: 0 | AE18: 46163 | AF18: 1294.23 | AG18: 205 | AH18: R600 | AI18: M5416 | AM18: TURLEY, TODD | AN18: ASAP - DEER VALLEY | AO18: 46048
A19: =IFERROR(IF(INDEX([1]BH!$A$2:$A$17,MATCH($D19,[1]BH!$D$2:$D$17,0))="","",INDEX([1]BH!$A$2:$A$17,MATCH($D19,[1]BH!$D$2:$D$17,0))),"") -> Denied | B19: =IFERROR(IF(INDEX([1]BH!$B$2:$B$17,MATCH($D19,[1]BH!$D$2:$D$17,0))="","",INDEX([1]BH!$B$2:$B$17,MATCH($D19,[1]BH!$D$2:$D$17,0))),"") -> Under review - TAT 15 days - Ref # 10605826 - Rep Muthamma | C19: =IFERROR(IF(INDEX([1]BH!$C$2:$C$17,MATCH($D19,[1]BH!$D$2:$D$17,0))="","",INDEX([1]BH!$C$2:$C$17,MATCH($D19,[1]BH!$D$2:$D$17,0))),"") -> 46064 | D19: 548015539 | E19: HF537685966 | F19: 46043 | G19: Blue Cross Blue Shield of Arizona (BCBS AZ) | H19: Blue Cross Blue Shield of Arizona (BCBS AZ) | I19: Medicare Part B Arizona * | J19: 99494 x1; 99492 x1 | K19: =IFERROR(IF(INDEX([1]BH!$K$2:$K$17,MATCH($D19,[1]BH!$D$2:$D$17,0))="","",INDEX([1]BH!$K$2:$K$17,MATCH($D19,[1]BH!$D$2:$D$17,0))),"") -> 46134 | L19: =IF($O19="","",$O19-TODAY()) -> -171 | M19: =IF(AND(TRIM($A19)="Finalized",$K19<>""),"",IF($F19="","",$F19+90-TODAY())) -> -171 | N19: =IF(AND(TRIM($A19)="Finalized",$K19<>""),"",IF($C19="","",$C19+365-TODAY())) -> 125 | O19: =IF(AND(TRIM($A19)="Finalized",$K19<>""),"",DATE(2026,4,21)) -> 46133 | P19: 90 days | Q19: BCBS | R19: 90 days | S19: Date of service | T19: 365 days | U19: Processed date | V19: 2026-01 January | W19: BH | AA19: 1 | AB19: 1426.25 | AC19: 0 | AD19: 0 | AE19: 46064 | AF19: 1426.25 | AG19: 199 | AH19: F330 | AM19: LEATHEM, JARRETT | AN19: ASAP - Gilbert | AO19: 46057
A20: =IFERROR(IF(INDEX([1]US!$A$2:$A$8,MATCH($D20,[1]US!$D$2:$D$8,0))="","",INDEX([1]US!$A$2:$A$8,MATCH($D20,[1]US!$D$2:$D$8,0))),"") -> Received | B20: =IFERROR(IF(INDEX([1]US!$B$2:$B$8,MATCH($D20,[1]US!$D$2:$D$8,0))="","",INDEX([1]US!$B$2:$B$8,MATCH($D20,[1]US!$D$2:$D$8,0))),"") | C20: =IFERROR(IF(INDEX([1]US!$C$2:$C$8,MATCH($D20,[1]US!$D$2:$D$8,0))="","",INDEX([1]US!$C$2:$C$8,MATCH($D20,[1]US!$D$2:$D$8,0))),"") -> 46160 | D20: 547481511 | E20: HF513229920 | F20: 46043 | G20: HealthSpring Medicare Advantage | H20: HealthSpring Medicare Advantage | I20: No Payer | J20: 93970 x1 | K20: =IFERROR(IF(INDEX([1]US!$K$2:$K$8,MATCH($D20,[1]US!$D$2:$D$8,0))="","",INDEX([1]US!$K$2:$K$8,MATCH($D20,[1]US!$D$2:$D$8,0))),"") | L20: =IF($O20="","",$O20-TODAY()) -> -171 | M20: =IF(AND(TRIM($A20)="Finalized",$K20<>""),"",IF($F20="","",$F20+90-TODAY())) -> -171 | N20: =IF(AND(TRIM($A20)="Finalized",$K20<>""),"",IF($C20="","",$C20+180-TODAY())) -> 36 | O20: =IF(AND(TRIM($A20)="Finalized",$K20<>""),"",DATE(2026,4,21)) -> 46133 | P20: 90 days | Q20: CIGNA / CIGNA MEDICARE | R20: 90 days | S20: Date of service | T20: 180 days | U20: Processed date | V20: 2026-01 January | W20: US | AA20: 1 | AB20: 1294.23 | AC20: -176 | AD20: 176 | AE20: 46160 | AF20: 1294.23 | AG20: 199 | AH20: I872 | AI20: I83812 | AM20: BURGHER, ABRAM | AN20: ASAP - Surprise - Reems | AO20: 46048
A21: =IFERROR(IF(INDEX([1]BH!$A$2:$A$17,MATCH($D21,[1]BH!$D$2:$D$17,0))="","",INDEX([1]BH!$A$2:$A$17,MATCH($D21,[1]BH!$D$2:$D$17,0))),"") -> Pending | B21: =IFERROR(IF(INDEX([1]BH!$B$2:$B$17,MATCH($D21,[1]BH!$D$2:$D$17,0))="","",INDEX([1]BH!$B$2:$B$17,MATCH($D21,[1]BH!$D$2:$D$17,0))),"") -> secondary - Resubmitted to AmeTrust | C21: =IFERROR(IF(INDEX([1]BH!$C$2:$C$17,MATCH($D21,[1]BH!$D$2:$D$17,0))="","",INDEX([1]BH!$C$2:$C$17,MATCH($D21,[1]BH!$D$2:$D$17,0))),"") -> 46094 | D21: 547442681 | E21: HF359780591 | F21: 46044 | G21: TRIADA GAP BENEFITS | H21: Blue Cross Blue Shield of Arizona (BCBS AZ) | I21: TRIADA GAP BENEFITS | J21: 99493 x1 | K21: =IFERROR(IF(INDEX([1]BH!$K$2:$K$17,MATCH($D21,[1]BH!$D$2:$D$17,0))="","",INDEX([1]BH!$K$2:$K$17,MATCH($D21,[1]BH!$D$2:$D$17,0))),"") -> 46304 | L21: =IF($O21="","",$O21-TODAY()) -> -170 | M21: =IF(AND(TRIM($A21)="Finalized",$K21<>""),"",IF($F21="","",$F21+90-TODAY())) -> -170 | N21: =IF(AND(TRIM($A21)="Finalized",$K21<>""),"",IF($C21="","",$C21+365-TODAY())) -> 155 | O21: =IF(AND(TRIM($A21)="Finalized",$K21<>""),"",DATE(2026,4,22)) -> 46134 | P21: 90 days | Q21: BCBS | R21: 90 days | S21: Date of service | T21: 365 days | U21: Processed date | V21: 2026-01 January | W21: BH | AA21: 1 | AB21: 976.64 | AC21: 840.66 | AD21: 0 | AE21: 46094 | AF21: 135.98 | AG21: 198 | AH21: F411 | AL21: 556556161 | AM21: LEATHEM, JARRETT | AN21: ASAP - DEER VALLEY | AO21: 46056
A22: =IFERROR(IF(INDEX([1]ORTHO!$A$2:$A$10,MATCH($D22,[1]ORTHO!$D$2:$D$10,0))="","",INDEX([1]ORTHO!$A$2:$A$10,MATCH($D22,[1]ORTHO!$D$2:$D$10,0))),"") -> Denied | B22: =IFERROR(IF(INDEX([1]ORTHO!$B$2:$B$10,MATCH($D22,[1]ORTHO!$D$2:$D$10,0))="","",INDEX([1]ORTHO!$B$2:$B$10,MATCH($D22,[1]ORTHO!$D$2:$D$10,0))),"") | C22: =IFERROR(IF(INDEX([1]ORTHO!$C$2:$C$10,MATCH($D22,[1]ORTHO!$D$2:$D$10,0))="","",INDEX([1]ORTHO!$C$2:$C$10,MATCH($D22,[1]ORTHO!$D$2:$D$10,0))),"") -> 46163 | D22: 547275123 | E22: HF470511781 | F22: 46045 | G22: United Healthcare | H22: Blue Cross Blue Shield of Arizona (BCBS AZ) | I22: United Healthcare | J22: 27279+LT x1 | K22: =IFERROR(IF(INDEX([1]ORTHO!$K$2:$K$10,MATCH($D22,[1]ORTHO!$D$2:$D$10,0))="","",INDEX([1]ORTHO!$K$2:$K$10,MATCH($D22,[1]ORTHO!$D$2:$D$10,0))),"") | L22: =IF($O22="","",$O22-TODAY()) -> -169 | M22: =IF(AND(TRIM($A22)="Finalized",$K22<>""),"",IF($F22="","",$F22+90-TODAY())) -> -169 | N22: =IF(AND(TRIM($A22)="Finalized",$K22<>""),"",IF($C22="","",$C22+365-TODAY())) -> 224 | O22: =IF(AND(TRIM($A22)="Finalized",$K22<>""),"",DATE(2026,4,23)) -> 46135 | P22: 90 days | Q22: BCBS | R22: 90 days | S22: Date of service | T22: 365 days | U22: Processed date | V22: 2026-01 January | W22: ORTHO | X22: LT | AA22: 1 | AB22: 5614.63 | AC22: -186.91 | AD22: 0 | AE22: 46163 | AF22: 5614.63 | AG22: 197 | AH22: M461 | AL22: 549237390 | AM22: LEATHEM, JARRETT | AN22: Premier Endoscopy Center, LLC | AO22: 46049
A23: =IFERROR(IF(INDEX([1]ORTHO!$A$2:$A$10,MATCH($D23,[1]ORTHO!$D$2:$D$10,0))="","",INDEX([1]ORTHO!$A$2:$A$10,MATCH($D23,[1]ORTHO!$D$2:$D$10,0))),"") -> Denied | B23: =IFERROR(IF(INDEX([1]ORTHO!$B$2:$B$10,MATCH($D23,[1]ORTHO!$D$2:$D$10,0))="","",INDEX([1]ORTHO!$B$2:$B$10,MATCH($D23,[1]ORTHO!$D$2:$D$10,0))),"") -> On it | C23: =IFERROR(IF(INDEX([1]ORTHO!$C$2:$C$10,MATCH($D23,[1]ORTHO!$D$2:$D$10,0))="","",INDEX([1]ORTHO!$C$2:$C$10,MATCH($D23,[1]ORTHO!$D$2:$D$10,0))),"") -> 46052 | D23: 547576017 | E23: HF524606724 | F23: 46045 | G23: Blue Cross Blue Shield of Arizona (BCBS AZ) | H23: Blue Cross Blue Shield of Arizona (BCBS AZ) | I23: No Payer | J23: 63047 x1 | K23: =IFERROR(IF(INDEX([1]ORTHO!$K$2:$K$10,MATCH($D23,[1]ORTHO!$D$2:$D$10,0))="","",INDEX([1]ORTHO!$K$2:$K$10,MATCH($D23,[1]ORTHO!$D$2:$D$10,0))),"") | L23: =IF($O23="","",$O23-TODAY()) -> -169 | M23: =IF(AND(TRIM($A23)="Finalized",$K23<>""),"",IF($F23="","",$F23+90-TODAY())) -> -169 | N23: =IF(AND(TRIM($A23)="Finalized",$K23<>""),"",IF($C23="","",$C23+365-TODAY())) -> 113 | O23: =IF(AND(TRIM($A23)="Finalized",$K23<>""),"",DATE(2026,4,23)) -> 46135 | P23: 90 days | Q23: BCBS | R23: 90 days | S23: Date of service | T23: 365 days | U23: Processed date | V23: 2026-01 January | W23: ORTHO | AA23: 1 | AB23: 7623.07 | AC23: 0 | AD23: 0 | AE23: 46052 | AF23: 7623.07 | AG23: 197 | AH23: M48062 | AM23: O'NEIL, ROY | AN23: ASAP Surgery Centers North Valley LLC | AO23: 46049
A24: =IFERROR(IF(INDEX([1]DME!$A$2:$A$8,MATCH($D24,[1]DME!$D$2:$D$8,0))="","",INDEX([1]DME!$A$2:$A$8,MATCH($D24,[1]DME!$D$2:$D$8,0))),"") -> Pending | B24: =IFERROR(IF(INDEX([1]DME!$B$2:$B$8,MATCH($D24,[1]DME!$D$2:$D$8,0))="","",INDEX([1]DME!$B$2:$B$8,MATCH($D24,[1]DME!$D$2:$D$8,0))),"") -> secondary - I need to crossover claim - Edited charges for A6219, and resubmitted | C24: =IFERROR(IF(INDEX([1]DME!$C$2:$C$8,MATCH($D24,[1]DME!$D$2:$D$8,0))="","",INDEX([1]DME!$C$2:$C$8,MATCH($D24,[1]DME!$D$2:$D$8,0))),"") -> 46156 | D24: 557162806 | E24: HF518924824 | F24: 46041 | G24: Mercy Care Plan (AHCCCS) - Complete Care & Long Term Care (LTC) | H24: Allwell - All States (Centene) | I24: Mercy Care Plan (AHCCCS) - Complete Care & Long Term Care (LTC) | J24: A6023+A2 x10 | K24: =IFERROR(IF(INDEX([1]DME!$K$2:$K$8,MATCH($D24,[1]DME!$D$2:$D$8,0))="","",INDEX([1]DME!$K$2:$K$8,MATCH($D24,[1]DME!$D$2:$D$8,0))),"") -> 46136 | L24: =IF($O24="","",$O24-TODAY()) -> -168 | M24: =IF(AND(TRIM($A24)="Finalized",$K24<>""),"",IF($C24="","",$C24+90-TODAY())) -> -58 | N24: =IF(AND(TRIM($A24)="Finalized",$K24<>""),"",IF($C24="","",$C24+90-TODAY())) -> -58 | O24: =IF(AND(TRIM($A24)="Finalized",$K24<>""),"",DATE(2026,4,24)) -> 46136 | P24: 95 days | Q24: WELLCARE BY ALLWELL | R24: 90 days | S24: Processed date | T24: 90 days | U24: Processed date | V24: 2026-01 January | W24: DME | X24: A2 | AA24: 10 | AB24: 18176.9 | AC24: 16142.75 | AD24: 1627.48 | AE24: 46156 | AF24: 406.67 | AG24: 201 | AH24: G894 | AI24: M961 | AJ24: M5416 | AL24: 551367817 | AM24: KALLGREN, MARK | AN24: ASAP - Mesa | AO24: 46063
A25: =IFERROR(IF(INDEX([1]GAE!$A$2:$A$12,MATCH($D25,[1]GAE!$D$2:$D$12,0))="","",INDEX([1]GAE!$A$2:$A$12,MATCH($D25,[1]GAE!$D$2:$D$12,0))),"") | B25: =IFERROR(IF(INDEX([1]GAE!$B$2:$B$12,MATCH($D25,[1]GAE!$D$2:$D$12,0))="","",INDEX([1]GAE!$B$2:$B$12,MATCH($D25,[1]GAE!$D$2:$D$12,0))),"") | C25: =IFERROR(IF(INDEX([1]GAE!$C$2:$C$12,MATCH($D25,[1]GAE!$D$2:$D$12,0))="","",INDEX([1]GAE!$C$2:$C$12,MATCH($D25,[1]GAE!$D$2:$D$12,0))),"") -> 46111 | D25: 552170540 | E25: HF505789977 | F25: 46048 | G25: Humana Gold Plus HMO | H25: Humana Gold Plus HMO | I25: No Payer | J25: 37242 x1; 36245+59 x1; 36248+59 x1; 36246+59+RT x1 | K25: =IFERROR(IF(INDEX([1]GAE!$K$2:$K$12,MATCH($D25,[1]GAE!$D$2:$D$12,0))="","",INDEX([1]GAE!$K$2:$K$12,MATCH($D25,[1]GAE!$D$2:$D$12,0))),"") | L25: =IF($O25="","",$O25-TODAY()) -> -166 | M25: =IF(AND(TRIM($A25)="Finalized",$K25<>""),"",IF($F25="","",$F25+90-TODAY())) -> -166 | N25: =IF(AND(TRIM($A25)="Finalized",$K25<>""),"",IF($C25="","",$C25+540-TODAY())) -> 347 | O25: =IF(AND(TRIM($A25)="Finalized",$K25<>""),"",DATE(2026,4,26)) -> 46138 | P25: 90 days | Q25: HUMANA MA | R25: 90 days | S25: Date of service | T25: 540 days | U25: Processed date | V25: 2026-01 January | W25: GAE | X25: 59 | Y25: RT | AA25: 1 | AB25: 64277.64 | AC25: 0 | AD25: 0 | AE25: 46111 | AF25: 64277.64 | AG25: 194 | AH25: M1711 | AI25: I798 | AJ25: M25561 | AM25: HUNTER, DREW | AN25: ASAP Surgery Centers North Valley LLC | AO25: 46062
A26: =IFERROR(IF(INDEX([1]BH!$A$2:$A$17,MATCH($D26,[1]BH!$D$2:$D$17,0))="","",INDEX([1]BH!$A$2:$A$17,MATCH($D26,[1]BH!$D$2:$D$17,0))),"") -> Received | B26: =IFERROR(IF(INDEX([1]BH!$B$2:$B$17,MATCH($D26,[1]BH!$D$2:$D$17,0))="","",INDEX([1]BH!$B$2:$B$17,MATCH($D26,[1]BH!$D$2:$D$17,0))),"") -> Resubmitted - no changes | C26: =IFERROR(IF(INDEX([1]BH!$C$2:$C$17,MATCH($D26,[1]BH!$D$2:$D$17,0))="","",INDEX([1]BH!$C$2:$C$17,MATCH($D26,[1]BH!$D$2:$D$17,0))),"") -> 46128 | D26: 555599776 | E26: HF475536429 | F26: 46049 | G26: Blue Cross Blue Shield of Arizona (BCBS AZ) | H26: Blue Cross Blue Shield of Arizona (BCBS AZ) | I26: No Payer | J26: 99492 x1; 99494 x1 | K26: =IFERROR(IF(INDEX([1]BH!$K$2:$K$17,MATCH($D26,[1]BH!$D$2:$D$17,0))="","",INDEX([1]BH!$K$2:$K$17,MATCH($D26,[1]BH!$D$2:$D$17,0))),"") -> 46122 | L26: =IF($O26="","",$O26-TODAY()) -> -165 | M26: =IF(AND(TRIM($A26)="Finalized",$K26<>""),"",IF($F26="","",$F26+90-TODAY())) -> -165 | N26: =IF(AND(TRIM($A26)="Finalized",$K26<>""),"",IF($C26="","",$C26+365-TODAY())) -> 189 | O26: =IF(AND(TRIM($A26)="Finalized",$K26<>""),"",DATE(2026,4,27)) -> 46139 | P26: 90 days | Q26: BCBS | R26: 90 days | S26: Date of service | T26: 365 days | U26: Processed date | V26: 2026-01 January | W26: BH | AA26: 1 | AB26: 1426.25 | AC26: 0 | AD26: 0 | AE26: 46128 | AF26: 1426.25 | AG26: 193 | AH26: F4320 | AM26: O'NEIL, ROY | AN26: ASAP Peoria | AO26: 46057
A27: =IFERROR(IF(INDEX([1]BH!$A$2:$A$17,MATCH($D27,[1]BH!$D$2:$D$17,0))="","",INDEX([1]BH!$A$2:$A$17,MATCH($D27,[1]BH!$D$2:$D$17,0))),"") -> Denied | B27: =IFERROR(IF(INDEX([1]BH!$B$2:$B$17,MATCH($D27,[1]BH!$D$2:$D$17,0))="","",INDEX([1]BH!$B$2:$B$17,MATCH($D27,[1]BH!$D$2:$D$17,0))),"") -> Resubmitted with 99492 - Recon filed - Request ID TT2647830 - Claim 26A635462200 DOS 01/27/26 99493 denied no prior CoCM 6mo. Prior 99493 DOS 12/16/25 paid clm 26A070631100 under old ID 2062477. Req reprocess; PRA attached - DND 99493 This non-payable code is for required reporting only - Added Date of Current Illness, claim note, and resubmitted | C27: =IFERROR(IF(INDEX([1]BH!$C$2:$C$17,MATCH($D27,[1]BH!$D$2:$D$17,0))="","",INDEX([1]BH!$C$2:$C$17,MATCH($D27,[1]BH!$D$2:$D$17,0))),"") -> 46287 | D27: 556349314 | E27: HF431164004 | F27: 46049 | G27: Optum Care Medical Network of Arizona, Utah, & Washington (LifePrint) | H27: Optum Care Medical Network of Arizona, Utah, & Washington (LifePrint) | I27: No Payer | J27: 99493 x1 | K27: =IFERROR(IF(INDEX([1]BH!$K$2:$K$17,MATCH($D27,[1]BH!$D$2:$D$17,0))="","",INDEX([1]BH!$K$2:$K$17,MATCH($D27,[1]BH!$D$2:$D$17,0))),"") -> 46300 | L27: =IF($O27="","",$O27-TODAY()) -> -165 | M27: =IF(AND(TRIM($A27)="Finalized",$K27<>""),"",IF($C27="","",$C27+365-TODAY())) -> 348 | N27: =IF(AND(TRIM($A27)="Finalized",$K27<>""),"",IF($C27="","",$C27+365-TODAY())) -> 348 | O27: =IF(AND(TRIM($A27)="Finalized",$K27<>""),"",DATE(2026,4,27)) -> 46139 | P27: 90 days | Q27: OPTUM | R27: 365 days | S27: Processed date | T27: 365 days | U27: Processed date | V27: 2026-01 January | W27: BH | AA27: 1 | AB27: 976.64 | AC27: 0 | AD27: 0 | AE27: 46133 | AF27: 976.64 | AG27: 193 | AH27: F331 | AI27: F411 | AM27: O'NEIL, ROY | AN27: ASAP - Goodyear | AO27: 46056
A28: =IFERROR(IF(INDEX([1]BH!$A$2:$A$17,MATCH($D28,[1]BH!$D$2:$D$17,0))="","",INDEX([1]BH!$A$2:$A$17,MATCH($D28,[1]BH!$D$2:$D$17,0))),"") -> Pending | B28: =IFERROR(IF(INDEX([1]BH!$B$2:$B$17,MATCH($D28,[1]BH!$D$2:$D$17,0))="","",INDEX([1]BH!$B$2:$B$17,MATCH($D28,[1]BH!$D$2:$D$17,0))),"") -> Not shifting - working on it Shifted to PR - Ins didn't receive PT update - I talked to PT on the phone, she said she will contact the insurance to take care of the IQ this week | C28: =IFERROR(IF(INDEX([1]BH!$C$2:$C$17,MATCH($D28,[1]BH!$D$2:$D$17,0))="","",INDEX([1]BH!$C$2:$C$17,MATCH($D28,[1]BH!$D$2:$D$17,0))),"") -> 46066 | D28: 547976909 | E28: HF535417942 | F28: 46051 | G28: Blue Cross Blue Shield of Arizona (BCBS AZ) | H28: Blue Cross Blue Shield of Arizona (BCBS AZ) | I28: LIEN 05 | J28: 99493 x1 | K28: =IFERROR(IF(INDEX([1]BH!$K$2:$K$17,MATCH($D28,[1]BH!$D$2:$D$17,0))="","",INDEX([1]BH!$K$2:$K$17,MATCH($D28,[1]BH!$D$2:$D$17,0))),"") -> 46245 | L28: =IF($O28="","",$O28-TODAY()) -> -163 | M28: =IF(AND(TRIM($A28)="Finalized",$K28<>""),"",IF($F28="","",$F28+90-TODAY())) -> -163 | N28: =IF(AND(TRIM($A28)="Finalized",$K28<>""),"",IF($C28="","",$C28+365-TODAY())) -> 127 | O28: =IF(AND(TRIM($A28)="Finalized",$K28<>""),"",DATE(2026,4,29)) -> 46141 | P28: 90 days | Q28: BCBS | R28: 90 days | S28: Date of service | T28: 365 days | U28: Processed date | V28: 2026-01 January | W28: BH | AA28: 1 | AB28: 976.64 | AC28: 0 | AD28: 0 | AE28: 46066 | AF28: 976.64 | AG28: 191 | AH28: F4323 | AM28: TURLEY, TODD | AN28: ASAP - DEER VALLEY | AO28: 46056
A29: =IFERROR(IF(INDEX([1]US!$A$2:$A$8,MATCH($D29,[1]US!$D$2:$D$8,0))="","",INDEX([1]US!$A$2:$A$8,MATCH($D29,[1]US!$D$2:$D$8,0))),"") | B29: =IFERROR(IF(INDEX([1]US!$B$2:$B$8,MATCH($D29,[1]US!$D$2:$D$8,0))="","",INDEX([1]US!$B$2:$B$8,MATCH($D29,[1]US!$D$2:$D$8,0))),"") | C29: =IFERROR(IF(INDEX([1]US!$C$2:$C$8,MATCH($D29,[1]US!$D$2:$D$8,0))="","",INDEX([1]US!$C$2:$C$8,MATCH($D29,[1]US!$D$2:$D$8,0))),"") -> 46156 | D29: 548573158 | E29: HF537684538 | F29: 46051 | G29: United Healthcare | H29: United Healthcare | I29: No Payer | J29: 93970 x1 | K29: =IFERROR(IF(INDEX([1]US!$K$2:$K$8,MATCH($D29,[1]US!$D$2:$D$8,0))="","",INDEX([1]US!$K$2:$K$8,MATCH($D29,[1]US!$D$2:$D$8,0))),"") | L29: =IF($O29="","",$O29-TODAY()) -> -163 | M29: =IF(AND(TRIM($A29)="Finalized",$K29<>""),"",IF($C29="","",$C29+180-TODAY())) -> 32 | N29: =IF(AND(TRIM($A29)="Finalized",$K29<>""),"",IF($C29="","",$C29+365-TODAY())) -> 217 | O29: =IF(AND(TRIM($A29)="Finalized",$K29<>""),"",DATE(2026,4,29)) -> 46141 | P29: 90 days | Q29: UHC COMMERCIAL | R29: 180 days | S29: Processed date | T29: 365 days | U29: Processed date | V29: 2026-01 January | W29: US | AA29: 1 | AB29: 1294.23 | AC29: 0 | AD29: 0 | AE29: 46156 | AF29: 1294.23 | AG29: 191 | AH29: R600 | AI29: M79604 | AJ29: M79605 | AM29: TURLEY, TODD | AN29: ASAP - DEER VALLEY | AO29: 46058
A30: =IFERROR(IF(INDEX([2]BH!$A$2:$A$9,MATCH($D30,[2]BH!$D$2:$D$9,0))="","",INDEX([2]BH!$A$2:$A$9,MATCH($D30,[2]BH!$D$2:$D$9,0))),"") -> Denied | B30: =IFERROR(IF(INDEX([2]BH!$B$2:$B$9,MATCH($D30,[2]BH!$D$2:$D$9,0))="","",INDEX([2]BH!$B$2:$B$9,MATCH($D30,[2]BH!$D$2:$D$9,0))),"") -> Rep Briana - Jarrett Leathem is not contracted with member's Focus Network - Reference number 11216220 | C30: =IFERROR(IF(INDEX([2]BH!$C$2:$C$9,MATCH($D30,[2]BH!$D$2:$D$9,0))="","",INDEX([2]BH!$C$2:$C$9,MATCH($D30,[2]BH!$D$2:$D$9,0))),"") -> 46098 | D30: 548676737 | E30: HF499806568 | F30: 46056 | G30: Blue Cross Blue Shield of Arizona (BCBS AZ) | H30: Blue Cross Blue Shield of Arizona (BCBS AZ) | I30: No Payer | J30: 99494 x1; 99493 x1 | K30: =IFERROR(IF(INDEX([2]BH!$K$2:$K$9,MATCH($D30,[2]BH!$D$2:$D$9,0))="","",INDEX([2]BH!$K$2:$K$9,MATCH($D30,[2]BH!$D$2:$D$9,0))),"") -> 46183 | L30: =IF($O30="","",$O30-TODAY()) -> -158 | M30: =IF(AND(TRIM($A30)="Finalized",$K30<>""),"",IF($F30="","",$F30+90-TODAY())) -> -158 | N30: =IF(AND(TRIM($A30)="Finalized",$K30<>""),"",IF($C30="","",$C30+365-TODAY())) -> 159 | O30: =IF(AND(TRIM($A30)="Finalized",$K30<>""),"",DATE(2026,5,4)) -> 46146 | P30: 90 days | Q30: BCBS | R30: 90 days | S30: Date of service | T30: 365 days | U30: Processed date | V30: 2026-02 February | W30: BH | AA30: 1 | AB30: 1372.91 | AC30: 0 | AD30: 0 | AE30: 46098 | AF30: 1372.91 | AG30: 186 | AH30: F4320 | AM30: LEATHEM, JARRETT | AN30: ASAP - Goodyear | AO30: 46086
A31: =IFERROR(IF(INDEX([1]GAE!$A$2:$A$12,MATCH($D31,[1]GAE!$D$2:$D$12,0))="","",INDEX([1]GAE!$A$2:$A$12,MATCH($D31,[1]GAE!$D$2:$D$12,0))),"") | B31: =IFERROR(IF(INDEX([1]GAE!$B$2:$B$12,MATCH($D31,[1]GAE!$D$2:$D$12,0))="","",INDEX([1]GAE!$B$2:$B$12,MATCH($D31,[1]GAE!$D$2:$D$12,0))),"") | C31: =IFERROR(IF(INDEX([1]GAE!$C$2:$C$12,MATCH($D31,[1]GAE!$D$2:$D$12,0))="","",INDEX([1]GAE!$C$2:$C$12,MATCH($D31,[1]GAE!$D$2:$D$12,0))),"") -> 46127 | D31: 555373347 | E31: HF543361488 | F31: 46027 | G31: Aetna Medicare PPO | H31: Aetna Medicare PPO | I31: No Payer | J31: 36248+59 x3; 37242 x1; 36246+59+RT x1 | K31: =IFERROR(IF(INDEX([1]GAE!$K$2:$K$12,MATCH($D31,[1]GAE!$D$2:$D$12,0))="","",INDEX([1]GAE!$K$2:$K$12,MATCH($D31,[1]GAE!$D$2:$D$12,0))),"") | L31: =IF($O31="","",$O31-TODAY()) -> -157 | M31: =IF(AND(TRIM($A31)="Finalized",$K31<>""),"",IF($C31="","",$C31+180-TODAY())) -> 3 | N31: =IF(AND(TRIM($A31)="Finalized",$K31<>""),"",IF($C31="","",$C31+180-TODAY())) -> 3 | O31: =IF(AND(TRIM($A31)="Finalized",$K31<>""),"",DATE(2026,5,5)) -> 46147 | P31: 120 days | Q31: AETNA | R31: 180 days | S31: Processed date | T31: 180 days | U31: Processed date | V31: 2026-01 January | W31: GAE | X31: 59 | Y31: RT | AA31: 3, 1 | AB31: 57326.78 | AC31: 0 | AD31: 0 | AE31: 46127 | AF31: 57326.78 | AG31: 215 | AH31: M1711 | AI31: I798 | AJ31: M25561 | AM31: HUNTER, DREW | AN31: ASAP - DEER VALLEY | AO31: 46062
A32: =IFERROR(IF(INDEX([2]ORTHO!$A$2:$A$11,MATCH($D32,[2]ORTHO!$D$2:$D$11,0))="","",INDEX([2]ORTHO!$A$2:$A$11,MATCH($D32,[2]ORTHO!$D$2:$D$11,0))),"") -> Denied | B32: =IFERROR(IF(INDEX([2]ORTHO!$B$2:$B$11,MATCH($D32,[2]ORTHO!$D$2:$D$11,0))="","",INDEX([2]ORTHO!$B$2:$B$11,MATCH($D32,[2]ORTHO!$D$2:$D$11,0))),"") -> Deanne is reviewing this one - Rep Jessie - Claim contains a non anesthesia service, and rendering is listed as an anesthesiologist on ins end | C32: =IFERROR(IF(INDEX([2]ORTHO!$C$2:$C$11,MATCH($D32,[2]ORTHO!$D$2:$D$11,0))="","",INDEX([2]ORTHO!$C$2:$C$11,MATCH($D32,[2]ORTHO!$D$2:$D$11,0))),"") -> 46147 | D32: 555677002 | E32: HF540909294 | F32: 46059 | G32: Humana Gold Plus HMO | H32: Humana Gold Plus HMO | I32: No Payer | J32: 63048 x1; 63047 x1 | K32: =IFERROR(IF(INDEX([2]ORTHO!$K$2:$K$11,MATCH($D32,[2]ORTHO!$D$2:$D$11,0))="","",INDEX([2]ORTHO!$K$2:$K$11,MATCH($D32,[2]ORTHO!$D$2:$D$11,0))),"") -> 46247 | L32: =IF($O32="","",$O32-TODAY()) -> -155 | M32: =IF(AND(TRIM($A32)="Finalized",$K32<>""),"",IF($F32="","",$F32+90-TODAY())) -> -155 | N32: =IF(AND(TRIM($A32)="Finalized",$K32<>""),"",IF($C32="","",$C32+540-TODAY())) -> 383 | O32: =IF(AND(TRIM($A32)="Finalized",$K32<>""),"",DATE(2026,5,7)) -> 46149 | P32: 90 days | Q32: HUMANA MA | R32: 90 days | S32: Date of service | T32: 540 days | U32: Processed date | V32: 2026-02 February | W32: ORTHO | AA32: 1 | AB32: 9056.39 | AC32: 0 | AD32: 0 | AE32: 46147 | AF32: 9056.39 | AG32: 183 | AH32: M48062 | AM32: O'NEIL, ROY | AN32: ASAP Surgery Centers North Valley LLC | AO32: 46065
A33: =IFERROR(IF(INDEX([2]BH!$A$2:$A$9,MATCH($D33,[2]BH!$D$2:$D$9,0))="","",INDEX([2]BH!$A$2:$A$9,MATCH($D33,[2]BH!$D$2:$D$9,0))),"") -> Denied | B33: =IFERROR(IF(INDEX([2]BH!$B$2:$B$9,MATCH($D33,[2]BH!$D$2:$D$9,0))="","",INDEX([2]BH!$B$2:$B$9,MATCH($D33,[2]BH!$D$2:$D$9,0))),"") -> DND - Non contracted provider | C33: =IFERROR(IF(INDEX([2]BH!$C$2:$C$9,MATCH($D33,[2]BH!$D$2:$D$9,0))="","",INDEX([2]BH!$C$2:$C$9,MATCH($D33,[2]BH!$D$2:$D$9,0))),"") -> 46148 | D33: 548979329 | E33: HF527306886 | F33: 46062 | G33: Blue Cross Blue Shield of Arizona (BCBS AZ) | H33: Blue Cross Blue Shield of Arizona (BCBS AZ) | I33: No Payer | J33: 99493 x1; 99494 x1 | K33: =IFERROR(IF(INDEX([2]BH!$K$2:$K$9,MATCH($D33,[2]BH!$D$2:$D$9,0))="","",INDEX([2]BH!$K$2:$K$9,MATCH($D33,[2]BH!$D$2:$D$9,0))),"") -> 46183 | L33: =IF($O33="","",$O33-TODAY()) -> -152 | M33: =IF(AND(TRIM($A33)="Finalized",$K33<>""),"",IF($F33="","",$F33+90-TODAY())) -> -152 | N33: =IF(AND(TRIM($A33)="Finalized",$K33<>""),"",IF($C33="","",$C33+365-TODAY())) -> 209 | O33: =IF(AND(TRIM($A33)="Finalized",$K33<>""),"",DATE(2026,5,10)) -> 46152 | P33: 90 days | Q33: BCBS | R33: 90 days | S33: Date of service | T33: 365 days | U33: Processed date | V33: 2026-02 February | W33: BH | AA33: 1 | AB33: 1372.91 | AC33: 0 | AD33: 0 | AE33: 46148 | AF33: 1372.91 | AG33: 180 | AH33: F4320 | AM33: KALLGREN, MARK | AN33: ASAP Peoria | AO33: 46090
A34: =IFERROR(IF(INDEX([2]BH!$A$2:$A$9,MATCH($D34,[2]BH!$D$2:$D$9,0))="","",INDEX([2]BH!$A$2:$A$9,MATCH($D34,[2]BH!$D$2:$D$9,0))),"") -> Finalized | B34: =IFERROR(IF(INDEX([2]BH!$B$2:$B$9,MATCH($D34,[2]BH!$D$2:$D$9,0))="","",INDEX([2]BH!$B$2:$B$9,MATCH($D34,[2]BH!$D$2:$D$9,0))),"") | C34: =IFERROR(IF(INDEX([2]BH!$C$2:$C$9,MATCH($D34,[2]BH!$D$2:$D$9,0))="","",INDEX([2]BH!$C$2:$C$9,MATCH($D34,[2]BH!$D$2:$D$9,0))),"") -> 46119 | D34: 549765437 | E34: HF359780591 | F34: 46065 | G34: TRIADA GAP BENEFITS | H34: Blue Cross Blue Shield of Arizona (BCBS AZ) | I34: TRIADA GAP BENEFITS | J34: 99493 x1; 99494 x1 | K34: =IFERROR(IF(INDEX([2]BH!$K$2:$K$9,MATCH($D34,[2]BH!$D$2:$D$9,0))="","",INDEX([2]BH!$K$2:$K$9,MATCH($D34,[2]BH!$D$2:$D$9,0))),"") | L34: =IF($O34="","",$O34-TODAY()) -> -149 | M34: =IF(AND(TRIM($A34)="Finalized",$K34<>""),"",IF($F34="","",$F34+90-TODAY())) -> -149 | N34: =IF(AND(TRIM($A34)="Finalized",$K34<>""),"",IF($C34="","",$C34+365-TODAY())) -> 180 | O34: =IF(AND(TRIM($A34)="Finalized",$K34<>""),"",DATE(2026,5,13)) -> 46155 | P34: 90 days | Q34: BCBS | R34: 90 days | S34: Date of service | T34: 365 days | U34: Processed date | V34: 2026-02 February | W34: BH | AA34: 1 | AB34: 1372.91 | AC34: 1179.89 | AD34: 0 | AE34: 46119 | AF34: 193.02 | AG34: 177 | AH34: F411 | AL34: 558453526 | AM34: LEATHEM, JARRETT | AN34: ASAP - DEER VALLEY | AO34: 46086
A35: =IFERROR(IF(INDEX([1]BH!$A$2:$A$17,MATCH($D35,[1]BH!$D$2:$D$17,0))="","",INDEX([1]BH!$A$2:$A$17,MATCH($D35,[1]BH!$D$2:$D$17,0))),"") -> Rejected | B35: =IFERROR(IF(INDEX([1]BH!$B$2:$B$17,MATCH($D35,[1]BH!$D$2:$D$17,0))="","",INDEX([1]BH!$B$2:$B$17,MATCH($D35,[1]BH!$D$2:$D$17,0))),"") -> ASAP DEER VALLEY NPI missing - Resubmitted | C35: =IFERROR(IF(INDEX([1]BH!$C$2:$C$17,MATCH($D35,[1]BH!$D$2:$D$17,0))="","",INDEX([1]BH!$C$2:$C$17,MATCH($D35,[1]BH!$D$2:$D$17,0))),"") -> 46098 | D35: 557090486 | E35: HF342585384 | F35: 46036 | G35: TRIWEST VA CCN CLAIMS | H35: TRIWEST VA CCN CLAIMS | I35: No Payer | J35: 99494 x2; 99493 x1 | K35: =IFERROR(IF(INDEX([1]BH!$K$2:$K$17,MATCH($D35,[1]BH!$D$2:$D$17,0))="","",INDEX([1]BH!$K$2:$K$17,MATCH($D35,[1]BH!$D$2:$D$17,0))),"") -> 46135 | L35: =IF($O35="","",$O35-TODAY()) -> -148 | M35: =IF(AND(TRIM($A35)="Finalized",$K35<>""),"",IF($C35="","",$C35+365-TODAY())) -> 159 | N35: =IF(AND(TRIM($A35)="Finalized",$K35<>""),"",IF($C35="","",$C35+90-TODAY())) -> -116 | O35: =IF(AND(TRIM($A35)="Finalized",$K35<>""),"",DATE(2026,5,14)) -> 46156 | P35: 120 days | Q35: TRIWEST | R35: 365 days | S35: Processed date | T35: 90 days | U35: Processed date | V35: 2026-01 January | W35: BH | AA35: 2, 1 | AB35: 1769.18 | AC35: 0 | AD35: 0 | AE35: 46098 | AF35: 1769.18 | AG35: 206 | AH35: F332 | AM35: TURLEY, TODD | AN35: ASAP - DEER VALLEY | AO35: 46056
A36: =IFERROR(IF(INDEX([2]BH!$A$2:$A$9,MATCH($D36,[2]BH!$D$2:$D$9,0))="","",INDEX([2]BH!$A$2:$A$9,MATCH($D36,[2]BH!$D$2:$D$9,0))),"") -> Denied | B36: =IFERROR(IF(INDEX([2]BH!$B$2:$B$9,MATCH($D36,[2]BH!$D$2:$D$9,0))="","",INDEX([2]BH!$B$2:$B$9,MATCH($D36,[2]BH!$D$2:$D$9,0))),"") -> Added Date of Current Illness, claim note, and resubmitted | C36: =IFERROR(IF(INDEX([2]BH!$C$2:$C$9,MATCH($D36,[2]BH!$D$2:$D$9,0))="","",INDEX([2]BH!$C$2:$C$9,MATCH($D36,[2]BH!$D$2:$D$9,0))),"") -> 46147 | D36: 557794433 | E36: HF434792716 | F36: 46066 | G36: Optum Care Medical Network of Arizona, Utah, & Washington (LifePrint) | H36: Optum Care Medical Network of Arizona, Utah, & Washington (LifePrint) | I36: No Payer | J36: 99493 x1 | K36: =IFERROR(IF(INDEX([2]BH!$K$2:$K$9,MATCH($D36,[2]BH!$D$2:$D$9,0))="","",INDEX([2]BH!$K$2:$K$9,MATCH($D36,[2]BH!$D$2:$D$9,0))),"") -> 46142 | L36: =IF($O36="","",$O36-TODAY()) -> -148 | M36: =IF(AND(TRIM($A36)="Finalized",$K36<>""),"",IF($C36="","",$C36+365-TODAY())) -> 208 | N36: =IF(AND(TRIM($A36)="Finalized",$K36<>""),"",IF($C36="","",$C36+365-TODAY())) -> 208 | O36: =IF(AND(TRIM($A36)="Finalized",$K36<>""),"",DATE(2026,5,14)) -> 46156 | P36: 90 days | Q36: OPTUM | R36: 365 days | S36: Processed date | T36: 365 days | U36: Processed date | V36: 2026-02 February | W36: BH | AA36: 1 | AB36: 976.64 | AC36: 0 | AD36: 0 | AE36: 46147 | AF36: 976.64 | AG36: 176 | AH36: F1190 | AM36: LEATHEM, JARRETT | AN36: ASAP - Gilbert | AO36: 46086
A37: =IFERROR(IF(INDEX([2]GAE!$A$2:$A$6,MATCH($D37,[2]GAE!$D$2:$D$6,0))="","",INDEX([2]GAE!$A$2:$A$6,MATCH($D37,[2]GAE!$D$2:$D$6,0))),"") -> Denied | B37: =IFERROR(IF(INDEX([2]GAE!$B$2:$B$6,MATCH($D37,[2]GAE!$D$2:$D$6,0))="","",INDEX([2]GAE!$B$2:$B$6,MATCH($D37,[2]GAE!$D$2:$D$6,0))),"") -> Provider active, resubmitted | C37: =IFERROR(IF(INDEX([2]GAE!$C$2:$C$6,MATCH($D37,[2]GAE!$D$2:$D$6,0))="","",INDEX([2]GAE!$C$2:$C$6,MATCH($D37,[2]GAE!$D$2:$D$6,0))),"") -> 46154 | D37: 557784595 | E37: HF489558936 | F37: 46069 | G37: Blue Cross Blue Shield of Arizona (BCBS AZ) | H37: Blue Cross Blue Shield of Arizona (BCBS AZ) | I37: No Payer | J37: 36246+59+RT x1; 75710+XU+RT x1; 76937 x1; 75774+XU x4; 36248+59 x3; 37242 x1 | K37: =IFERROR(IF(INDEX([2]GAE!$K$2:$K$6,MATCH($D37,[2]GAE!$D$2:$D$6,0))="","",INDEX([2]GAE!$K$2:$K$6,MATCH($D37,[2]GAE!$D$2:$D$6,0))),"") -> 46142 | L37: =IF($O37="","",$O37-TODAY()) -> -145 | M37: =IF(AND(TRIM($A37)="Finalized",$K37<>""),"",IF($F37="","",$F37+90-TODAY())) -> -145 | N37: =IF(AND(TRIM($A37)="Finalized",$K37<>""),"",IF($C37="","",$C37+365-TODAY())) -> 215 | O37: =IF(AND(TRIM($A37)="Finalized",$K37<>""),"",DATE(2026,5,17)) -> 46159 | P37: 90 days | Q37: BCBS | R37: 90 days | S37: Date of service | T37: 365 days | U37: Processed date | V37: 2026-02 February | W37: GAE | X37: 59, XU | Y37: RT | AA37: 1, 4, 3 | AB37: 61320.35 | AC37: 0 | AD37: 0 | AE37: 46154 | AF37: 61320.35 | AG37: 173 | AH37: M1711 | AI37: I798 | AJ37: M25561 | AM37: HUNTER, DREW | AN37: ASAP - DEER VALLEY | AO37: 46090
A38: =IFERROR(IF(INDEX([2]DME!$A$2:$A$12,MATCH($D38,[2]DME!$D$2:$D$12,0))="","",INDEX([2]DME!$A$2:$A$12,MATCH($D38,[2]DME!$D$2:$D$12,0))),"") -> Under Review | B38: =IFERROR(IF(INDEX([2]DME!$B$2:$B$12,MATCH($D38,[2]DME!$D$2:$D$12,0))="","",INDEX([2]DME!$B$2:$B$12,MATCH($D38,[2]DME!$D$2:$D$12,0))),"") -> Auth issue - Denied payment again - Bri resubmitted - Provider TAX ID/NPI Combination is not on file with BCBS AZ. | C38: =IFERROR(IF(INDEX([2]DME!$C$2:$C$12,MATCH($D38,[2]DME!$D$2:$D$12,0))="","",INDEX([2]DME!$C$2:$C$12,MATCH($D38,[2]DME!$D$2:$D$12,0))),"") -> 46227 | D38: 565140993 | E38: HF513477727 | F38: 46069 | G38: Blue Cross Blue Shield of Arizona (BCBS AZ) | H38: Blue Cross Blue Shield of Arizona (BCBS AZ) | I38: No Payer | J38: L0648+KX x1 | K38: =IFERROR(IF(INDEX([2]DME!$K$2:$K$12,MATCH($D38,[2]DME!$D$2:$D$12,0))="","",INDEX([2]DME!$K$2:$K$12,MATCH($D38,[2]DME!$D$2:$D$12,0))),"") -> 46196 | L38: =IF($O38="","",$O38-TODAY()) -> -145 | M38: =IF(AND(TRIM($A38)="Finalized",$K38<>""),"",IF($F38="","",$F38+90-TODAY())) -> -145 | N38: =IF(AND(TRIM($A38)="Finalized",$K38<>""),"",IF($C38="","",$C38+365-TODAY())) -> 288 | O38: =IF(AND(TRIM($A38)="Finalized",$K38<>""),"",DATE(2026,5,17)) -> 46159 | P38: 90 days | Q38: BCBS | R38: 90 days | S38: Date of service | T38: 365 days | U38: Processed date | V38: 2026-02 February | W38: DME | X38: KX | AA38: 1 | AB38: 5492.55 | AC38: 0 | AD38: 0 | AF38: 5492.55 | AG38: 173 | AH38: M4316 | AI38: M51362 | AM38: MAYURAN, VIKRAM | AN38: ASAP - Mesa | AO38: 46080
A39: =IFERROR(IF(INDEX([2]BH!$A$2:$A$9,MATCH($D39,[2]BH!$D$2:$D$9,0))="","",INDEX([2]BH!$A$2:$A$9,MATCH($D39,[2]BH!$D$2:$D$9,0))),"") -> Denied | B39: =IFERROR(IF(INDEX([2]BH!$B$2:$B$9,MATCH($D39,[2]BH!$D$2:$D$9,0))="","",INDEX([2]BH!$B$2:$B$9,MATCH($D39,[2]BH!$D$2:$D$9,0))),"") -> Awaiting resolution on claim #556349314 (DOS 01/27/2026) before reprocessing DND 99493 This non-payable code is for required reporting only - Added Date of Current Illness, claim note, and resubmitted | C39: =IFERROR(IF(INDEX([2]BH!$C$2:$C$9,MATCH($D39,[2]BH!$D$2:$D$9,0))="","",INDEX([2]BH!$C$2:$C$9,MATCH($D39,[2]BH!$D$2:$D$9,0))),"") -> 46147 | D39: 557794882 | E39: HF431164004 | F39: 46070 | G39: Optum Care Medical Network of Arizona, Utah, & Washington (LifePrint) | H39: Optum Care Medical Network of Arizona, Utah, & Washington (LifePrint) | I39: No Payer | J39: 99493 x1 | K39: =IFERROR(IF(INDEX([2]BH!$K$2:$K$9,MATCH($D39,[2]BH!$D$2:$D$9,0))="","",INDEX([2]BH!$K$2:$K$9,MATCH($D39,[2]BH!$D$2:$D$9,0))),"") -> 46284 | L39: =IF($O39="","",$O39-TODAY()) -> -144 | M39: =IF(AND(TRIM($A39)="Finalized",$K39<>""),"",IF($C39="","",$C39+365-TODAY())) -> 208 | N39: =IF(AND(TRIM($A39)="Finalized",$K39<>""),"",IF($C39="","",$C39+365-TODAY())) -> 208 | O39: =IF(AND(TRIM($A39)="Finalized",$K39<>""),"",DATE(2026,5,18)) -> 46160 | P39: 90 days | Q39: OPTUM | R39: 365 days | S39: Processed date | T39: 365 days | U39: Processed date | V39: 2026-02 February | W39: BH | AA39: 1 | AB39: 976.64 | AC39: 0 | AD39: 0 | AE39: 46147 | AF39: 976.64 | AG39: 172 | AH39: F331 | AI39: F411 | AM39: O'NEIL, ROY | AN39: ASAP - Goodyear | AO39: 46086
A40: =IFERROR(IF(INDEX([2]BH!$A$2:$A$9,MATCH($D40,[2]BH!$D$2:$D$9,0))="","",INDEX([2]BH!$A$2:$A$9,MATCH($D40,[2]BH!$D$2:$D$9,0))),"") -> Denied | B40: =IFERROR(IF(INDEX([2]BH!$B$2:$B$9,MATCH($D40,[2]BH!$D$2:$D$9,0))="","",INDEX([2]BH!$B$2:$B$9,MATCH($D40,[2]BH!$D$2:$D$9,0))),"") -> Rep Muthamma - Under review - Ref # 11253575 | C40: =IFERROR(IF(INDEX([2]BH!$C$2:$C$9,MATCH($D40,[2]BH!$D$2:$D$9,0))="","",INDEX([2]BH!$C$2:$C$9,MATCH($D40,[2]BH!$D$2:$D$9,0))),"") -> 46101 | D40: 550288006 | E40: HF331718997 | F40: 46071 | G40: Blue Cross Blue Shield of Arizona (BCBS AZ) | H40: Blue Cross Blue Shield of Arizona (BCBS AZ) | I40: No Payer | J40: 99494 x2; 99492 x1 | K40: =IFERROR(IF(INDEX([2]BH!$K$2:$K$9,MATCH($D40,[2]BH!$D$2:$D$9,0))="","",INDEX([2]BH!$K$2:$K$9,MATCH($D40,[2]BH!$D$2:$D$9,0))),"") -> 46183 | L40: =IF($O40="","",$O40-TODAY()) -> -143 | M40: =IF(AND(TRIM($A40)="Finalized",$K40<>""),"",IF($F40="","",$F40+90-TODAY())) -> -143 | N40: =IF(AND(TRIM($A40)="Finalized",$K40<>""),"",IF($C40="","",$C40+365-TODAY())) -> 162 | O40: =IF(AND(TRIM($A40)="Finalized",$K40<>""),"",DATE(2026,5,19)) -> 46161 | P40: 90 days | Q40: BCBS | R40: 90 days | S40: Date of service | T40: 365 days | U40: Processed date | V40: 2026-02 February | W40: BH | AA40: 2, 1 | AB40: 1822.52 | AC40: 0 | AD40: 0 | AE40: 46101 | AF40: 1822.52 | AG40: 171 | AH40: F4323 | AM40: SARKAR, AWNIK | AN40: ASAP - DEER VALLEY | AO40: 46086
A41: =IFERROR(IF(INDEX([2]DME!$A$2:$A$12,MATCH($D41,[2]DME!$D$2:$D$12,0))="","",INDEX([2]DME!$A$2:$A$12,MATCH($D41,[2]DME!$D$2:$D$12,0))),"") -> Denied | B41: =IFERROR(IF(INDEX([2]DME!$B$2:$B$12,MATCH($D41,[2]DME!$D$2:$D$12,0))="","",INDEX([2]DME!$B$2:$B$12,MATCH($D41,[2]DME!$D$2:$D$12,0))),"") -> No authorization found or requested - Checking if we need auth on Curo portal # 19801266 - Pending - Review | C41: =IFERROR(IF(INDEX([2]DME!$C$2:$C$12,MATCH($D41,[2]DME!$D$2:$D$12,0))="","",INDEX([2]DME!$C$2:$C$12,MATCH($D41,[2]DME!$D$2:$D$12,0))),"") -> 46106 | D41: 550530483 | E41: HF544828362 | F41: 46072 | G41: UHC Group Medicare Advantage | H41: UHC Group Medicare Advantage | I41: No Payer | J41: A6010+A1 x20 | K41: =IFERROR(IF(INDEX([2]DME!$K$2:$K$12,MATCH($D41,[2]DME!$D$2:$D$12,0))="","",INDEX([2]DME!$K$2:$K$12,MATCH($D41,[2]DME!$D$2:$D$12,0))),"") -> 46197 | L41: =IF($O41="","",$O41-TODAY()) -> -142 | M41: =IF(AND(TRIM($A41)="Finalized",$K41<>""),"",IF($C41="","",$C41+180-TODAY())) -> -18 | N41: =IF(AND(TRIM($A41)="Finalized",$K41<>""),"",IF($C41="","",$C41+365-TODAY())) -> 167 | O41: =IF(AND(TRIM($A41)="Finalized",$K41<>""),"",DATE(2026,5,20)) -> 46162 | P41: 90 days | Q41: UHC MA | R41: 180 days | S41: Processed date | T41: 365 days | U41: Processed date | V41: 2026-02 February | W41: DME | X41: A1 | AA41: 20 | AB41: 5916.4 | AC41: 0 | AD41: 0 | AE41: 46106 | AF41: 5916.4 | AG41: 170 | AH41: G894 | AI41: L97529 | AM41: MEARS, CHAD | AN41: ASAP Peoria | AO41: 46077
A42: =IFERROR(IF(INDEX([2]BH!$A$2:$A$9,MATCH($D42,[2]BH!$D$2:$D$9,0))="","",INDEX([2]BH!$A$2:$A$9,MATCH($D42,[2]BH!$D$2:$D$9,0))),"") -> Denied | B42: =IFERROR(IF(INDEX([2]BH!$B$2:$B$9,MATCH($D42,[2]BH!$D$2:$D$9,0))="","",INDEX([2]BH!$B$2:$B$9,MATCH($D42,[2]BH!$D$2:$D$9,0))),"") -> Changed primary code - Used 99492, and resubmitted | C42: =IFERROR(IF(INDEX([2]BH!$C$2:$C$9,MATCH($D42,[2]BH!$D$2:$D$9,0))="","",INDEX([2]BH!$C$2:$C$9,MATCH($D42,[2]BH!$D$2:$D$9,0))),"") -> 46147 | D42: 557794229 | E42: HF460603685 | F42: 46073 | G42: Optum Care Medical Network of Arizona, Utah, & Washington (LifePrint) | H42: Optum Care Medical Network of Arizona, Utah, & Washington (LifePrint) | I42: No Payer | J42: 99493 x1 | K42: =IFERROR(IF(INDEX([2]BH!$K$2:$K$9,MATCH($D42,[2]BH!$D$2:$D$9,0))="","",INDEX([2]BH!$K$2:$K$9,MATCH($D42,[2]BH!$D$2:$D$9,0))),"") -> 46247 | L42: =IF($O42="","",$O42-TODAY()) -> -141 | M42: =IF(AND(TRIM($A42)="Finalized",$K42<>""),"",IF($C42="","",$C42+365-TODAY())) -> 208 | N42: =IF(AND(TRIM($A42)="Finalized",$K42<>""),"",IF($C42="","",$C42+365-TODAY())) -> 208 | O42: =IF(AND(TRIM($A42)="Finalized",$K42<>""),"",DATE(2026,5,21)) -> 46163 | P42: 90 days | Q42: OPTUM | R42: 365 days | S42: Processed date | T42: 365 days | U42: Processed date | V42: 2026-02 February | W42: BH | AA42: 1 | AB42: 976.64 | AC42: 0 | AD42: 0 | AE42: 46147 | AF42: 976.64 | AG42: 169 | AH42: F1190 | AM42: KALLGREN, MARK | AN42: ASAP - Gilbert | AO42: 46086
A43: =IFERROR(IF(INDEX([2]BH!$A$2:$A$9,MATCH($D43,[2]BH!$D$2:$D$9,0))="","",INDEX([2]BH!$A$2:$A$9,MATCH($D43,[2]BH!$D$2:$D$9,0))),"") -> Denied | B43: =IFERROR(IF(INDEX([2]BH!$B$2:$B$9,MATCH($D43,[2]BH!$D$2:$D$9,0))="","",INDEX([2]BH!$B$2:$B$9,MATCH($D43,[2]BH!$D$2:$D$9,0))),"") -> Edited service line 1 - Used cpt 99492, and resubmitted - The reconsideration option is unavailable on portal because the claim has already been adjusted - 99493 paid on claim 26A074466600, DOS 12/12/2025, under prior member ID 1718676 - current claim was billed with member ID 906162197 currently active - DND Subsequent psychiatric CoCM code 99493 is reported on 02/20/2026 and there is no line within the previous 6 months history with psychiatric CoCM codes 99492 or 99493 - Added Date of Current Illness, claim note, and resubmitted | C43: =IFERROR(IF(INDEX([2]BH!$C$2:$C$9,MATCH($D43,[2]BH!$D$2:$D$9,0))="","",INDEX([2]BH!$C$2:$C$9,MATCH($D43,[2]BH!$D$2:$D$9,0))),"") -> 46147 | D43: 557793858 | E43: HF443112560 | F43: 46073 | G43: Optum Care Medical Network of Arizona, Utah, & Washington (LifePrint) | H43: Optum Care Medical Network of Arizona, Utah, & Washington (LifePrint) | I43: No Payer | J43: 99493 x1 | K43: =IFERROR(IF(INDEX([2]BH!$K$2:$K$9,MATCH($D43,[2]BH!$D$2:$D$9,0))="","",INDEX([2]BH!$K$2:$K$9,MATCH($D43,[2]BH!$D$2:$D$9,0))),"") -> 46266 | L43: =IF($O43="","",$O43-TODAY()) -> -141 | M43: =IF(AND(TRIM($A43)="Finalized",$K43<>""),"",IF($C43="","",$C43+365-TODAY())) -> 208 | N43: =IF(AND(TRIM($A43)="Finalized",$K43<>""),"",IF($C43="","",$C43+365-TODAY())) -> 208 | O43: =IF(AND(TRIM($A43)="Finalized",$K43<>""),"",DATE(2026,5,21)) -> 46163 | P43: 90 days | Q43: OPTUM | R43: 365 days | S43: Processed date | T43: 365 days | U43: Processed date | V43: 2026-02 February | W43: BH | AA43: 1 | AB43: 976.64 | AC43: 0 | AD43: 0 | AE43: 46147 | AF43: 976.64 | AG43: 169 | AH43: F1190 | AM43: LEATHEM, JARRETT | AN43: ASAP - Gilbert | AO43: 46086
A44: =IFERROR(IF(INDEX([2]ORTHO!$A$2:$A$11,MATCH($D44,[2]ORTHO!$D$2:$D$11,0))="","",INDEX([2]ORTHO!$A$2:$A$11,MATCH($D44,[2]ORTHO!$D$2:$D$11,0))),"") -> Received | B44: =IFERROR(IF(INDEX([2]ORTHO!$B$2:$B$11,MATCH($D44,[2]ORTHO!$D$2:$D$11,0))="","",INDEX([2]ORTHO!$B$2:$B$11,MATCH($D44,[2]ORTHO!$D$2:$D$11,0))),"") -> Provider TAX ID/NPI Combination is not on file with BCBS AZ. | C44: =IFERROR(IF(INDEX([2]ORTHO!$C$2:$C$11,MATCH($D44,[2]ORTHO!$D$2:$D$11,0))="","",INDEX([2]ORTHO!$C$2:$C$11,MATCH($D44,[2]ORTHO!$D$2:$D$11,0))),"") -> 46212 | D44: 563274947 | E44: HF513477727 | F44: 46079 | G44: Blue Cross Blue Shield of Arizona (BCBS AZ) | H44: Blue Cross Blue Shield of Arizona (BCBS AZ) | I44: No Payer | J44: 22845+59 x1; 22853 x1 | K44: =IFERROR(IF(INDEX([2]ORTHO!$K$2:$K$11,MATCH($D44,[2]ORTHO!$D$2:$D$11,0))="","",INDEX([2]ORTHO!$K$2:$K$11,MATCH($D44,[2]ORTHO!$D$2:$D$11,0))),"") | L44: =IF($O44="","",$O44-TODAY()) -> -135 | M44: =IF(AND(TRIM($A44)="Finalized",$K44<>""),"",IF($F44="","",$F44+90-TODAY())) -> -135 | N44: =IF(AND(TRIM($A44)="Finalized",$K44<>""),"",IF($C44="","",$C44+365-TODAY())) -> 273 | O44: =IF(AND(TRIM($A44)="Finalized",$K44<>""),"",DATE(2026,5,27)) -> 46169 | P44: 90 days | Q44: BCBS | R44: 90 days | S44: Date of service | T44: 365 days | U44: Processed date | V44: 2026-02 February | W44: ORTHO | X44: 59 | AA44: 1 | AB44: 6709.36 | AC44: 0 | AD44: 0 | AE44: 46212 | AF44: 6709.36 | AG44: 163 | AH44: M5416 | AI44: M4807 | AM44: MAYURAN, VIKRAM | AN44: Banner Desert Medical Center | AO44: 46092
A45: =IFERROR(IF(INDEX([2]ORTHO!$A$2:$A$11,MATCH($D45,[2]ORTHO!$D$2:$D$11,0))="","",INDEX([2]ORTHO!$A$2:$A$11,MATCH($D45,[2]ORTHO!$D$2:$D$11,0))),"") -> Denied | B45: =IFERROR(IF(INDEX([2]ORTHO!$B$2:$B$11,MATCH($D45,[2]ORTHO!$D$2:$D$11,0))="","",INDEX([2]ORTHO!$B$2:$B$11,MATCH($D45,[2]ORTHO!$D$2:$D$11,0))),"") -> We need to reprocess when claim 568613230 gets adjusted - Added mod 58, and resubmitted | C45: =IFERROR(IF(INDEX([2]ORTHO!$C$2:$C$11,MATCH($D45,[2]ORTHO!$D$2:$D$11,0))="","",INDEX([2]ORTHO!$C$2:$C$11,MATCH($D45,[2]ORTHO!$D$2:$D$11,0))),"") -> 46189 | D45: 562083380 | E45: HF334213960 | F45: 46080 | G45: Optum Care Medical Network of Arizona, Utah, & Washington (LifePrint) | H45: Optum Care Medical Network of Arizona, Utah, & Washington (LifePrint) | I45: No Payer | J45: 63047+58 x1 | K45: =IFERROR(IF(INDEX([2]ORTHO!$K$2:$K$11,MATCH($D45,[2]ORTHO!$D$2:$D$11,0))="","",INDEX([2]ORTHO!$K$2:$K$11,MATCH($D45,[2]ORTHO!$D$2:$D$11,0))),"") -> 46247 | L45: =IF($O45="","",$O45-TODAY()) -> -134 | M45: =IF(AND(TRIM($A45)="Finalized",$K45<>""),"",IF($C45="","",$C45+365-TODAY())) -> 250 | N45: =IF(AND(TRIM($A45)="Finalized",$K45<>""),"",IF($C45="","",$C45+365-TODAY())) -> 250 | O45: =IF(AND(TRIM($A45)="Finalized",$K45<>""),"",DATE(2026,5,28)) -> 46170 | P45: 90 days | Q45: OPTUM | R45: 365 days | S45: Processed date | T45: 365 days | U45: Processed date | V45: 2026-02 February | W45: ORTHO | X45: 58 | AA45: 1 | AB45: 7623.07 | AC45: 0 | AD45: 0 | AE45: 46189 | AF45: 7623.07 | AG45: 162 | AH45: M48062 | AM45: LEATHEM, JARRETT | AN45: Premier Endoscopy Center, LLC | AO45: 46083
A46: =IFERROR(IF(INDEX([3]GAE!$A$2:$A$4,MATCH($D46,[3]GAE!$D$2:$D$4,0))="","",INDEX([3]GAE!$A$2:$A$4,MATCH($D46,[3]GAE!$D$2:$D$4,0))),"") -> Denied | B46: =IFERROR(IF(INDEX([3]GAE!$B$2:$B$4,MATCH($D46,[3]GAE!$D$2:$D$4,0))="","",INDEX([3]GAE!$B$2:$B$4,MATCH($D46,[3]GAE!$D$2:$D$4,0))),"") -> Uploaded MR - PIQ-86274627 | C46: =IFERROR(IF(INDEX([3]GAE!$C$2:$C$4,MATCH($D46,[3]GAE!$D$2:$D$4,0))="","",INDEX([3]GAE!$C$2:$C$4,MATCH($D46,[3]GAE!$D$2:$D$4,0))),"") -> 46217 | D46: 555067836 | E46: HF333306186 | F46: 46083 | G46: UnitedHealthcare Community Plan / Arizona Long Term Care | H46: UnitedHealthcare Community Plan / Arizona Long Term Care | I46: UnitedHealthcare Community Plan / Arizona Long Term Care | J46: 75710+26+XU+RT x1; 36246+59+RT x1; 75774+26+XU x5 | K46: =IFERROR(IF(INDEX([3]GAE!$K$2:$K$4,MATCH($D46,[3]GAE!$D$2:$D$4,0))="","",INDEX([3]GAE!$K$2:$K$4,MATCH($D46,[3]GAE!$D$2:$D$4,0))),"") -> 46197 | L46: =IF($O46="","",$O46-TODAY()) -> -131 | M46: =IF(AND(TRIM($A46)="Finalized",$K46<>""),"",IF($C46="","",$C46+180-TODAY())) -> 93 | N46: =IF(AND(TRIM($A46)="Finalized",$K46<>""),"",IF($C46="","",$C46+365-TODAY())) -> 278 | O46: =IF(AND(TRIM($A46)="Finalized",$K46<>""),"",DATE(2026,5,31)) -> 46173 | P46: 90 days | Q46: UHC COMMUNITY | R46: 180 days | S46: Processed date | T46: 365 days | U46: Processed date | V46: 2026-03 March | W46: GAE | X46: 26, 59 | Y46: XU, RT | Z46: RT | AA46: 1, 5 | AB46: 10134.88 | AC46: 0 | AD46: 0 | AE46: 46217 | AF46: 10134.88 | AG46: 159 | AH46: M1711 | AI46: I798 | AJ46: M25561 | AM46: HUNTER, DREW | AN46: ASAP Surgery Centers North Valley LLC | AO46: 46119
A47: =IFERROR(IF(INDEX([3]US!$A$2:$A$15,MATCH($D47,[3]US!$D$2:$D$15,0))="","",INDEX([3]US!$A$2:$A$15,MATCH($D47,[3]US!$D$2:$D$15,0))),"") -> Denied | B47: =IFERROR(IF(INDEX([3]US!$B$2:$B$15,MATCH($D47,[3]US!$D$2:$D$15,0))="","",INDEX([3]US!$B$2:$B$15,MATCH($D47,[3]US!$D$2:$D$15,0))),"") -> Edited dx order, and resubmitted - DND Diagnosis was invalid for the date(s) of service reported | C47: =IFERROR(IF(INDEX([3]US!$C$2:$C$15,MATCH($D47,[3]US!$D$2:$D$15,0))="","",INDEX([3]US!$C$2:$C$15,MATCH($D47,[3]US!$D$2:$D$15,0))),"") -> 46113 | D47: 571606836 | E47: HF539049375 | F47: 46084 | G47: CIGNA HealthSprings | H47: CIGNA HealthSprings | I47: No Payer | J47: 93970 x1; 93923 x1 | K47: =IFERROR(IF(INDEX([3]US!$K$2:$K$15,MATCH($D47,[3]US!$D$2:$D$15,0))="","",INDEX([3]US!$K$2:$K$15,MATCH($D47,[3]US!$D$2:$D$15,0))),"") -> 46278 | L47: =IF($O47="","",$O47-TODAY()) -> -130 | M47: =IF(AND(TRIM($A47)="Finalized",$K47<>""),"",IF($F47="","",$F47+90-TODAY())) -> -130 | N47: =IF(AND(TRIM($A47)="Finalized",$K47<>""),"",IF($C47="","",$C47+180-TODAY())) -> -11 | O47: =IF(AND(TRIM($A47)="Finalized",$K47<>""),"",DATE(2026,6,1)) -> 46174 | P47: 90 days | Q47: CIGNA / CIGNA MEDICARE | R47: 90 days | S47: Date of service | T47: 180 days | U47: Processed date | V47: 2026-03 March | W47: US | AA47: 1 | AB47: 2173.29 | AC47: 0 | AD47: 0 | AE47: 46113 | AF47: 2173.29 | AG47: 158 | AH47: M5416 | AI47: R600 | AJ47: E139 | AK47: I10 | AM47: LEATHEM, JARRETT | AN47: ASAP - Gilbert | AO47: 46106
A48: =IFERROR(IF(INDEX([3]BH!$A$2:$A$32,MATCH($D48,[3]BH!$D$2:$D$32,0))="","",INDEX([3]BH!$A$2:$A$32,MATCH($D48,[3]BH!$D$2:$D$32,0))),"") -> Denied | B48: =IFERROR(IF(INDEX([3]BH!$B$2:$B$32,MATCH($D48,[3]BH!$D$2:$D$32,0))="","",INDEX([3]BH!$B$2:$B$32,MATCH($D48,[3]BH!$D$2:$D$32,0))),"") -> Jess corrected rendering to TIMOTHY BAUGHER, and resubmitted - We had JARRETT LEATHEM - DND The procedure code is inconsistent with the provider type/specialty (taxonomy). | C48: =IFERROR(IF(INDEX([3]BH!$C$2:$C$32,MATCH($D48,[3]BH!$D$2:$D$32,0))="","",INDEX([3]BH!$C$2:$C$32,MATCH($D48,[3]BH!$D$2:$D$32,0))),"") -> 46134 | D48: 566722180 | E48: HF537685966 | F48: 46085 | G48: Blue Cross Blue Shield of Arizona (BCBS AZ) | H48: Blue Cross Blue Shield of Arizona (BCBS AZ) | I48: Medicare Part B Arizona * | J48: 99493 x1; 99494 x2 | K48: =IFERROR(IF(INDEX([3]BH!$K$2:$K$32,MATCH($D48,[3]BH!$D$2:$D$32,0))="","",INDEX([3]BH!$K$2:$K$32,MATCH($D48,[3]BH!$D$2:$D$32,0))),"") -> 46231 | L48: =IF($O48="","",$O48-TODAY()) -> -129 | M48: =IF(AND(TRIM($A48)="Finalized",$K48<>""),"",IF($F48="","",$F48+90-TODAY())) -> -129 | N48: =IF(AND(TRIM($A48)="Finalized",$K48<>""),"",IF($C48="","",$C48+365-TODAY())) -> 195 | O48: =IF(AND(TRIM($A48)="Finalized",$K48<>""),"",DATE(2026,6,2)) -> 46175 | P48: 90 days | Q48: BCBS | R48: 90 days | S48: Date of service | T48: 365 days | U48: Processed date | V48: 2026-03 March | W48: BH | AA48: 1, 2 | AB48: 1769.18 | AC48: 0 | AD48: 0 | AE48: 46134 | AF48: 1769.18 | AG48: 157 | AH48: F330 | AM48: BAUGHER, TIMOTHY | AN48: ASAP - Gilbert | AO48: 46119
A49: =IFERROR(IF(INDEX([3]ORTHO!$A$2:$A$16,MATCH($D49,[3]ORTHO!$D$2:$D$16,0))="","",INDEX([3]ORTHO!$A$2:$A$16,MATCH($D49,[3]ORTHO!$D$2:$D$16,0))),"") -> Denied | B49: =IFERROR(IF(INDEX([3]ORTHO!$B$2:$B$16,MATCH($D49,[3]ORTHO!$D$2:$D$16,0))="","",INDEX([3]ORTHO!$B$2:$B$16,MATCH($D49,[3]ORTHO!$D$2:$D$16,0))),"") -> Recon sent to fax 615-401-4642 by Christian J - DND 63048 Treatment was deemed by the payer to have been rendered in an inappropriate or invalid place of service | C49: =IFERROR(IF(INDEX([3]ORTHO!$C$2:$C$16,MATCH($D49,[3]ORTHO!$D$2:$D$16,0))="","",INDEX([3]ORTHO!$C$2:$C$16,MATCH($D49,[3]ORTHO!$D$2:$D$16,0))),"") -> 46204 | D49: 552284225 | E49: HF517981468 | F49: 46085 | G49: HealthSpring Medicare Advantage | H49: HealthSpring Medicare Advantage | I49: No Payer | J49: 63048 x1 | K49: =IFERROR(IF(INDEX([3]ORTHO!$K$2:$K$16,MATCH($D49,[3]ORTHO!$D$2:$D$16,0))="","",INDEX([3]ORTHO!$K$2:$K$16,MATCH($D49,[3]ORTHO!$D$2:$D$16,0))),"") | L49: =IF($O49="","",$O49-TODAY()) -> -129 | M49: =IF(AND(TRIM($A49)="Finalized",$K49<>""),"",IF($F49="","",$F49+90-TODAY())) -> -129 | N49: =IF(AND(TRIM($A49)="Finalized",$K49<>""),"",IF($C49="","",$C49+180-TODAY())) -> 80 | O49: =IF(AND(TRIM($A49)="Finalized",$K49<>""),"",DATE(2026,6,2)) -> 46175 | P49: 90 days | Q49: CIGNA / CIGNA MEDICARE | R49: 90 days | S49: Date of service | T49: 180 days | U49: Processed date | V49: 2026-03 March | W49: ORTHO | AA49: 1 | AB49: 1433.32 | AC49: 0 | AD49: 0 | AE49: 46204 | AF49: 1433.32 | AG49: 157 | AH49: M4316 | AI49: M4726 | AJ49: M5416 | AK49: M4120 | AM49: MCCUNNIFF, PETER | AN49: ASAP Surgery Centers North Valley LLC | AO49: 46197
A50: =IFERROR(IF(INDEX([3]BH!$A$2:$A$32,MATCH($D50,[3]BH!$D$2:$D$32,0))="","",INDEX([3]BH!$A$2:$A$32,MATCH($D50,[3]BH!$D$2:$D$32,0))),"") -> Denied | B50: =IFERROR(IF(INDEX([3]BH!$B$2:$B$32,MATCH($D50,[3]BH!$D$2:$D$32,0))="","",INDEX([3]BH!$B$2:$B$32,MATCH($D50,[3]BH!$D$2:$D$32,0))),"") -> Optum has no record of 99492 - that code was billed to UHC, not Optum - Resubmitted with 99492 | C50: =IFERROR(IF(INDEX([3]BH!$C$2:$C$32,MATCH($D50,[3]BH!$D$2:$D$32,0))="","",INDEX([3]BH!$C$2:$C$32,MATCH($D50,[3]BH!$D$2:$D$32,0))),"") -> 46141 | D50: 551769931 | E50: HF372010397 | F50: 46086 | G50: Optum Care Medical Network of Arizona, Utah, & Washington (LifePrint) | H50: Optum Care Medical Network of Arizona, Utah, & Washington (LifePrint) | I50: No Payer | J50: 99493 x1; 99494 x1 | K50: =IFERROR(IF(INDEX([3]BH!$K$2:$K$32,MATCH($D50,[3]BH!$D$2:$D$32,0))="","",INDEX([3]BH!$K$2:$K$32,MATCH($D50,[3]BH!$D$2:$D$32,0))),"") -> 46265 | L50: =IF($O50="","",$O50-TODAY()) -> -128 | M50: =IF(AND(TRIM($A50)="Finalized",$K50<>""),"",IF($C50="","",$C50+365-TODAY())) -> 202 | N50: =IF(AND(TRIM($A50)="Finalized",$K50<>""),"",IF($C50="","",$C50+365-TODAY())) -> 202 | O50: =IF(AND(TRIM($A50)="Finalized",$K50<>""),"",DATE(2026,6,3)) -> 46176 | P50: 90 days | Q50: OPTUM | R50: 365 days | S50: Processed date | T50: 365 days | U50: Processed date | V50: 2026-03 March | W50: BH | AA50: 1 | AB50: 1372.91 | AC50: 0 | AD50: 0 | AE50: 46141 | AF50: 1372.91 | AG50: 156 | AH50: F1190 | AM50: LEATHEM, JARRETT | AN50: ASAP - DEER VALLEY | AO50: 46119
A51: =IFERROR(IF(INDEX([3]BH!$A$2:$A$32,MATCH($D51,[3]BH!$D$2:$D$32,0))="","",INDEX([3]BH!$A$2:$A$32,MATCH($D51,[3]BH!$D$2:$D$32,0))),"") -> Denied | B51: =IFERROR(IF(INDEX([3]BH!$B$2:$B$32,MATCH($D51,[3]BH!$D$2:$D$32,0))="","",INDEX([3]BH!$B$2:$B$32,MATCH($D51,[3]BH!$D$2:$D$32,0))),"") -> Corrected rendering provider, and resubmitted | C51: =IFERROR(IF(INDEX([3]BH!$C$2:$C$32,MATCH($D51,[3]BH!$D$2:$D$32,0))="","",INDEX([3]BH!$C$2:$C$32,MATCH($D51,[3]BH!$D$2:$D$32,0))),"") -> 46121 | D51: 551874008 | E51: HF515864933 | F51: 46087 | G51: Optum Care Medical Network of Arizona, Utah, & Washington (LifePrint) | H51: Optum Care Medical Network of Arizona, Utah, & Washington (LifePrint) | I51: No Payer | J51: 99494 x1; 99492 x1 | K51: =IFERROR(IF(INDEX([3]BH!$K$2:$K$32,MATCH($D51,[3]BH!$D$2:$D$32,0))="","",INDEX([3]BH!$K$2:$K$32,MATCH($D51,[3]BH!$D$2:$D$32,0))),"") -> 46265 | L51: =IF($O51="","",$O51-TODAY()) -> -127 | M51: =IF(AND(TRIM($A51)="Finalized",$K51<>""),"",IF($C51="","",$C51+365-TODAY())) -> 182 | N51: =IF(AND(TRIM($A51)="Finalized",$K51<>""),"",IF($C51="","",$C51+365-TODAY())) -> 182 | O51: =IF(AND(TRIM($A51)="Finalized",$K51<>""),"",DATE(2026,6,4)) -> 46177 | P51: 90 days | Q51: OPTUM | R51: 365 days | S51: Processed date | T51: 365 days | U51: Processed date | V51: 2026-03 March | W51: BH | AA51: 1 | AB51: 1426.25 | AC51: 0 | AD51: 0 | AE51: 46121 | AF51: 1426.25 | AG51: 155 | AH51: F4320 | AM51: KRAUSE, JEFFREY | AN51: ASAP - DEER VALLEY | AO51: 46119
A52: =IFERROR(IF(INDEX([3]BH!$A$2:$A$32,MATCH($D52,[3]BH!$D$2:$D$32,0))="","",INDEX([3]BH!$A$2:$A$32,MATCH($D52,[3]BH!$D$2:$D$32,0))),"") -> Pending | B52: =IFERROR(IF(INDEX([3]BH!$B$2:$B$32,MATCH($D52,[3]BH!$D$2:$D$32,0))="","",INDEX([3]BH!$B$2:$B$32,MATCH($D52,[3]BH!$D$2:$D$32,0))),"") -> secondary - Rep Gloria C - Ins started the refund request - Rep sent claim back to have it reprocessed - Ref # 188336955 - Ticket # SF20260903906271400 - TAT 30 bd - OP by secondary insurance | C52: =IFERROR(IF(INDEX([3]BH!$C$2:$C$32,MATCH($D52,[3]BH!$D$2:$D$32,0))="","",INDEX([3]BH!$C$2:$C$32,MATCH($D52,[3]BH!$D$2:$D$32,0))),"") -> 46196 | D52: 551830492 | E52: HF417864409 | F52: 46087 | G52: UnitedHealthcare Community Plan / Arizona Long Term Care | H52: United Healthcare | I52: UnitedHealthcare Community Plan / Arizona Long Term Care | J52: 99492 x1; 99494 x1 | K52: =IFERROR(IF(INDEX([3]BH!$K$2:$K$32,MATCH($D52,[3]BH!$D$2:$D$32,0))="","",INDEX([3]BH!$K$2:$K$32,MATCH($D52,[3]BH!$D$2:$D$32,0))),"") -> 46268 | L52: =IF($O52="","",$O52-TODAY()) -> -127 | M52: =IF(AND(TRIM($A52)="Finalized",$K52<>""),"",IF($C52="","",$C52+180-TODAY())) -> 72 | N52: =IF(AND(TRIM($A52)="Finalized",$K52<>""),"",IF($C52="","",$C52+365-TODAY())) -> 257 | O52: =IF(AND(TRIM($A52)="Finalized",$K52<>""),"",DATE(2026,6,4)) -> 46177 | P52: 90 days | Q52: UHC COMMERCIAL | R52: 180 days | S52: Processed date | T52: 365 days | U52: Processed date | V52: 2026-03 March | W52: BH | AA52: 1 | AB52: 1426.25 | AC52: 1223.69 | AD52: 354.8 | AE52: 46196 | AF52: -152.24 | AG52: 155 | AH52: F39 | AL52: 560056768 | AM52: LEATHEM, JARRETT | AN52: ASAP - Gilbert | AO52: 46119
A53: =IFERROR(IF(INDEX([3]ORTHO!$A$2:$A$16,MATCH($D53,[3]ORTHO!$D$2:$D$16,0))="","",INDEX([3]ORTHO!$A$2:$A$16,MATCH($D53,[3]ORTHO!$D$2:$D$16,0))),"") -> Denied | B53: =IFERROR(IF(INDEX([3]ORTHO!$B$2:$B$16,MATCH($D53,[3]ORTHO!$D$2:$D$16,0))="","",INDEX([3]ORTHO!$B$2:$B$16,MATCH($D53,[3]ORTHO!$D$2:$D$16,0))),"") -> Adjusted balance - Auth only included 62330 - DND 63047 missing auth | C53: =IFERROR(IF(INDEX([3]ORTHO!$C$2:$C$16,MATCH($D53,[3]ORTHO!$D$2:$D$16,0))="","",INDEX([3]ORTHO!$C$2:$C$16,MATCH($D53,[3]ORTHO!$D$2:$D$16,0))),"") -> 46097 | D53: 551964467 | E53: HF490461961 | F53: 46087 | G53: Humana Gold Plus HMO | H53: Humana Gold Plus HMO | I53: No Payer | J53: 63047 x1 | K53: =IFERROR(IF(INDEX([3]ORTHO!$K$2:$K$16,MATCH($D53,[3]ORTHO!$D$2:$D$16,0))="","",INDEX([3]ORTHO!$K$2:$K$16,MATCH($D53,[3]ORTHO!$D$2:$D$16,0))),"") -> 46279 | L53: =IF($O53="","",$O53-TODAY()) -> -127 | M53: =IF(AND(TRIM($A53)="Finalized",$K53<>""),"",IF($F53="","",$F53+90-TODAY())) -> -127 | N53: =IF(AND(TRIM($A53)="Finalized",$K53<>""),"",IF($C53="","",$C53+540-TODAY())) -> 333 | O53: =IF(AND(TRIM($A53)="Finalized",$K53<>""),"",DATE(2026,6,4)) -> 46177 | P53: 90 days | Q53: HUMANA MA | R53: 90 days | S53: Date of service | T53: 540 days | U53: Processed date | V53: 2026-03 March | W53: ORTHO | AA53: 1 | AB53: 7623.07 | AC53: 0 | AD53: 0 | AE53: 46097 | AF53: 7623.07 | AG53: 155 | AH53: M48062 | AM53: MORALES, DAVID | AN53: ASAP Surgery Centers North Valley LLC | AO53: 46091
A54: =IFERROR(IF(INDEX([2]ORTHO!$A$2:$A$11,MATCH($D54,[2]ORTHO!$D$2:$D$11,0))="","",INDEX([2]ORTHO!$A$2:$A$11,MATCH($D54,[2]ORTHO!$D$2:$D$11,0))),"") -> Denied | B54: =IFERROR(IF(INDEX([2]ORTHO!$B$2:$B$11,MATCH($D54,[2]ORTHO!$D$2:$D$11,0))="","",INDEX([2]ORTHO!$B$2:$B$11,MATCH($D54,[2]ORTHO!$D$2:$D$11,0))),"") -> Filed appeal # Z264AZW09999 on portal - Basis: add-on to auth'd/paid 63047, intraop findings. Op note attached - Add-on 63048 requires auth according to medicaid auth tool - Auth # OP4987640976 didn't include 63048 - DND 63048 due to missing auth | C54: =IFERROR(IF(INDEX([2]ORTHO!$C$2:$C$11,MATCH($D54,[2]ORTHO!$D$2:$D$11,0))="","",INDEX([2]ORTHO!$C$2:$C$11,MATCH($D54,[2]ORTHO!$D$2:$D$11,0))),"") -> 46218 | D54: 564578362 | E54: HF496014369 | F54: 46057 | G54: Arizona Complete Health (Centene) | H54: Arizona Complete Health (Centene) | I54: No Payer | J54: 63048 x1 | K54: =IFERROR(IF(INDEX([2]ORTHO!$K$2:$K$11,MATCH($D54,[2]ORTHO!$D$2:$D$11,0))="","",INDEX([2]ORTHO!$K$2:$K$11,MATCH($D54,[2]ORTHO!$D$2:$D$11,0))),"") -> 46285 | L54: =IF($O54="","",$O54-TODAY()) -> -127 | M54: =IF(AND(TRIM($A54)="Finalized",$K54<>""),"",IF($F54="","",$F54+365-TODAY())) -> 118 | N54: =IF(AND(TRIM($A54)="Finalized",$K54<>""),"",IF($F54="","",$F54+365-TODAY())) -> 118 | O54: =IF(AND(TRIM($A54)="Finalized",$K54<>""),"",DATE(2026,6,4)) -> 46177 | P54: 120 days | Q54: AZ COMPLETE | R54: 365 days | S54: Date of service | T54: 365 days | U54: Date of service | V54: 2026-02 February | W54: ORTHO | AA54: 1 | AB54: 1433.32 | AC54: 0 | AD54: 0 | AE54: 46218 | AF54: 1433.32 | AG54: 185 | AH54: M48062 | AI54: M51370 | AM54: MCCUNNIFF, PETER | AN54: ASAP Surgery Centers North Valley LLC | AO54: 46077
A55: =IFERROR(IF(INDEX([3]ORTHO!$A$2:$A$16,MATCH($D55,[3]ORTHO!$D$2:$D$16,0))="","",INDEX([3]ORTHO!$A$2:$A$16,MATCH($D55,[3]ORTHO!$D$2:$D$16,0))),"") -> PAID | B55: =IFERROR(IF(INDEX([3]ORTHO!$B$2:$B$16,MATCH($D55,[3]ORTHO!$D$2:$D$16,0))="","",INDEX([3]ORTHO!$B$2:$B$16,MATCH($D55,[3]ORTHO!$D$2:$D$16,0))),"") -> PENDING POSTING | C55: =IFERROR(IF(INDEX([3]ORTHO!$C$2:$C$16,MATCH($D55,[3]ORTHO!$D$2:$D$16,0))="","",INDEX([3]ORTHO!$C$2:$C$16,MATCH($D55,[3]ORTHO!$D$2:$D$16,0))),"") -> 46203 | D55: 553643849 | E55: HF537038069 | F55: 46087 | G55: Blue Cross Blue Shield of Arizona (BCBS AZ) | H55: Blue Cross Blue Shield of Arizona (BCBS AZ) | I55: No Payer | J55: 22853 x1; 22551 x1; 22845+59 x1 | K55: =IFERROR(IF(INDEX([3]ORTHO!$K$2:$K$16,MATCH($D55,[3]ORTHO!$D$2:$D$16,0))="","",INDEX([3]ORTHO!$K$2:$K$16,MATCH($D55,[3]ORTHO!$D$2:$D$16,0))),"") | L55: =IF($O55="","",$O55-TODAY()) -> -127 | M55: =IF(AND(TRIM($A55)="Finalized",$K55<>""),"",IF($F55="","",$F55+90-TODAY())) -> -127 | N55: =IF(AND(TRIM($A55)="Finalized",$K55<>""),"",IF($C55="","",$C55+365-TODAY())) -> 264 | O55: =IF(AND(TRIM($A55)="Finalized",$K55<>""),"",DATE(2026,6,4)) -> 46177 | P55: 90 days | Q55: BCBS | R55: 90 days | S55: Date of service | T55: 365 days | U55: Processed date | V55: 2026-03 March | W55: ORTHO | X55: 59 | AA55: 1 | AB55: 18400.34 | AC55: 0 | AD55: 0 | AF55: 18400.34 | AG55: 155 | AH55: M4802 | AI55: M50021 | AM55: MAYURAN, VIKRAM | AN55: Banner Desert Medical Center | AO55: 46197
A56: =IFERROR(IF(INDEX([3]BH!$A$2:$A$32,MATCH($D56,[3]BH!$D$2:$D$32,0))="","",INDEX([3]BH!$A$2:$A$32,MATCH($D56,[3]BH!$D$2:$D$32,0))),"") -> Denied | B56: =IFERROR(IF(INDEX([3]BH!$B$2:$B$32,MATCH($D56,[3]BH!$D$2:$D$32,0))="","",INDEX([3]BH!$B$2:$B$32,MATCH($D56,[3]BH!$D$2:$D$32,0))),"") -> Resubmitted to Alignment active on DOS | C56: =IFERROR(IF(INDEX([3]BH!$C$2:$C$32,MATCH($D56,[3]BH!$D$2:$D$32,0))="","",INDEX([3]BH!$C$2:$C$32,MATCH($D56,[3]BH!$D$2:$D$32,0))),"") -> 46121 | D56: 552405449 | E56: HF509386349 | F56: 46092 | G56: Optum Care Medical Network of Arizona, Utah, & Washington (LifePrint) | H56: Optum Care Medical Network of Arizona, Utah, & Washington (LifePrint) | I56: No Payer | J56: 99492 x1; 99494 x1 | K56: =IFERROR(IF(INDEX([3]BH!$K$2:$K$32,MATCH($D56,[3]BH!$D$2:$D$32,0))="","",INDEX([3]BH!$K$2:$K$32,MATCH($D56,[3]BH!$D$2:$D$32,0))),"") -> 46257 | L56: =IF($O56="","",$O56-TODAY()) -> -122 | M56: =IF(AND(TRIM($A56)="Finalized",$K56<>""),"",IF($C56="","",$C56+365-TODAY())) -> 182 | N56: =IF(AND(TRIM($A56)="Finalized",$K56<>""),"",IF($C56="","",$C56+365-TODAY())) -> 182 | O56: =IF(AND(TRIM($A56)="Finalized",$K56<>""),"",DATE(2026,6,9)) -> 46182 | P56: 90 days | Q56: OPTUM | R56: 365 days | S56: Processed date | T56: 365 days | U56: Processed date | V56: 2026-03 March | W56: BH | AA56: 1 | AB56: 1426.25 | AC56: 0 | AD56: 0 | AE56: 46121 | AF56: 1426.25 | AG56: 150 | AH56: F1190 | AM56: O'NEIL, ROY | AN56: ASAP - DEER VALLEY | AO56: 46119
A57: =IFERROR(IF(INDEX([3]ORTHO!$A$2:$A$16,MATCH($D57,[3]ORTHO!$D$2:$D$16,0))="","",INDEX([3]ORTHO!$A$2:$A$16,MATCH($D57,[3]ORTHO!$D$2:$D$16,0))),"") -> Denied | B57: =IFERROR(IF(INDEX([3]ORTHO!$B$2:$B$16,MATCH($D57,[3]ORTHO!$D$2:$D$16,0))="","",INDEX([3]ORTHO!$B$2:$B$16,MATCH($D57,[3]ORTHO!$D$2:$D$16,0))),"") -> Jess resubmitted claim on 08/31/2026 | C57: =IFERROR(IF(INDEX([3]ORTHO!$C$2:$C$16,MATCH($D57,[3]ORTHO!$D$2:$D$16,0))="","",INDEX([3]ORTHO!$C$2:$C$16,MATCH($D57,[3]ORTHO!$D$2:$D$16,0))),"") -> 46108 | D57: 553652690 | E57: HF495165589 | F57: 46093 | G57: Humana Gold Plus HMO | H57: Humana Gold Plus HMO | I57: No Payer | J57: 22853 x1; 22845+59 x1; 22551 x1 | K57: =IFERROR(IF(INDEX([3]ORTHO!$K$2:$K$16,MATCH($D57,[3]ORTHO!$D$2:$D$16,0))="","",INDEX([3]ORTHO!$K$2:$K$16,MATCH($D57,[3]ORTHO!$D$2:$D$16,0))),"") -> 46265 | L57: =IF($O57="","",$O57-TODAY()) -> -121 | M57: =IF(AND(TRIM($A57)="Finalized",$K57<>""),"",IF($F57="","",$F57+90-TODAY())) -> -121 | N57: =IF(AND(TRIM($A57)="Finalized",$K57<>""),"",IF($C57="","",$C57+540-TODAY())) -> 344 | O57: =IF(AND(TRIM($A57)="Finalized",$K57<>""),"",DATE(2026,6,10)) -> 46183 | P57: 90 days | Q57: HUMANA MA | R57: 90 days | S57: Date of service | T57: 540 days | U57: Processed date | V57: 2026-03 March | W57: ORTHO | X57: 59 | AA57: 1 | AB57: 18400.34 | AC57: 0 | AD57: 0 | AE57: 46108 | AF57: 18400.34 | AG57: 149 | AH57: M5416 | AI57: M4317 | AM57: MAYURAN, VIKRAM | AN57: Banner Desert Medical Center | AO57: 46105
A58: =IFERROR(IF(INDEX([3]ORTHO!$A$2:$A$16,MATCH($D58,[3]ORTHO!$D$2:$D$16,0))="","",INDEX([3]ORTHO!$A$2:$A$16,MATCH($D58,[3]ORTHO!$D$2:$D$16,0))),"") -> Denied | B58: =IFERROR(IF(INDEX([3]ORTHO!$B$2:$B$16,MATCH($D58,[3]ORTHO!$D$2:$D$16,0))="","",INDEX([3]ORTHO!$B$2:$B$16,MATCH($D58,[3]ORTHO!$D$2:$D$16,0))),"") -> Uploaded op notes from 03/12/2026 to 03/15/2026 - Request ID 35165602 - DND incomplete documentation - Jess uploaded MR | C58: =IFERROR(IF(INDEX([3]ORTHO!$C$2:$C$16,MATCH($D58,[3]ORTHO!$D$2:$D$16,0))="","",INDEX([3]ORTHO!$C$2:$C$16,MATCH($D58,[3]ORTHO!$D$2:$D$16,0))),"") -> 46220 | D58: 553656838 | E58: HF536440270 | F58: 46093 | G58: Humana Gold Plus HMO | H58: Humana Gold Plus HMO | I58: No Payer | J58: 22853 x1; 22612 x1 | K58: =IFERROR(IF(INDEX([3]ORTHO!$K$2:$K$16,MATCH($D58,[3]ORTHO!$D$2:$D$16,0))="","",INDEX([3]ORTHO!$K$2:$K$16,MATCH($D58,[3]ORTHO!$D$2:$D$16,0))),"") -> 46279 | L58: =IF($O58="","",$O58-TODAY()) -> -121 | M58: =IF(AND(TRIM($A58)="Finalized",$K58<>""),"",IF($F58="","",$F58+90-TODAY())) -> -121 | N58: =IF(AND(TRIM($A58)="Finalized",$K58<>""),"",IF($C58="","",$C58+540-TODAY())) -> 456 | O58: =IF(AND(TRIM($A58)="Finalized",$K58<>""),"",DATE(2026,6,10)) -> 46183 | P58: 90 days | Q58: HUMANA MA | R58: 90 days | S58: Date of service | T58: 540 days | U58: Processed date | V58: 2026-03 March | W58: ORTHO | AA58: 1 | AB58: 12650.96 | AC58: 0 | AD58: 0 | AE58: 46220 | AF58: 12650.96 | AG58: 149 | AH58: M5416 | AI58: M48061 | AM58: MAYURAN, VIKRAM | AN58: Banner Desert Medical Center | AO58: 46105
A59: =IFERROR(IF(INDEX([3]ORTHO!$A$2:$A$16,MATCH($D59,[3]ORTHO!$D$2:$D$16,0))="","",INDEX([3]ORTHO!$A$2:$A$16,MATCH($D59,[3]ORTHO!$D$2:$D$16,0))),"") -> Denied | B59: =IFERROR(IF(INDEX([3]ORTHO!$B$2:$B$16,MATCH($D59,[3]ORTHO!$D$2:$D$16,0))="","",INDEX([3]ORTHO!$B$2:$B$16,MATCH($D59,[3]ORTHO!$D$2:$D$16,0))),"") -> Uploaded MR - PIQ-90849065 | C59: =IFERROR(IF(INDEX([3]ORTHO!$C$2:$C$16,MATCH($D59,[3]ORTHO!$D$2:$D$16,0))="","",INDEX([3]ORTHO!$C$2:$C$16,MATCH($D59,[3]ORTHO!$D$2:$D$16,0))),"") -> 46127 | D59: 555351211 | E59: HF404885397 | F59: 46093 | G59: UnitedHealthcare Community Plan / Arizona Long Term Care | H59: UnitedHealthcare Community Plan / Arizona Long Term Care | I59: No Payer | J59: 63655 x1; 63685 x1 | K59: =IFERROR(IF(INDEX([3]ORTHO!$K$2:$K$16,MATCH($D59,[3]ORTHO!$D$2:$D$16,0))="","",INDEX([3]ORTHO!$K$2:$K$16,MATCH($D59,[3]ORTHO!$D$2:$D$16,0))),"") -> 46279 | L59: =IF($O59="","",$O59-TODAY()) -> -121 | M59: =IF(AND(TRIM($A59)="Finalized",$K59<>""),"",IF($C59="","",$C59+180-TODAY())) -> 3 | N59: =IF(AND(TRIM($A59)="Finalized",$K59<>""),"",IF($C59="","",$C59+365-TODAY())) -> 188 | O59: =IF(AND(TRIM($A59)="Finalized",$K59<>""),"",DATE(2026,6,10)) -> 46183 | P59: 90 days | Q59: UHC COMMUNITY | R59: 180 days | S59: Processed date | T59: 365 days | U59: Processed date | V59: 2026-03 March | W59: ORTHO | AA59: 1 | AB59: 8277.57 | AC59: 0 | AD59: 0 | AE59: 46127 | AF59: 8277.57 | AG59: 149 | AH59: M961 | AI59: M5416 | AM59: LUKE, TIMOTHY | AN59: ASAP Surgery Centers North Valley LLC | AO59: 46120
A60: =IFERROR(IF(INDEX([3]BH!$A$2:$A$32,MATCH($D60,[3]BH!$D$2:$D$32,0))="","",INDEX([3]BH!$A$2:$A$32,MATCH($D60,[3]BH!$D$2:$D$32,0))),"") -> Denied | B60: =IFERROR(IF(INDEX([3]BH!$B$2:$B$32,MATCH($D60,[3]BH!$D$2:$D$32,0))="","",INDEX([3]BH!$B$2:$B$32,MATCH($D60,[3]BH!$D$2:$D$32,0))),"") -> Edited insured's info, and resubmitted - DND Remark: Patient/Insured health identification number and name do not match | C60: =IFERROR(IF(INDEX([3]BH!$C$2:$C$32,MATCH($D60,[3]BH!$D$2:$D$32,0))="","",INDEX([3]BH!$C$2:$C$32,MATCH($D60,[3]BH!$D$2:$D$32,0))),"") -> 46135 | D60: 552859864 | E60: HF492208813 | F60: 46097 | G60: Blue Cross Blue Shield of Arizona (BCBS AZ) | H60: Blue Cross Blue Shield of Arizona (BCBS AZ) | I60: Blue Cross Blue Shield of Arizona (BCBS AZ) | J60: 99494 x1; 99492 x1 | K60: =IFERROR(IF(INDEX([3]BH!$K$2:$K$32,MATCH($D60,[3]BH!$D$2:$D$32,0))="","",INDEX([3]BH!$K$2:$K$32,MATCH($D60,[3]BH!$D$2:$D$32,0))),"") -> 46268 | L60: =IF($O60="","",$O60-TODAY()) -> -117 | M60: =IF(AND(TRIM($A60)="Finalized",$K60<>""),"",IF($F60="","",$F60+90-TODAY())) -> -117 | N60: =IF(AND(TRIM($A60)="Finalized",$K60<>""),"",IF($C60="","",$C60+365-TODAY())) -> 196 | O60: =IF(AND(TRIM($A60)="Finalized",$K60<>""),"",DATE(2026,6,14)) -> 46187 | P60: 90 days | Q60: BCBS | R60: 90 days | S60: Date of service | T60: 365 days | U60: Processed date | V60: 2026-03 March | W60: BH | AA60: 1 | AB60: 1426.25 | AC60: 0 | AD60: 0 | AE60: 46135 | AF60: 1426.25 | AG60: 145 | AH60: F1190 | AI60: F411 | AM60: MEARS, CHAD | AN60: ASAP Peoria | AO60: 46119
A61: =IFERROR(IF(INDEX([3]US!$A$2:$A$15,MATCH($D61,[3]US!$D$2:$D$15,0))="","",INDEX([3]US!$A$2:$A$15,MATCH($D61,[3]US!$D$2:$D$15,0))),"") -> Denied | B61: =IFERROR(IF(INDEX([3]US!$B$2:$B$15,MATCH($D61,[3]US!$D$2:$D$15,0))="","",INDEX([3]US!$B$2:$B$15,MATCH($D61,[3]US!$D$2:$D$15,0))),"") -> Resubmitted to UHC as primary - DND This care may be covered by another payer per coordination of benefits | C61: =IFERROR(IF(INDEX([3]US!$C$2:$C$15,MATCH($D61,[3]US!$D$2:$D$15,0))="","",INDEX([3]US!$C$2:$C$15,MATCH($D61,[3]US!$D$2:$D$15,0))),"") -> 46135 | D61: 571607238 | E61: HF470511781 | F61: 46098 | G61: United Healthcare | H61: United Healthcare | I61: Blue Cross Blue Shield of Arizona (BCBS AZ) | J61: 93970 x1 | K61: =IFERROR(IF(INDEX([3]US!$K$2:$K$15,MATCH($D61,[3]US!$D$2:$D$15,0))="","",INDEX([3]US!$K$2:$K$15,MATCH($D61,[3]US!$D$2:$D$15,0))),"") -> 46278 | L61: =IF($O61="","",$O61-TODAY()) -> -116 | M61: =IF(AND(TRIM($A61)="Finalized",$K61<>""),"",IF($C61="","",$C61+180-TODAY())) -> 11 | N61: =IF(AND(TRIM($A61)="Finalized",$K61<>""),"",IF($C61="","",$C61+365-TODAY())) -> 196 | O61: =IF(AND(TRIM($A61)="Finalized",$K61<>""),"",DATE(2026,6,15)) -> 46188 | P61: 90 days | Q61: UHC COMMERCIAL | R61: 180 days | S61: Processed date | T61: 365 days | U61: Processed date | V61: 2026-03 March | W61: US | AA61: 1 | AB61: 1294.23 | AC61: 0 | AD61: 0 | AE61: 46135 | AF61: 1294.23 | AG61: 144 | AH61: M5412 | AI61: R609 | AM61: LEATHEM, JARRETT | AN61: ASAP - Gilbert | AO61: 46119
A62: =IFERROR(IF(INDEX([3]US!$A$2:$A$15,MATCH($D62,[3]US!$D$2:$D$15,0))="","",INDEX([3]US!$A$2:$A$15,MATCH($D62,[3]US!$D$2:$D$15,0))),"") -> Denied | B62: =IFERROR(IF(INDEX([3]US!$B$2:$B$15,MATCH($D62,[3]US!$D$2:$D$15,0))="","",INDEX([3]US!$B$2:$B$15,MATCH($D62,[3]US!$D$2:$D$15,0))),"") -> Corrected cpt codes, added code 7, and resubmitted | C62: =IFERROR(IF(INDEX([3]US!$C$2:$C$15,MATCH($D62,[3]US!$D$2:$D$15,0))="","",INDEX([3]US!$C$2:$C$15,MATCH($D62,[3]US!$D$2:$D$15,0))),"") -> 46146 | D62: 571612561 | E62: HF505830380 | F62: 46098 | G62: AARP MedicareComplete (SecureHorizons & Oxford Network) | H62: AARP MedicareComplete (SecureHorizons & Oxford Network) | I62: No Payer | J62: 93970 x1; 93923 x1; 93925 x1 | K62: =IFERROR(IF(INDEX([3]US!$K$2:$K$15,MATCH($D62,[3]US!$D$2:$D$15,0))="","",INDEX([3]US!$K$2:$K$15,MATCH($D62,[3]US!$D$2:$D$15,0))),"") -> 46278 | L62: =IF($O62="","",$O62-TODAY()) -> -116 | M62: =IF(AND(TRIM($A62)="Finalized",$K62<>""),"",IF($C62="","",$C62+365-TODAY())) -> 207 | N62: =IF(AND(TRIM($A62)="Finalized",$K62<>""),"",IF($C62="","",$C62+365-TODAY())) -> 207 | O62: =IF(AND(TRIM($A62)="Finalized",$K62<>""),"",DATE(2026,6,15)) -> 46188 | P62: 90 days | Q62: AARP MA CHOICE / MEDICARE COMPLETE | R62: 365 days | S62: Processed date | T62: 365 days | U62: Processed date | V62: 2026-03 March | W62: US | AA62: 1 | AB62: 3822.49 | AC62: 0 | AD62: 0 | AE62: 46146 | AF62: 3822.49 | AG62: 144 | AH62: M79604 | AI62: M79605 | AJ62: R600 | AM62: LEATHEM, JARRETT | AN62: ASAP - Gilbert | AO62: 46106
A63: =IFERROR(IF(INDEX([3]BH!$A$2:$A$32,MATCH($D63,[3]BH!$D$2:$D$32,0))="","",INDEX([3]BH!$A$2:$A$32,MATCH($D63,[3]BH!$D$2:$D$32,0))),"") -> Denied | B63: =IFERROR(IF(INDEX([3]BH!$B$2:$B$32,MATCH($D63,[3]BH!$D$2:$D$32,0))="","",INDEX([3]BH!$B$2:$B$32,MATCH($D63,[3]BH!$D$2:$D$32,0))),"") -> Added Date of Current Illness, claim note, and resubmitted | C63: =IFERROR(IF(INDEX([3]BH!$C$2:$C$32,MATCH($D63,[3]BH!$D$2:$D$32,0))="","",INDEX([3]BH!$C$2:$C$32,MATCH($D63,[3]BH!$D$2:$D$32,0))),"") -> 46167 | D63: 553148506 | E63: HF341023592 | F63: 46099 | G63: Optum Care Medical Network of Arizona, Utah, & Washington (LifePrint) | H63: Optum Care Medical Network of Arizona, Utah, & Washington (LifePrint) | I63: No Payer | J63: 99493 x1; 99494 x1 | K63: =IFERROR(IF(INDEX([3]BH!$K$2:$K$32,MATCH($D63,[3]BH!$D$2:$D$32,0))="","",INDEX([3]BH!$K$2:$K$32,MATCH($D63,[3]BH!$D$2:$D$32,0))),"") -> 46265 | L63: =IF($O63="","",$O63-TODAY()) -> -115 | M63: =IF(AND(TRIM($A63)="Finalized",$K63<>""),"",IF($C63="","",$C63+365-TODAY())) -> 228 | N63: =IF(AND(TRIM($A63)="Finalized",$K63<>""),"",IF($C63="","",$C63+365-TODAY())) -> 228 | O63: =IF(AND(TRIM($A63)="Finalized",$K63<>""),"",DATE(2026,6,16)) -> 46189 | P63: 90 days | Q63: OPTUM | R63: 365 days | S63: Processed date | T63: 365 days | U63: Processed date | V63: 2026-03 March | W63: BH | AA63: 1 | AB63: 1372.91 | AC63: 0 | AD63: 0 | AE63: 46167 | AF63: 1372.91 | AG63: 143 | AH63: F331 | AI63: F411 | AM63: TURLEY, TODD | AN63: ASAP - Gilbert | AO63: 46153
A64: =IFERROR(IF(INDEX([3]BH!$A$2:$A$32,MATCH($D64,[3]BH!$D$2:$D$32,0))="","",INDEX([3]BH!$A$2:$A$32,MATCH($D64,[3]BH!$D$2:$D$32,0))),"") -> Denied | B64: =IFERROR(IF(INDEX([3]BH!$B$2:$B$32,MATCH($D64,[3]BH!$D$2:$D$32,0))="","",INDEX([3]BH!$B$2:$B$32,MATCH($D64,[3]BH!$D$2:$D$32,0))),"") -> Filed reconsideration with the 02/27/2026 order notes for BHE prior to SCS trial + March 2026 Monthly Review Summary - PIQ-90338069 - Jess uploaded MR | C64: =IFERROR(IF(INDEX([3]BH!$C$2:$C$32,MATCH($D64,[3]BH!$D$2:$D$32,0))="","",INDEX([3]BH!$C$2:$C$32,MATCH($D64,[3]BH!$D$2:$D$32,0))),"") -> 46161 | D64: 553133483 | E64: HF542079660 | F64: 46099 | G64: United Healthcare | H64: United Healthcare | I64: No Payer | J64: 99492 x1; 99494 x1 | K64: =IFERROR(IF(INDEX([3]BH!$K$2:$K$32,MATCH($D64,[3]BH!$D$2:$D$32,0))="","",INDEX([3]BH!$K$2:$K$32,MATCH($D64,[3]BH!$D$2:$D$32,0))),"") -> 46268 | L64: =IF($O64="","",$O64-TODAY()) -> -115 | M64: =IF(AND(TRIM($A64)="Finalized",$K64<>""),"",IF($C64="","",$C64+180-TODAY())) -> 37 | N64: =IF(AND(TRIM($A64)="Finalized",$K64<>""),"",IF($C64="","",$C64+365-TODAY())) -> 222 | O64: =IF(AND(TRIM($A64)="Finalized",$K64<>""),"",DATE(2026,6,16)) -> 46189 | P64: 90 days | Q64: UHC COMMERCIAL | R64: 180 days | S64: Processed date | T64: 365 days | U64: Processed date | V64: 2026-03 March | W64: BH | AA64: 1 | AB64: 1426.25 | AC64: 0 | AD64: 0 | AE64: 46161 | AF64: 1426.25 | AG64: 143 | AH64: F39 | AM64: O'NEIL, ROY | AN64: ASAP - Gilbert | AO64: 46119
A65: =IFERROR(IF(INDEX([3]US!$A$2:$A$15,MATCH($D65,[3]US!$D$2:$D$15,0))="","",INDEX([3]US!$A$2:$A$15,MATCH($D65,[3]US!$D$2:$D$15,0))),"") -> Not found | B65: =IFERROR(IF(INDEX([3]US!$B$2:$B$15,MATCH($D65,[3]US!$D$2:$D$15,0))="","",INDEX([3]US!$B$2:$B$15,MATCH($D65,[3]US!$D$2:$D$15,0))),"") -> secondary - Resubmitted to Tricare for life - claim sent to tricare west and cant be locate it on Availity | C65: =IFERROR(IF(INDEX([3]US!$C$2:$C$15,MATCH($D65,[3]US!$D$2:$D$15,0))="","",INDEX([3]US!$C$2:$C$15,MATCH($D65,[3]US!$D$2:$D$15,0))),"") -> 46114 | D65: 553857983 | E65: HF546700195 | F65: 46099 | G65: Tricare West | H65: CIGNA HealthSprings | I65: Tricare West | J65: 93925 x1 | K65: =IFERROR(IF(INDEX([3]US!$K$2:$K$15,MATCH($D65,[3]US!$D$2:$D$15,0))="","",INDEX([3]US!$K$2:$K$15,MATCH($D65,[3]US!$D$2:$D$15,0))),"") -> 46278 | L65: =IF($O65="","",$O65-TODAY()) -> -115 | M65: =IF(AND(TRIM($A65)="Finalized",$K65<>""),"",IF($F65="","",$F65+90-TODAY())) -> -115 | N65: =IF(AND(TRIM($A65)="Finalized",$K65<>""),"",IF($C65="","",$C65+180-TODAY())) -> -10 | O65: =IF(AND(TRIM($A65)="Finalized",$K65<>""),"",DATE(2026,6,16)) -> 46189 | P65: 90 days | Q65: CIGNA / CIGNA MEDICARE | R65: 90 days | S65: Date of service | T65: 180 days | U65: Processed date | V65: 2026-03 March | W65: US | AA65: 1 | AB65: 1649.2 | AC65: 1420.82 | AD65: 160.93 | AE65: 46114 | AF65: 67.45 | AG65: 143 | AH65: I70213 | AL65: 571607938 | AM65: BURGHER, ABRAM | AN65: ASAP - Surprise - Reems | AO65: 46106
A66: =IFERROR(IF(INDEX([3]US!$A$2:$A$15,MATCH($D66,[3]US!$D$2:$D$15,0))="","",INDEX([3]US!$A$2:$A$15,MATCH($D66,[3]US!$D$2:$D$15,0))),"") -> Under Review | B66: =IFERROR(IF(INDEX([3]US!$B$2:$B$15,MATCH($D66,[3]US!$D$2:$D$15,0))="","",INDEX([3]US!$B$2:$B$15,MATCH($D66,[3]US!$D$2:$D$15,0))),"") -> I need to ask Juan for MR | C66: =IFERROR(IF(INDEX([3]US!$C$2:$C$15,MATCH($D66,[3]US!$D$2:$D$15,0))="","",INDEX([3]US!$C$2:$C$15,MATCH($D66,[3]US!$D$2:$D$15,0))),"") -> 46220 | D66: 553063753 | E66: HF419953579 | F66: 46099 | G66: Humana Gold Plus HMO | H66: Humana Gold Plus HMO | I66: No Payer | J66: 93970 x1; 93923 x1; 93925 x1 | K66: =IFERROR(IF(INDEX([3]US!$K$2:$K$15,MATCH($D66,[3]US!$D$2:$D$15,0))="","",INDEX([3]US!$K$2:$K$15,MATCH($D66,[3]US!$D$2:$D$15,0))),"") | L66: =IF($O66="","",$O66-TODAY()) -> -115 | M66: =IF(AND(TRIM($A66)="Finalized",$K66<>""),"",IF($F66="","",$F66+90-TODAY())) -> -115 | N66: =IF(AND(TRIM($A66)="Finalized",$K66<>""),"",IF($C66="","",$C66+540-TODAY())) -> 456 | O66: =IF(AND(TRIM($A66)="Finalized",$K66<>""),"",DATE(2026,6,16)) -> 46189 | P66: 90 days | Q66: HUMANA MA | R66: 90 days | S66: Date of service | T66: 540 days | U66: Processed date | V66: 2026-03 March | W66: US | AA66: 1 | AB66: 3822.49 | AC66: 0 | AD66: 0 | AE66: 46220 | AF66: 3822.49 | AG66: 143 | AH66: M47816 | AI66: M47817 | AJ66: Z79891 | AK66: I872 | AM66: ADLER, STEVEN | AN66: ASAP - DEER VALLEY | AO66: 46125
A67: =IFERROR(IF(INDEX([3]BH!$A$2:$A$32,MATCH($D67,[3]BH!$D$2:$D$32,0))="","",INDEX([3]BH!$A$2:$A$32,MATCH($D67,[3]BH!$D$2:$D$32,0))),"") -> PAID | B67: =IFERROR(IF(INDEX([3]BH!$B$2:$B$32,MATCH($D67,[3]BH!$D$2:$D$32,0))="","",INDEX([3]BH!$B$2:$B$32,MATCH($D67,[3]BH!$D$2:$D$32,0))),"") -> Duplicate payment - checks VP3502669763 and 5533489. VP3502669763 not found in NGO or Optum. Posting team notified to review - possible OP | C67: =IFERROR(IF(INDEX([3]BH!$C$2:$C$32,MATCH($D67,[3]BH!$D$2:$D$32,0))="","",INDEX([3]BH!$C$2:$C$32,MATCH($D67,[3]BH!$D$2:$D$32,0))),"") -> 46185 | D67: 553362911 | E67: HF550612373 | F67: 46101 | G67: Optum Care Medical Network of Arizona, Utah, & Washington (LifePrint) | H67: Optum Care Medical Network of Arizona, Utah, & Washington (LifePrint) | I67: No Payer | J67: 99492 x1; 99494 x1 | K67: =IFERROR(IF(INDEX([3]BH!$K$2:$K$32,MATCH($D67,[3]BH!$D$2:$D$32,0))="","",INDEX([3]BH!$K$2:$K$32,MATCH($D67,[3]BH!$D$2:$D$32,0))),"") -> 46266 | L67: =IF($O67="","",$O67-TODAY()) -> -113 | M67: =IF(AND(TRIM($A67)="Finalized",$K67<>""),"",IF($C67="","",$C67+365-TODAY())) -> 246 | N67: =IF(AND(TRIM($A67)="Finalized",$K67<>""),"",IF($C67="","",$C67+365-TODAY())) -> 246 | O67: =IF(AND(TRIM($A67)="Finalized",$K67<>""),"",DATE(2026,6,18)) -> 46191 | P67: 90 days | Q67: OPTUM | R67: 365 days | S67: Processed date | T67: 365 days | U67: Processed date | V67: 2026-03 March | W67: BH | AA67: 1 | AB67: 1426.25 | AC67: 1245.54 | AD67: 361.42 | AE67: 46185 | AF67: -180.71 | AG67: 141 | AH67: F4320 | AM67: MEARS, CHAD | AN67: ASAP - DEER VALLEY | AO67: 46119
A68: =IFERROR(IF(INDEX([3]BH!$A$2:$A$32,MATCH($D68,[3]BH!$D$2:$D$32,0))="","",INDEX([3]BH!$A$2:$A$32,MATCH($D68,[3]BH!$D$2:$D$32,0))),"") -> Under Review | B68: =IFERROR(IF(INDEX([3]BH!$B$2:$B$32,MATCH($D68,[3]BH!$D$2:$D$32,0))="","",INDEX([3]BH!$B$2:$B$32,MATCH($D68,[3]BH!$D$2:$D$32,0))),"") -> Sent email to AZ Blue for insights - active coverage on DOS - DND Expenses incurred after coverage terminated | C68: =IFERROR(IF(INDEX([3]BH!$C$2:$C$32,MATCH($D68,[3]BH!$D$2:$D$32,0))="","",INDEX([3]BH!$C$2:$C$32,MATCH($D68,[3]BH!$D$2:$D$32,0))),"") -> 46124 | D68: 553498942 | E68: HF549281205 | F68: 46101 | G68: Blue Cross Blue Shield of Arizona (BCBS AZ) | H68: Blue Cross Blue Shield of Arizona (BCBS AZ) | I68: No Payer | J68: 99494 x1; 99492 x1 | K68: =IFERROR(IF(INDEX([3]BH!$K$2:$K$32,MATCH($D68,[3]BH!$D$2:$D$32,0))="","",INDEX([3]BH!$K$2:$K$32,MATCH($D68,[3]BH!$D$2:$D$32,0))),"") -> 46268 | L68: =IF($O68="","",$O68-TODAY()) -> -113 | M68: =IF(AND(TRIM($A68)="Finalized",$K68<>""),"",IF($F68="","",$F68+90-TODAY())) -> -113 | N68: =IF(AND(TRIM($A68)="Finalized",$K68<>""),"",IF($C68="","",$C68+365-TODAY())) -> 185 | O68: =IF(AND(TRIM($A68)="Finalized",$K68<>""),"",DATE(2026,6,18)) -> 46191 | P68: 90 days | Q68: BCBS | R68: 90 days | S68: Date of service | T68: 365 days | U68: Processed date | V68: 2026-03 March | W68: BH | AA68: 1 | AB68: 1426.25 | AC68: 0 | AD68: 0 | AE68: 46124 | AF68: 1426.25 | AG68: 141 | AH68: F4320 | AM68: MORALES, DAVID | AN68: ASAP - DEER VALLEY | AO68: 46119
A69: =IFERROR(IF(INDEX([3]US!$A$2:$A$15,MATCH($D69,[3]US!$D$2:$D$15,0))="","",INDEX([3]US!$A$2:$A$15,MATCH($D69,[3]US!$D$2:$D$15,0))),"") -> Denied | B69: =IFERROR(IF(INDEX([3]US!$B$2:$B$15,MATCH($D69,[3]US!$D$2:$D$15,0))="","",INDEX([3]US!$B$2:$B$15,MATCH($D69,[3]US!$D$2:$D$15,0))),"") -> Resubmitted to the same payer - Active coverage on DOS - DND Expenses incurred after coverage terminated | C69: =IFERROR(IF(INDEX([3]US!$C$2:$C$15,MATCH($D69,[3]US!$D$2:$D$15,0))="","",INDEX([3]US!$C$2:$C$15,MATCH($D69,[3]US!$D$2:$D$15,0))),"") -> 46126 | D69: 571608266 | E69: HF545494297 | F69: 46105 | G69: Optum Care Medical Network of Arizona, Utah, & Washington (LifePrint) | H69: Optum Care Medical Network of Arizona, Utah, & Washington (LifePrint) | I69: No Payer | J69: 93970 x1 | K69: =IFERROR(IF(INDEX([3]US!$K$2:$K$15,MATCH($D69,[3]US!$D$2:$D$15,0))="","",INDEX([3]US!$K$2:$K$15,MATCH($D69,[3]US!$D$2:$D$15,0))),"") -> 46278 | L69: =IF($O69="","",$O69-TODAY()) -> -109 | M69: =IF(AND(TRIM($A69)="Finalized",$K69<>""),"",IF($C69="","",$C69+365-TODAY())) -> 187 | N69: =IF(AND(TRIM($A69)="Finalized",$K69<>""),"",IF($C69="","",$C69+365-TODAY())) -> 187 | O69: =IF(AND(TRIM($A69)="Finalized",$K69<>""),"",DATE(2026,6,22)) -> 46195 | P69: 90 days | Q69: OPTUM | R69: 365 days | S69: Processed date | T69: 365 days | U69: Processed date | V69: 2026-03 March | W69: US | AA69: 1 | AB69: 1294.23 | AC69: 0 | AD69: 0 | AE69: 46126 | AF69: 1294.23 | AG69: 137 | AH69: M1712 | AI69: G894 | AJ69: E785 | AM69: LEATHEM, JARRETT | AN69: ASAP - Gilbert | AO69: 46121
A70: =IFERROR(IF(INDEX([3]DME!$A$2:$A$11,MATCH($D70,[3]DME!$D$2:$D$11,0))="","",INDEX([3]DME!$A$2:$A$11,MATCH($D70,[3]DME!$D$2:$D$11,0))),"") -> Denied | B70: =IFERROR(IF(INDEX([3]DME!$B$2:$B$11,MATCH($D70,[3]DME!$D$2:$D$11,0))="","",INDEX([3]DME!$B$2:$B$11,MATCH($D70,[3]DME!$D$2:$D$11,0))),"") -> Uploaded MR - PIQ-92059096 | C70: =IFERROR(IF(INDEX([3]DME!$C$2:$C$11,MATCH($D70,[3]DME!$D$2:$D$11,0))="","",INDEX([3]DME!$C$2:$C$11,MATCH($D70,[3]DME!$D$2:$D$11,0))),"") -> 46216 | D70: 554940052 | E70: HF548742459 | F70: 46107 | G70: UnitedHealthcare / All Savers Insurance | H70: United Healthcare | I70: UnitedHealthcare / All Savers Insurance | J70: L0650+NU x1 | K70: =IFERROR(IF(INDEX([3]DME!$K$2:$K$11,MATCH($D70,[3]DME!$D$2:$D$11,0))="","",INDEX([3]DME!$K$2:$K$11,MATCH($D70,[3]DME!$D$2:$D$11,0))),"") -> 46300 | L70: =IF($O70="","",$O70-TODAY()) -> -107 | M70: =IF(AND(TRIM($A70)="Finalized",$K70<>""),"",IF($C70="","",$C70+180-TODAY())) -> 92 | N70: =IF(AND(TRIM($A70)="Finalized",$K70<>""),"",IF($C70="","",$C70+365-TODAY())) -> 277 | O70: =IF(AND(TRIM($A70)="Finalized",$K70<>""),"",DATE(2026,6,24)) -> 46197 | P70: 90 days | Q70: UHC COMMERCIAL | R70: 180 days | S70: Processed date | T70: 365 days | U70: Processed date | V70: 2026-03 March | W70: DME | X70: NU | AA70: 1 | AB70: 6392.96 | AC70: 5793.21 | AD70: 0 | AE70: 46216 | AF70: 599.75 | AG70: 135 | AH70: M5416 | AI70: M47896 | AJ70: M5489 | AL70: 561872992 | AM70: ADLER, STEVEN | AN70: ASAP - DEER VALLEY | AO70: 46118
A71: =IFERROR(IF(INDEX([3]BH!$A$2:$A$32,MATCH($D71,[3]BH!$D$2:$D$32,0))="","",INDEX([3]BH!$A$2:$A$32,MATCH($D71,[3]BH!$D$2:$D$32,0))),"") -> Denied | B71: =IFERROR(IF(INDEX([3]BH!$B$2:$B$32,MATCH($D71,[3]BH!$D$2:$D$32,0))="","",INDEX([3]BH!$B$2:$B$32,MATCH($D71,[3]BH!$D$2:$D$32,0))),"") -> Bundling with Claim ID 26F500108500 Line ID 1 on date of service 03/24/2026 CPT 64640 | C71: =IFERROR(IF(INDEX([3]BH!$C$2:$C$32,MATCH($D71,[3]BH!$D$2:$D$32,0))="","",INDEX([3]BH!$C$2:$C$32,MATCH($D71,[3]BH!$D$2:$D$32,0))),"") -> 46197 | D71: 563362114 | E71: HF481780302 | F71: 46108 | G71: UnitedHealthcare Community Plan / Arizona Long Term Care | H71: UnitedHealthcare Community Plan / Arizona Long Term Care | I71: No Payer | J71: 99494 x1; 99492+79 x1 | K71: =IFERROR(IF(INDEX([3]BH!$K$2:$K$32,MATCH($D71,[3]BH!$D$2:$D$32,0))="","",INDEX([3]BH!$K$2:$K$32,MATCH($D71,[3]BH!$D$2:$D$32,0))),"") -> 46148 | L71: =IF($O71="","",$O71-TODAY()) -> -106 | M71: =IF(AND(TRIM($A71)="Finalized",$K71<>""),"",IF($C71="","",$C71+180-TODAY())) -> 73 | N71: =IF(AND(TRIM($A71)="Finalized",$K71<>""),"",IF($C71="","",$C71+365-TODAY())) -> 258 | O71: =IF(AND(TRIM($A71)="Finalized",$K71<>""),"",DATE(2026,6,25)) -> 46198 | P71: 90 days | Q71: UHC COMMUNITY | R71: 180 days | S71: Processed date | T71: 365 days | U71: Processed date | V71: 2026-03 March | W71: BH | X71: 79 | AA71: 1 | AB71: 1426.25 | AC71: 0 | AD71: 0 | AE71: 46197 | AF71: 1426.25 | AG71: 134 | AH71: F1190 | AM71: LEATHEM, JARRETT | AN71: ASAP - Gilbert | AO71: 46119
A72: =IFERROR(IF(INDEX([3]BH!$A$2:$A$32,MATCH($D72,[3]BH!$D$2:$D$32,0))="","",INDEX([3]BH!$A$2:$A$32,MATCH($D72,[3]BH!$D$2:$D$32,0))),"") -> Denied | B72: =IFERROR(IF(INDEX([3]BH!$B$2:$B$32,MATCH($D72,[3]BH!$D$2:$D$32,0))="","",INDEX([3]BH!$B$2:$B$32,MATCH($D72,[3]BH!$D$2:$D$32,0))),"") -> Reprocess when claim 570543000 is paid | C72: =IFERROR(IF(INDEX([3]BH!$C$2:$C$32,MATCH($D72,[3]BH!$D$2:$D$32,0))="","",INDEX([3]BH!$C$2:$C$32,MATCH($D72,[3]BH!$D$2:$D$32,0))),"") -> 46141 | D72: 554088972 | E72: HF443112560 | F72: 46108 | G72: Optum Care Medical Network of Arizona, Utah, & Washington (LifePrint) | H72: Optum Care Medical Network of Arizona, Utah, & Washington (LifePrint) | I72: No Payer | J72: 99494 x1; 99493 x1 | K72: =IFERROR(IF(INDEX([3]BH!$K$2:$K$32,MATCH($D72,[3]BH!$D$2:$D$32,0))="","",INDEX([3]BH!$K$2:$K$32,MATCH($D72,[3]BH!$D$2:$D$32,0))),"") -> 46266 | L72: =IF($O72="","",$O72-TODAY()) -> -106 | M72: =IF(AND(TRIM($A72)="Finalized",$K72<>""),"",IF($C72="","",$C72+365-TODAY())) -> 202 | N72: =IF(AND(TRIM($A72)="Finalized",$K72<>""),"",IF($C72="","",$C72+365-TODAY())) -> 202 | O72: =IF(AND(TRIM($A72)="Finalized",$K72<>""),"",DATE(2026,6,25)) -> 46198 | P72: 90 days | Q72: OPTUM | R72: 365 days | S72: Processed date | T72: 365 days | U72: Processed date | V72: 2026-03 March | W72: BH | AA72: 1 | AB72: 1372.91 | AC72: 0 | AD72: 0 | AE72: 46141 | AF72: 1372.91 | AG72: 134 | AH72: F1190 | AM72: LEATHEM, JARRETT | AN72: ASAP - Gilbert | AO72: 46119
A73: =IFERROR(IF(INDEX([4]BH!$A$2:$A$12,MATCH($D73,[4]BH!$D$2:$D$12,0))="","",INDEX([4]BH!$A$2:$A$12,MATCH($D73,[4]BH!$D$2:$D$12,0))),"") -> Denied | B73: =IFERROR(IF(INDEX([4]BH!$B$2:$B$12,MATCH($D73,[4]BH!$D$2:$D$12,0))="","",INDEX([4]BH!$B$2:$B$12,MATCH($D73,[4]BH!$D$2:$D$12,0))),"") -> Jess resubmitted claim | C73: =IFERROR(IF(INDEX([4]BH!$C$2:$C$12,MATCH($D73,[4]BH!$D$2:$D$12,0))="","",INDEX([4]BH!$C$2:$C$12,MATCH($D73,[4]BH!$D$2:$D$12,0))),"") -> 46162 | D73: 566720408 | E73: HF537685966 | F73: 46113 | G73: Blue Cross Blue Shield of Arizona (BCBS AZ) | H73: Blue Cross Blue Shield of Arizona (BCBS AZ) | I73: Medicare Part B Arizona * | J73: 99494 x1; 99493 x1 | K73: =IFERROR(IF(INDEX([4]BH!$K$2:$K$12,MATCH($D73,[4]BH!$D$2:$D$12,0))="","",INDEX([4]BH!$K$2:$K$12,MATCH($D73,[4]BH!$D$2:$D$12,0))),"") -> 46231 | L73: =IF($O73="","",$O73-TODAY()) -> -101 | M73: =IF(AND(TRIM($A73)="Finalized",$K73<>""),"",IF($F73="","",$F73+90-TODAY())) -> -101 | N73: =IF(AND(TRIM($A73)="Finalized",$K73<>""),"",IF($C73="","",$C73+365-TODAY())) -> 223 | O73: =IF(AND(TRIM($A73)="Finalized",$K73<>""),"",DATE(2026,6,30)) -> 46203 | P73: 90 days | Q73: BCBS | R73: 90 days | S73: Date of service | T73: 365 days | U73: Processed date | V73: 2026-04 April | W73: BH | AA73: 1 | AB73: 1372.91 | AC73: 0 | AD73: 0 | AE73: 46162 | AF73: 1372.91 | AG73: 129 | AH73: F330 | AM73: BAUGHER, TIMOTHY | AN73: ASAP - Gilbert | AO73: 46153
A74: =IFERROR(IF(INDEX([4]ORTHO!$A$2:$A$21,MATCH($D74,[4]ORTHO!$D$2:$D$21,0))="","",INDEX([4]ORTHO!$A$2:$A$21,MATCH($D74,[4]ORTHO!$D$2:$D$21,0))),"") -> Denied | B74: =IFERROR(IF(INDEX([4]ORTHO!$B$2:$B$21,MATCH($D74,[4]ORTHO!$D$2:$D$21,0))="","",INDEX([4]ORTHO!$B$2:$B$21,MATCH($D74,[4]ORTHO!$D$2:$D$21,0))),"") -> Uploaded MR - PIQ-90772964 | C74: =IFERROR(IF(INDEX([4]ORTHO!$C$2:$C$21,MATCH($D74,[4]ORTHO!$D$2:$D$21,0))="","",INDEX([4]ORTHO!$C$2:$C$21,MATCH($D74,[4]ORTHO!$D$2:$D$21,0))),"") -> 46218 | D74: 556734047 | E74: HF531362064 | F74: 46113 | G74: UnitedHealthcare Community Plan / Arizona Long Term Care | H74: UnitedHealthcare Community Plan / Arizona Long Term Care | I74: No Payer | J74: 63047 x1; 63048 x1 | K74: =IFERROR(IF(INDEX([4]ORTHO!$K$2:$K$21,MATCH($D74,[4]ORTHO!$D$2:$D$21,0))="","",INDEX([4]ORTHO!$K$2:$K$21,MATCH($D74,[4]ORTHO!$D$2:$D$21,0))),"") -> 46278 | L74: =IF($O74="","",$O74-TODAY()) -> -101 | M74: =IF(AND(TRIM($A74)="Finalized",$K74<>""),"",IF($C74="","",$C74+180-TODAY())) -> 94 | N74: =IF(AND(TRIM($A74)="Finalized",$K74<>""),"",IF($C74="","",$C74+365-TODAY())) -> 279 | O74: =IF(AND(TRIM($A74)="Finalized",$K74<>""),"",DATE(2026,6,30)) -> 46203 | P74: 90 days | Q74: UHC COMMUNITY | R74: 180 days | S74: Processed date | T74: 365 days | U74: Processed date | V74: 2026-04 April | W74: ORTHO | AA74: 1 | AB74: 9056.39 | AC74: 0 | AD74: 0 | AE74: 46218 | AF74: 9056.39 | AG74: 129 | AH74: M5416, M4807 | AI74: M5116, M5417 | AJ74: M5126 | AM74: MCCUNNIFF, PETER | AN74: ASAP Surgery Centers North Valley LLC | AO74: 46146
A75: =IFERROR(IF(INDEX([4]US!$A$2:$A$23,MATCH($D75,[4]US!$D$2:$D$23,0))="","",INDEX([4]US!$A$2:$A$23,MATCH($D75,[4]US!$D$2:$D$23,0))),"") -> Denied | B75: =IFERROR(IF(INDEX([4]US!$B$2:$B$23,MATCH($D75,[4]US!$D$2:$D$23,0))="","",INDEX([4]US!$B$2:$B$23,MATCH($D75,[4]US!$D$2:$D$23,0))),"") -> Uploaded MR - PIQ-91107053 as per insurance request | C75: =IFERROR(IF(INDEX([4]US!$C$2:$C$23,MATCH($D75,[4]US!$D$2:$D$23,0))="","",INDEX([4]US!$C$2:$C$23,MATCH($D75,[4]US!$D$2:$D$23,0))),"") -> 46216 | D75: 558304247 | E75: HF535105976 | F75: 46114 | G75: UnitedHealthcare Community Plan / Arizona Long Term Care | H75: UnitedHealthcare Community Plan / Arizona Long Term Care | I75: Mercy Care Plan (AHCCCS) - Complete Care & Long Term Care (LTC) | J75: 93923 x1; 93970 x1 | K75: =IFERROR(IF(INDEX([4]US!$K$2:$K$23,MATCH($D75,[4]US!$D$2:$D$23,0))="","",INDEX([4]US!$K$2:$K$23,MATCH($D75,[4]US!$D$2:$D$23,0))),"") -> 46282 | L75: =IF($O75="","",$O75-TODAY()) -> -100 | M75: =IF(AND(TRIM($A75)="Finalized",$K75<>""),"",IF($C75="","",$C75+180-TODAY())) -> 92 | N75: =IF(AND(TRIM($A75)="Finalized",$K75<>""),"",IF($C75="","",$C75+365-TODAY())) -> 277 | O75: =IF(AND(TRIM($A75)="Finalized",$K75<>""),"",DATE(2026,7,1)) -> 46204 | P75: 90 days | Q75: UHC COMMUNITY | R75: 180 days | S75: Processed date | T75: 365 days | U75: Processed date | V75: 2026-04 April | W75: US | AA75: 1 | AB75: 2173.29 | AC75: 0 | AD75: 0 | AE75: 46218 | AF75: 2173.29 | AG75: 128 | AH75: E1140 | AI75: E785 | AJ75: I10 | AM75: TURLEY, TODD | AN75: ASAP - DEER VALLEY 240 | AO75: 46148
A76: =IFERROR(IF(INDEX([3]US!$A$2:$A$15,MATCH($D76,[3]US!$D$2:$D$15,0))="","",INDEX([3]US!$A$2:$A$15,MATCH($D76,[3]US!$D$2:$D$15,0))),"") -> Denied | B76: =IFERROR(IF(INDEX([3]US!$B$2:$B$15,MATCH($D76,[3]US!$D$2:$D$15,0))="","",INDEX([3]US!$B$2:$B$15,MATCH($D76,[3]US!$D$2:$D$15,0))),"") -> Edited dx codes, and resubmitted - DND due to invalid dx | C76: =IFERROR(IF(INDEX([3]US!$C$2:$C$15,MATCH($D76,[3]US!$D$2:$D$15,0))="","",INDEX([3]US!$C$2:$C$15,MATCH($D76,[3]US!$D$2:$D$15,0))),"") -> 46113 | D76: 553787632 | E76: HF442066976 | F76: 46085 | G76: Aetna Medicare PPO | H76: Aetna Medicare PPO | I76: No Payer | J76: 93970 x1; 93925 x1 | K76: =IFERROR(IF(INDEX([3]US!$K$2:$K$15,MATCH($D76,[3]US!$D$2:$D$15,0))="","",INDEX([3]US!$K$2:$K$15,MATCH($D76,[3]US!$D$2:$D$15,0))),"") -> 46282 | L76: =IF($O76="","",$O76-TODAY()) -> -99 | M76: =IF(AND(TRIM($A76)="Finalized",$K76<>""),"",IF($C76="","",$C76+180-TODAY())) -> -11 | N76: =IF(AND(TRIM($A76)="Finalized",$K76<>""),"",IF($C76="","",$C76+180-TODAY())) -> -11 | O76: =IF(AND(TRIM($A76)="Finalized",$K76<>""),"",DATE(2026,7,2)) -> 46205 | P76: 120 days | Q76: AETNA | R76: 180 days | S76: Processed date | T76: 180 days | U76: Processed date | V76: 2026-03 March | W76: US | AA76: 1 | AB76: 2943.43 | AC76: 0 | AD76: 0 | AE76: 46113 | AF76: 2943.43 | AG76: 157 | AH76: I70213 | AI76: I739 | AM76: BURGHER, ABRAM | AN76: ASAP - Surprise - Reems | AO76: 46106
A77: =IFERROR(IF(INDEX([4]DME!$A$2:$A$34,MATCH($D77,[4]DME!$D$2:$D$34,0))="","",INDEX([4]DME!$A$2:$A$34,MATCH($D77,[4]DME!$D$2:$D$34,0))),"") -> Denied | B77: =IFERROR(IF(INDEX([4]DME!$B$2:$B$34,MATCH($D77,[4]DME!$D$2:$D$34,0))="","",INDEX([4]DME!$B$2:$B$34,MATCH($D77,[4]DME!$D$2:$D$34,0))),"") -> Appeal form completed with MR and forwarded to April for fax submission to payer - Fax # 855-699-8985 | C77: =IFERROR(IF(INDEX([4]DME!$C$2:$C$34,MATCH($D77,[4]DME!$D$2:$D$34,0))="","",INDEX([4]DME!$C$2:$C$34,MATCH($D77,[4]DME!$D$2:$D$34,0))),"") -> 46197 | D77: 555586629 | E77: HF553228745 | F77: 46118 | G77: HealthSpring Medicare Advantage | H77: HealthSpring Medicare Advantage | I77: No Payer | J77: L0648+KX x1 | K77: =IFERROR(IF(INDEX([4]DME!$K$2:$K$34,MATCH($D77,[4]DME!$D$2:$D$34,0))="","",INDEX([4]DME!$K$2:$K$34,MATCH($D77,[4]DME!$D$2:$D$34,0))),"") -> 46300 | L77: =IF($O77="","",$O77-TODAY()) -> -96 | M77: =IF(AND(TRIM($A77)="Finalized",$K77<>""),"",IF($F77="","",$F77+90-TODAY())) -> -96 | N77: =IF(AND(TRIM($A77)="Finalized",$K77<>""),"",IF($C77="","",$C77+180-TODAY())) -> 73 | O77: =IF(AND(TRIM($A77)="Finalized",$K77<>""),"",DATE(2026,7,5)) -> 46208 | P77: 90 days | Q77: CIGNA / CIGNA MEDICARE | R77: 90 days | S77: Date of service | T77: 180 days | U77: Processed date | V77: 2026-04 April | W77: DME | X77: KX | AA77: 1 | AB77: 5492.55 | AC77: 0 | AD77: 0 | AE77: 46197 | AF77: 5492.55 | AG77: 124 | AH77: M8008XA | AM77: KALLGREN, MARK | AN77: ASAP - Mesa | AO77: 46134
A78: =IFERROR(IF(INDEX([4]GAE!$A$2:$A$8,MATCH($D78,[4]GAE!$D$2:$D$8,0))="","",INDEX([4]GAE!$A$2:$A$8,MATCH($D78,[4]GAE!$D$2:$D$8,0))),"") -> Under Review | B78: =IFERROR(IF(INDEX([4]GAE!$B$2:$B$8,MATCH($D78,[4]GAE!$D$2:$D$8,0))="","",INDEX([4]GAE!$B$2:$B$8,MATCH($D78,[4]GAE!$D$2:$D$8,0))),"") -> DND 75710 This procedure or procedure/modifier combination is not compatible with another procedure or procedure/modifier combination provided on the same day according to the National Correct Coding Initiative or workers compensation state regulations/ fee schedule requirements - Adjusted balance for 36246 not included in the auth requested - 36248 add on requires payment for other cpt code - 99153 cant be billed on pos 24 | C78: =IFERROR(IF(INDEX([4]GAE!$C$2:$C$8,MATCH($D78,[4]GAE!$D$2:$D$8,0))="","",INDEX([4]GAE!$C$2:$C$8,MATCH($D78,[4]GAE!$D$2:$D$8,0))),"") -> 46165 | D78: 558554119 | E78: HF517884474 | F78: 46118 | G78: Humana Gold Plus HMO | H78: Humana Gold Plus HMO | I78: No Payer | J78: 36248+59 x1; 75710+26+XU+LT x1; 36246+59+LT x1 | K78: =IFERROR(IF(INDEX([4]GAE!$K$2:$K$8,MATCH($D78,[4]GAE!$D$2:$D$8,0))="","",INDEX([4]GAE!$K$2:$K$8,MATCH($D78,[4]GAE!$D$2:$D$8,0))),"") | L78: =IF($O78="","",$O78-TODAY()) -> -96 | M78: =IF(AND(TRIM($A78)="Finalized",$K78<>""),"",IF($F78="","",$F78+90-TODAY())) -> -96 | N78: =IF(AND(TRIM($A78)="Finalized",$K78<>""),"",IF($C78="","",$C78+540-TODAY())) -> 401 | O78: =IF(AND(TRIM($A78)="Finalized",$K78<>""),"",DATE(2026,7,5)) -> 46208 | P78: 90 days | Q78: HUMANA MA | R78: 90 days | S78: Date of service | T78: 540 days | U78: Processed date | V78: 2026-04 April | W78: GAE | X78: 59, 26 | Y78: XU, LT | Z78: LT | AA78: 1 | AB78: 7585.97 | AC78: 0 | AD78: 0 | AE78: 46165 | AF78: 7585.97 | AG78: 124 | AH78: M1712 | AI78: I798 | AJ78: M25562 | AM78: HUNTER, DREW | AN78: Premier Endoscopy Center, LLC | AO78: 46149
A79: =IFERROR(IF(INDEX([5]ORTHO!$A$2:$A$24,MATCH($D79,[5]ORTHO!$D$2:$D$24,0))="","",INDEX([5]ORTHO!$A$2:$A$24,MATCH($D79,[5]ORTHO!$D$2:$D$24,0))),"") -> Under Review | B79: =IFERROR(IF(INDEX([5]ORTHO!$B$2:$B$24,MATCH($D79,[5]ORTHO!$D$2:$D$24,0))="","",INDEX([5]ORTHO!$B$2:$B$24,MATCH($D79,[5]ORTHO!$D$2:$D$24,0))),"") -> Call ins - Bundled - but we have an auth for this one | C79: =IFERROR(IF(INDEX([5]ORTHO!$C$2:$C$24,MATCH($D79,[5]ORTHO!$D$2:$D$24,0))="","",INDEX([5]ORTHO!$C$2:$C$24,MATCH($D79,[5]ORTHO!$D$2:$D$24,0))),"") -> 46162 | D79: 559115526 | E79: HF530195235 | F79: 46148 | G79: Devoted Health Plan | H79: Devoted Health Plan | I79: No Payer | J79: 63047 x1 | K79: =IFERROR(IF(INDEX([5]ORTHO!$K$2:$K$24,MATCH($D79,[5]ORTHO!$D$2:$D$24,0))="","",INDEX([5]ORTHO!$K$2:$K$24,MATCH($D79,[5]ORTHO!$D$2:$D$24,0))),"") | L79: =IF($O79="","",$O79-TODAY()) -> -96 | M79: =IF(AND(TRIM($A79)="Finalized",$K79<>""),"",IF($C79="","",$C79+365-TODAY())) -> 223 | N79: =IF(AND(TRIM($A79)="Finalized",$K79<>""),"",IF($C79="","",$C79+90-TODAY())) -> -52 | O79: =IF(AND(TRIM($A79)="Finalized",$K79<>""),"",DATE(2026,7,5)) -> 46208 | P79: 60 days | Q79: DEVOTED | R79: 365 days | S79: Processed date | T79: 90 days | U79: Processed date | V79: 2026-05 May | W79: ORTHO | AA79: 1 | AB79: 7623.07 | AC79: 0 | AD79: 0 | AE79: 46162 | AF79: 7623.07 | AG79: 94 | AH79: M48062 | AI79: M5416 | AM79: MAYURAN, VIKRAM | AN79: ASAP Surgery Centers North Valley LLC | AO79: 46155
A80: =IFERROR(IF(INDEX([4]US!$A$2:$A$23,MATCH($D80,[4]US!$D$2:$D$23,0))="","",INDEX([4]US!$A$2:$A$23,MATCH($D80,[4]US!$D$2:$D$23,0))),"") -> Denied | B80: =IFERROR(IF(INDEX([4]US!$B$2:$B$23,MATCH($D80,[4]US!$D$2:$D$23,0))="","",INDEX([4]US!$B$2:$B$23,MATCH($D80,[4]US!$D$2:$D$23,0))),"") -> Added mod XS to 93970, and resubmitted - Anthem Commercial Reimbursement Policy Number: C-23003 - secondary subject to MPPR rules | C80: =IFERROR(IF(INDEX([4]US!$C$2:$C$23,MATCH($D80,[4]US!$D$2:$D$23,0))="","",INDEX([4]US!$C$2:$C$23,MATCH($D80,[4]US!$D$2:$D$23,0))),"") -> 46164 | D80: 558637485 | E80: HF518562105 | F80: 46119 | G80: Blue Cross Blue Shield of Arizona (BCBS AZ) | H80: Blue Cross Blue Shield of Arizona (BCBS AZ) | I80: No Payer | J80: 93923 x1; 93970 x1 | K80: =IFERROR(IF(INDEX([4]US!$K$2:$K$23,MATCH($D80,[4]US!$D$2:$D$23,0))="","",INDEX([4]US!$K$2:$K$23,MATCH($D80,[4]US!$D$2:$D$23,0))),"") -> 46283 | L80: =IF($O80="","",$O80-TODAY()) -> -95 | M80: =IF(AND(TRIM($A80)="Finalized",$K80<>""),"",IF($F80="","",$F80+90-TODAY())) -> -95 | N80: =IF(AND(TRIM($A80)="Finalized",$K80<>""),"",IF($C80="","",$C80+365-TODAY())) -> 225 | O80: =IF(AND(TRIM($A80)="Finalized",$K80<>""),"",DATE(2026,7,6)) -> 46209 | P80: 90 days | Q80: BCBS | R80: 90 days | S80: Date of service | T80: 365 days | U80: Processed date | V80: 2026-04 April | W80: US | AA80: 1 | AB80: 2173.29 | AC80: 0 | AD80: 0 | AF80: 2173.29 | AG80: 123 | AH80: I83893 | AI80: I872 | AM80: LEATHEM, JARRETT | AN80: ASAP - Gilbert | AO80: 46140
A81: =IFERROR(IF(INDEX([4]US!$A$2:$A$23,MATCH($D81,[4]US!$D$2:$D$23,0))="","",INDEX([4]US!$A$2:$A$23,MATCH($D81,[4]US!$D$2:$D$23,0))),"") -> Denied | B81: =IFERROR(IF(INDEX([4]US!$B$2:$B$23,MATCH($D81,[4]US!$D$2:$D$23,0))="","",INDEX([4]US!$B$2:$B$23,MATCH($D81,[4]US!$D$2:$D$23,0))),"") -> Changed 93970 to 93971, and resubmitted | C81: =IFERROR(IF(INDEX([4]US!$C$2:$C$23,MATCH($D81,[4]US!$D$2:$D$23,0))="","",INDEX([4]US!$C$2:$C$23,MATCH($D81,[4]US!$D$2:$D$23,0))),"") -> 46184 | D81: 558308311 | E81: HF537684538 | F81: 46121 | G81: United Healthcare | H81: United Healthcare | I81: No Payer | J81: 93970 x1 | K81: =IFERROR(IF(INDEX([4]US!$K$2:$K$23,MATCH($D81,[4]US!$D$2:$D$23,0))="","",INDEX([4]US!$K$2:$K$23,MATCH($D81,[4]US!$D$2:$D$23,0))),"") -> 46278 | L81: =IF($O81="","",$O81-TODAY()) -> -93 | M81: =IF(AND(TRIM($A81)="Finalized",$K81<>""),"",IF($C81="","",$C81+180-TODAY())) -> 60 | N81: =IF(AND(TRIM($A81)="Finalized",$K81<>""),"",IF($C81="","",$C81+365-TODAY())) -> 245 | O81: =IF(AND(TRIM($A81)="Finalized",$K81<>""),"",DATE(2026,7,8)) -> 46211 | P81: 90 days | Q81: UHC COMMERCIAL | R81: 180 days | S81: Processed date | T81: 365 days | U81: Processed date | V81: 2026-04 April | W81: US | AA81: 1 | AB81: 1294.23 | AC81: 0 | AD81: 0 | AE81: 46184 | AF81: 1294.23 | AG81: 121 | AH81: M79605 | AI81: I82401 | AM81: TURLEY, TODD | AN81: ASAP - DEER VALLEY 240 | AO81: 46148
A82: =IFERROR(IF(INDEX([4]US!$A$2:$A$23,MATCH($D82,[4]US!$D$2:$D$23,0))="","",INDEX([4]US!$A$2:$A$23,MATCH($D82,[4]US!$D$2:$D$23,0))),"") -> Denied | B82: =IFERROR(IF(INDEX([4]US!$B$2:$B$23,MATCH($D82,[4]US!$D$2:$D$23,0))="","",INDEX([4]US!$B$2:$B$23,MATCH($D82,[4]US!$D$2:$D$23,0))),"") -> Uploaded MR - PIQ-90770826 | C82: =IFERROR(IF(INDEX([4]US!$C$2:$C$23,MATCH($D82,[4]US!$D$2:$D$23,0))="","",INDEX([4]US!$C$2:$C$23,MATCH($D82,[4]US!$D$2:$D$23,0))),"") -> 46224 | D82: 558638750 | E82: HF469471726 | F82: 46121 | G82: UnitedHealthcare Community Plan / Arizona Long Term Care | H82: UnitedHealthcare Community Plan / Arizona Long Term Care | I82: Mercy Care RBHA | J82: 93970 x1; 93925 x1; 93923 x1 | K82: =IFERROR(IF(INDEX([4]US!$K$2:$K$23,MATCH($D82,[4]US!$D$2:$D$23,0))="","",INDEX([4]US!$K$2:$K$23,MATCH($D82,[4]US!$D$2:$D$23,0))),"") -> 46278 | L82: =IF($O82="","",$O82-TODAY()) -> -93 | M82: =IF(AND(TRIM($A82)="Finalized",$K82<>""),"",IF($C82="","",$C82+180-TODAY())) -> 100 | N82: =IF(AND(TRIM($A82)="Finalized",$K82<>""),"",IF($C82="","",$C82+365-TODAY())) -> 285 | O82: =IF(AND(TRIM($A82)="Finalized",$K82<>""),"",DATE(2026,7,8)) -> 46211 | P82: 90 days | Q82: UHC COMMUNITY | R82: 180 days | S82: Processed date | T82: 365 days | U82: Processed date | V82: 2026-04 April | W82: US | AA82: 1 | AB82: 3822.49 | AC82: 0 | AD82: 0 | AE82: 46224 | AF82: 3822.49 | AG82: 121 | AH82: I70213 | AM82: TURLEY, TODD | AN82: ASAP - DEER VALLEY 240 | AO82: 46150
A83: =IFERROR(IF(INDEX([4]DME!$A$2:$A$34,MATCH($D83,[4]DME!$D$2:$D$34,0))="","",INDEX([4]DME!$A$2:$A$34,MATCH($D83,[4]DME!$D$2:$D$34,0))),"") -> Under Review | B83: =IFERROR(IF(INDEX([4]DME!$B$2:$B$34,MATCH($D83,[4]DME!$D$2:$D$34,0))="","",INDEX([4]DME!$B$2:$B$34,MATCH($D83,[4]DME!$D$2:$D$34,0))),"") -> Call 800-636-2123 - DND A6010 Preferred Homecare is responsible for these services. Please submit the claim to Preferred Homecare for consideration | C83: =IFERROR(IF(INDEX([4]DME!$C$2:$C$34,MATCH($D83,[4]DME!$D$2:$D$34,0))="","",INDEX([4]DME!$C$2:$C$34,MATCH($D83,[4]DME!$D$2:$D$34,0))),"") -> 46141 | D83: 556770603 | E83: HF329310676 | F83: 46121 | G83: UnitedHealthcare Community Plan / Arizona Long Term Care | H83: UnitedHealthcare Community Plan / Arizona Long Term Care | I83: No Payer | J83: A6010+A1 x10 | K83: =IFERROR(IF(INDEX([4]DME!$K$2:$K$34,MATCH($D83,[4]DME!$D$2:$D$34,0))="","",INDEX([4]DME!$K$2:$K$34,MATCH($D83,[4]DME!$D$2:$D$34,0))),"") | L83: =IF($O83="","",$O83-TODAY()) -> -93 | M83: =IF(AND(TRIM($A83)="Finalized",$K83<>""),"",IF($C83="","",$C83+180-TODAY())) -> 17 | N83: =IF(AND(TRIM($A83)="Finalized",$K83<>""),"",IF($C83="","",$C83+365-TODAY())) -> 202 | O83: =IF(AND(TRIM($A83)="Finalized",$K83<>""),"",DATE(2026,7,8)) -> 46211 | P83: 90 days | Q83: UHC COMMUNITY | R83: 180 days | S83: Processed date | T83: 365 days | U83: Processed date | V83: 2026-04 April | W83: DME | X83: A1 | AA83: 10 | AB83: 2958.2 | AC83: 0 | AD83: 0 | AE83: 46141 | AF83: 2958.2 | AG83: 121 | AH83: G894 | AI83: M5127 | AM83: MARTINEZ, DIANA | AN83: ASAP - DEER VALLEY | AO83: 46133
A84: =IFERROR(IF(INDEX([4]DME!$A$2:$A$34,MATCH($D84,[4]DME!$D$2:$D$34,0))="","",INDEX([4]DME!$A$2:$A$34,MATCH($D84,[4]DME!$D$2:$D$34,0))),"") -> Under Review | B84: =IFERROR(IF(INDEX([4]DME!$B$2:$B$34,MATCH($D84,[4]DME!$D$2:$D$34,0))="","",INDEX([4]DME!$B$2:$B$34,MATCH($D84,[4]DME!$D$2:$D$34,0))),"") -> Call 800-636-2123 - DND A6010 Preferred Homecare is responsible for these services. Please submit the claim to Preferred Homecare for consideration | C84: =IFERROR(IF(INDEX([4]DME!$C$2:$C$34,MATCH($D84,[4]DME!$D$2:$D$34,0))="","",INDEX([4]DME!$C$2:$C$34,MATCH($D84,[4]DME!$D$2:$D$34,0))),"") -> 46141 | D84: 556772233 | E84: HF537334664 | F84: 46122 | G84: UnitedHealthcare Community Plan / Arizona Long Term Care | H84: UnitedHealthcare Community Plan / Arizona Long Term Care | I84: Mercy Care Plan (AHCCCS) - Complete Care & Long Term Care (LTC) | J84: A6010+A2 x20 | K84: =IFERROR(IF(INDEX([4]DME!$K$2:$K$34,MATCH($D84,[4]DME!$D$2:$D$34,0))="","",INDEX([4]DME!$K$2:$K$34,MATCH($D84,[4]DME!$D$2:$D$34,0))),"") | L84: =IF($O84="","",$O84-TODAY()) -> -92 | M84: =IF(AND(TRIM($A84)="Finalized",$K84<>""),"",IF($C84="","",$C84+180-TODAY())) -> 17 | N84: =IF(AND(TRIM($A84)="Finalized",$K84<>""),"",IF($C84="","",$C84+365-TODAY())) -> 202 | O84: =IF(AND(TRIM($A84)="Finalized",$K84<>""),"",DATE(2026,7,9)) -> 46212 | P84: 90 days | Q84: UHC COMMUNITY | R84: 180 days | S84: Processed date | T84: 365 days | U84: Processed date | V84: 2026-04 April | W84: DME | X84: A2 | AA84: 20 | AB84: 5916.4 | AC84: 0 | AD84: 0 | AE84: 46141 | AF84: 5916.4 | AG84: 120 | AH84: G894 | AM84: ADLER, STEVEN | AN84: ASAP - DEER VALLEY | AO84: 46133
A85: =IFERROR(IF(INDEX([5]DME!$A$2:$A$35,MATCH($D85,[5]DME!$D$2:$D$35,0))="","",INDEX([5]DME!$A$2:$A$35,MATCH($D85,[5]DME!$D$2:$D$35,0))),"") -> Denied | B85: =IFERROR(IF(INDEX([5]DME!$B$2:$B$35,MATCH($D85,[5]DME!$D$2:$D$35,0))="","",INDEX([5]DME!$B$2:$B$35,MATCH($D85,[5]DME!$D$2:$D$35,0))),"") -> Shift to PT - ABN signed - Bundled remark - Rep Mark confirmed that Integra is the delegated DME vendor for this PT - Provider OON with Devoted - Ref # CALLX8R53SRA | C85: =IFERROR(IF(INDEX([5]DME!$C$2:$C$35,MATCH($D85,[5]DME!$D$2:$D$35,0))="","",INDEX([5]DME!$C$2:$C$35,MATCH($D85,[5]DME!$D$2:$D$35,0))),"") -> 46162 | D85: 559115746 | E85: HF530195235 | F85: 46153 | G85: Devoted Health Plan | H85: Devoted Health Plan | I85: No Payer | J85: A6023+A1 x20 | K85: =IFERROR(IF(INDEX([5]DME!$K$2:$K$35,MATCH($D85,[5]DME!$D$2:$D$35,0))="","",INDEX([5]DME!$K$2:$K$35,MATCH($D85,[5]DME!$D$2:$D$35,0))),"") -> 46255 | L85: =IF($O85="","",$O85-TODAY()) -> -91 | M85: =IF(AND(TRIM($A85)="Finalized",$K85<>""),"",IF($C85="","",$C85+365-TODAY())) -> 223 | N85: =IF(AND(TRIM($A85)="Finalized",$K85<>""),"",IF($C85="","",$C85+90-TODAY())) -> -52 | O85: =IF(AND(TRIM($A85)="Finalized",$K85<>""),"",DATE(2026,7,10)) -> 46213 | P85: 60 days | Q85: DEVOTED | R85: 365 days | S85: Processed date | T85: 90 days | U85: Processed date | V85: 2026-05 May | W85: DME | X85: A1 | AA85: 20 | AB85: 36353.8 | AC85: 0 | AD85: 0 | AE85: 46162 | AF85: 36353.8 | AG85: 89 | AH85: G894 | AM85: OROC, RENEE | AN85: ASAP Prescott Valley | AO85: 46155
A86: =IFERROR(IF(INDEX([4]DME!$A$2:$A$34,MATCH($D86,[4]DME!$D$2:$D$34,0))="","",INDEX([4]DME!$A$2:$A$34,MATCH($D86,[4]DME!$D$2:$D$34,0))),"") -> Under Review | B86: =IFERROR(IF(INDEX([4]DME!$B$2:$B$34,MATCH($D86,[4]DME!$D$2:$D$34,0))="","",INDEX([4]DME!$B$2:$B$34,MATCH($D86,[4]DME!$D$2:$D$34,0))),"") -> Checking with Bri - Dr. Awnik Sarkar OON with member's Independence Blue Cross PPO - Devereux Benefit Plan | C86: =IFERROR(IF(INDEX([4]DME!$C$2:$C$34,MATCH($D86,[4]DME!$D$2:$D$34,0))="","",INDEX([4]DME!$C$2:$C$34,MATCH($D86,[4]DME!$D$2:$D$34,0))),"") -> 46141 | D86: 556801807 | E86: HF331718997 | F86: 46125 | G86: Blue Cross Blue Shield of Arizona (BCBS AZ) | H86: Blue Cross Blue Shield of Arizona (BCBS AZ) | I86: No Payer | J86: A6010+A1 x10 | K86: =IFERROR(IF(INDEX([4]DME!$K$2:$K$34,MATCH($D86,[4]DME!$D$2:$D$34,0))="","",INDEX([4]DME!$K$2:$K$34,MATCH($D86,[4]DME!$D$2:$D$34,0))),"") | L86: =IF($O86="","",$O86-TODAY()) -> -89 | M86: =IF(AND(TRIM($A86)="Finalized",$K86<>""),"",IF($F86="","",$F86+90-TODAY())) -> -89 | N86: =IF(AND(TRIM($A86)="Finalized",$K86<>""),"",IF($C86="","",$C86+365-TODAY())) -> 202 | O86: =IF(AND(TRIM($A86)="Finalized",$K86<>""),"",DATE(2026,7,12)) -> 46215 | P86: 90 days | Q86: BCBS | R86: 90 days | S86: Date of service | T86: 365 days | U86: Processed date | V86: 2026-04 April | W86: DME | X86: A1 | AA86: 10 | AB86: 2958.2 | AC86: 0 | AD86: 0 | AE86: 46141 | AF86: 2958.2 | AG86: 117 | AH86: G894 | AI86: G588 | AM86: SARKAR, AWNIK | AN86: ASAP - Surprise - Reems | AO86: 46134
A87: =IFERROR(IF(INDEX([4]GAE!$A$2:$A$8,MATCH($D87,[4]GAE!$D$2:$D$8,0))="","",INDEX([4]GAE!$A$2:$A$8,MATCH($D87,[4]GAE!$D$2:$D$8,0))),"") -> Under Review | B87: =IFERROR(IF(INDEX([4]GAE!$B$2:$B$8,MATCH($D87,[4]GAE!$D$2:$D$8,0))="","",INDEX([4]GAE!$B$2:$B$8,MATCH($D87,[4]GAE!$D$2:$D$8,0))),"") -> DND 36248 due to exceeded MUE - DND 36245, 36246, and 75710 due to invalid dx | C87: =IFERROR(IF(INDEX([4]GAE!$C$2:$C$8,MATCH($D87,[4]GAE!$D$2:$D$8,0))="","",INDEX([4]GAE!$C$2:$C$8,MATCH($D87,[4]GAE!$D$2:$D$8,0))),"") -> 46162 | D87: 558686340 | E87: HF536642190 | F87: 46125 | G87: HealthSpring Medicare Advantage | H87: HealthSpring Medicare Advantage | I87: No Payer | J87: 75710+XU+LT x1; 36245+59 x1; 36248+59 x3; 36246+59+LT x1 | K87: =IFERROR(IF(INDEX([4]GAE!$K$2:$K$8,MATCH($D87,[4]GAE!$D$2:$D$8,0))="","",INDEX([4]GAE!$K$2:$K$8,MATCH($D87,[4]GAE!$D$2:$D$8,0))),"") | L87: =IF($O87="","",$O87-TODAY()) -> -89 | M87: =IF(AND(TRIM($A87)="Finalized",$K87<>""),"",IF($F87="","",$F87+90-TODAY())) -> -89 | N87: =IF(AND(TRIM($A87)="Finalized",$K87<>""),"",IF($C87="","",$C87+180-TODAY())) -> 38 | O87: =IF(AND(TRIM($A87)="Finalized",$K87<>""),"",DATE(2026,7,12)) -> 46215 | P87: 90 days | Q87: CIGNA / CIGNA MEDICARE | R87: 90 days | S87: Date of service | T87: 180 days | U87: Processed date | V87: 2026-04 April | W87: GAE | X87: XU, 59 | Y87: LT | AA87: 1, 3 | AB87: 17767.19 | AC87: 0 | AD87: 0 | AE87: 46162 | AF87: 17767.19 | AG87: 117 | AH87: M1712 | AI87: I798 | AJ87: M25562 | AM87: HUNTER, DREW | AN87: ASAP - DEER VALLEY | AO87: 46152
A88: =IFERROR(IF(INDEX([4]BH!$A$2:$A$12,MATCH($D88,[4]BH!$D$2:$D$12,0))="","",INDEX([4]BH!$A$2:$A$12,MATCH($D88,[4]BH!$D$2:$D$12,0))),"") -> Denied | B88: =IFERROR(IF(INDEX([4]BH!$B$2:$B$12,MATCH($D88,[4]BH!$D$2:$D$12,0))="","",INDEX([4]BH!$B$2:$B$12,MATCH($D88,[4]BH!$D$2:$D$12,0))),"") -> Waiting to post and adjust balance - DND The time limit for filing has expired - Added Date of Current Illness, claim note, and resubmitted | C88: =IFERROR(IF(INDEX([4]BH!$C$2:$C$12,MATCH($D88,[4]BH!$D$2:$D$12,0))="","",INDEX([4]BH!$C$2:$C$12,MATCH($D88,[4]BH!$D$2:$D$12,0))),"") -> 46262 | D88: 556413148 | E88: HF509386349 | F88: 46127 | G88: Optum Care Medical Network of Arizona, Utah, & Washington (LifePrint) | H88: Optum Care Medical Network of Arizona, Utah, & Washington (LifePrint) | I88: No Payer | J88: 99494 x2; 99493 x1 | K88: =IFERROR(IF(INDEX([4]BH!$K$2:$K$12,MATCH($D88,[4]BH!$D$2:$D$12,0))="","",INDEX([4]BH!$K$2:$K$12,MATCH($D88,[4]BH!$D$2:$D$12,0))),"") -> 46257 | L88: =IF($O88="","",$O88-TODAY()) -> -87 | M88: =IF(AND(TRIM($A88)="Finalized",$K88<>""),"",IF($C88="","",$C88+365-TODAY())) -> 323 | N88: =IF(AND(TRIM($A88)="Finalized",$K88<>""),"",IF($C88="","",$C88+365-TODAY())) -> 323 | O88: =IF(AND(TRIM($A88)="Finalized",$K88<>""),"",DATE(2026,7,14)) -> 46217 | P88: 90 days | Q88: OPTUM | R88: 365 days | S88: Processed date | T88: 365 days | U88: Processed date | V88: 2026-04 April | W88: BH | AA88: 2, 1 | AB88: 1769.18 | AC88: 0 | AD88: 0 | AF88: 1769.18 | AG88: 115 | AH88: F1190 | AM88: O'NEIL, ROY | AN88: ASAP - DEER VALLEY | AO88: 46153
A89: =IFERROR(IF(INDEX([4]ORTHO!$A$2:$A$21,MATCH($D89,[4]ORTHO!$D$2:$D$21,0))="","",INDEX([4]ORTHO!$A$2:$A$21,MATCH($D89,[4]ORTHO!$D$2:$D$21,0))),"") -> Denied | B89: =IFERROR(IF(INDEX([4]ORTHO!$B$2:$B$21,MATCH($D89,[4]ORTHO!$D$2:$D$21,0))="","",INDEX([4]ORTHO!$B$2:$B$21,MATCH($D89,[4]ORTHO!$D$2:$D$21,0))),"") -> Uploaded MR - PIQ-90772754 - Delete 20936, and resubmitted | C89: =IFERROR(IF(INDEX([4]ORTHO!$C$2:$C$21,MATCH($D89,[4]ORTHO!$D$2:$D$21,0))="","",INDEX([4]ORTHO!$C$2:$C$21,MATCH($D89,[4]ORTHO!$D$2:$D$21,0))),"") -> 46252 | D89: 556717576 | E89: HF525461225 | F89: 46127 | G89: UHC Group Medicare Advantage | H89: UHC Group Medicare Advantage | I89: No Payer | J89: 22845+59 x1; 22853+59 x1; 22551 x1; 22853 x1 | K89: =IFERROR(IF(INDEX([4]ORTHO!$K$2:$K$21,MATCH($D89,[4]ORTHO!$D$2:$D$21,0))="","",INDEX([4]ORTHO!$K$2:$K$21,MATCH($D89,[4]ORTHO!$D$2:$D$21,0))),"") -> 46278 | L89: =IF($O89="","",$O89-TODAY()) -> -87 | M89: =IF(AND(TRIM($A89)="Finalized",$K89<>""),"",IF($C89="","",$C89+180-TODAY())) -> 128 | N89: =IF(AND(TRIM($A89)="Finalized",$K89<>""),"",IF($C89="","",$C89+365-TODAY())) -> 313 | O89: =IF(AND(TRIM($A89)="Finalized",$K89<>""),"",DATE(2026,7,14)) -> 46217 | P89: 90 days | Q89: UHC MA | R89: 180 days | S89: Processed date | T89: 365 days | U89: Processed date | V89: 2026-04 April | W89: ORTHO | X89: 59 | AA89: 1 | AB89: 20158.46 | AC89: 0 | AD89: 0 | AF89: 20158.46 | AG89: 115 | AH89: M4802 | AI89: M5412 | AJ89: M542 | AM89: MCCUNNIFF, PETER | AN89: ASAP Surgery Centers North Valley LLC | AO89: 46197
A90: =IFERROR(IF(INDEX([4]DME!$A$2:$A$34,MATCH($D90,[4]DME!$D$2:$D$34,0))="","",INDEX([4]DME!$A$2:$A$34,MATCH($D90,[4]DME!$D$2:$D$34,0))),"") -> Denied | B90: =IFERROR(IF(INDEX([4]DME!$B$2:$B$34,MATCH($D90,[4]DME!$D$2:$D$34,0))="","",INDEX([4]DME!$B$2:$B$34,MATCH($D90,[4]DME!$D$2:$D$34,0))),"") -> Uploaded missing MR to PIQ-85007180 - Jess uploaded POD | C90: =IFERROR(IF(INDEX([4]DME!$C$2:$C$34,MATCH($D90,[4]DME!$D$2:$D$34,0))="","",INDEX([4]DME!$C$2:$C$34,MATCH($D90,[4]DME!$D$2:$D$34,0))),"") -> 46156 | D90: 561043971 | E90: HF550434312 | F90: 46128 | G90: UnitedHealthcare Community Plan / Arizona Long Term Care | H90: UnitedHealthcare Community Plan / Arizona Long Term Care | I90: No Payer | J90: L0650+NU x1 | K90: =IFERROR(IF(INDEX([4]DME!$K$2:$K$34,MATCH($D90,[4]DME!$D$2:$D$34,0))="","",INDEX([4]DME!$K$2:$K$34,MATCH($D90,[4]DME!$D$2:$D$34,0))),"") -> 46285 | L90: =IF($O90="","",$O90-TODAY()) -> -86 | M90: =IF(AND(TRIM($A90)="Finalized",$K90<>""),"",IF($C90="","",$C90+180-TODAY())) -> 32 | N90: =IF(AND(TRIM($A90)="Finalized",$K90<>""),"",IF($C90="","",$C90+365-TODAY())) -> 217 | O90: =IF(AND(TRIM($A90)="Finalized",$K90<>""),"",DATE(2026,7,15)) -> 46218 | P90: 90 days | Q90: UHC COMMUNITY | R90: 180 days | S90: Processed date | T90: 365 days | U90: Processed date | V90: 2026-04 April | W90: DME | X90: NU | AA90: 1 | AB90: 6392.96 | AC90: 0 | AD90: 0 | AE90: 46156 | AF90: 6392.96 | AG90: 114 | AH90: M5416 | AM90: LUKE, TIMOTHY | AN90: ASAP - DEER VALLEY | AO90: 46143
A91: =IFERROR(IF(INDEX([4]DME!$A$2:$A$34,MATCH($D91,[4]DME!$D$2:$D$34,0))="","",INDEX([4]DME!$A$2:$A$34,MATCH($D91,[4]DME!$D$2:$D$34,0))),"") -> Under Review | B91: =IFERROR(IF(INDEX([4]DME!$B$2:$B$34,MATCH($D91,[4]DME!$D$2:$D$34,0))="","",INDEX([4]DME!$B$2:$B$34,MATCH($D91,[4]DME!$D$2:$D$34,0))),"") -> Call 800-636-2123 - DND A6010 Preferred Homecare is responsible for these services. Please submit the claim to Preferred Homecare for consideration | C91: =IFERROR(IF(INDEX([4]DME!$C$2:$C$34,MATCH($D91,[4]DME!$D$2:$D$34,0))="","",INDEX([4]DME!$C$2:$C$34,MATCH($D91,[4]DME!$D$2:$D$34,0))),"") -> 46143 | D91: 565388312 | E91: HF523440375 | F91: 46128 | G91: UnitedHealthcare Community Plan / Arizona Long Term Care | H91: UnitedHealthcare Community Plan / Arizona Long Term Care | I91: No Payer | J91: A6010+A1 x20 | K91: =IFERROR(IF(INDEX([4]DME!$K$2:$K$34,MATCH($D91,[4]DME!$D$2:$D$34,0))="","",INDEX([4]DME!$K$2:$K$34,MATCH($D91,[4]DME!$D$2:$D$34,0))),"") | L91: =IF($O91="","",$O91-TODAY()) -> -86 | M91: =IF(AND(TRIM($A91)="Finalized",$K91<>""),"",IF($C91="","",$C91+180-TODAY())) -> 19 | N91: =IF(AND(TRIM($A91)="Finalized",$K91<>""),"",IF($C91="","",$C91+365-TODAY())) -> 204 | O91: =IF(AND(TRIM($A91)="Finalized",$K91<>""),"",DATE(2026,7,15)) -> 46218 | P91: 90 days | Q91: UHC COMMUNITY | R91: 180 days | S91: Processed date | T91: 365 days | U91: Processed date | V91: 2026-04 April | W91: DME | X91: A1 | AA91: 20 | AB91: 5916.4 | AC91: 0 | AD91: 0 | AE91: 46143 | AF91: 5916.4 | AG91: 114 | AH91: G894 | AI91: M5416 | AM91: HOLLISTER, ALICIA | AN91: ASAP - DEER VALLEY | AO91: 46134
A92: =IFERROR(IF(INDEX([3]BH!$A$2:$A$32,MATCH($D92,[3]BH!$D$2:$D$32,0))="","",INDEX([3]BH!$A$2:$A$32,MATCH($D92,[3]BH!$D$2:$D$32,0))),"") -> Pending | B92: =IFERROR(IF(INDEX([3]BH!$B$2:$B$32,MATCH($D92,[3]BH!$D$2:$D$32,0))="","",INDEX([3]BH!$B$2:$B$32,MATCH($D92,[3]BH!$D$2:$D$32,0))),"") -> Submitted to bcbs - BCBS is primary and banner aetna secondary - Removed mod 79 - Added mod 24, and resubmitted - Payer edits only allow 79/78/58 on surgical/procedural codes - 99492 is an E/M - DND The procedure code is inconsistent with the modifier used - Jess resubmitted with mod 79 - DND Bundling with Claim ID 26F500108500 Line ID 1 on date of service 03/24/2026 CPT 64640 | C92: =IFERROR(IF(INDEX([3]BH!$C$2:$C$32,MATCH($D92,[3]BH!$D$2:$D$32,0))="","",INDEX([3]BH!$C$2:$C$32,MATCH($D92,[3]BH!$D$2:$D$32,0))),"") -> 46184 | D92: 553283455 | E92: HF330559209 | F92: 46100 | G92: Banner Aetna | H92: Banner Aetna | I92: No Payer | J92: 99492 x1; 99494 x1 | K92: =IFERROR(IF(INDEX([3]BH!$K$2:$K$32,MATCH($D92,[3]BH!$D$2:$D$32,0))="","",INDEX([3]BH!$K$2:$K$32,MATCH($D92,[3]BH!$D$2:$D$32,0))),"") -> 46300 | L92: =IF($O92="","",$O92-TODAY()) -> -84 | M92: =IF(AND(TRIM($A92)="Finalized",$K92<>""),"",IF($C92="","",$C92+180-TODAY())) -> 60 | N92: =IF(AND(TRIM($A92)="Finalized",$K92<>""),"",IF($C92="","",$C92+180-TODAY())) -> 60 | O92: =IF(AND(TRIM($A92)="Finalized",$K92<>""),"",DATE(2026,7,17)) -> 46220 | P92: 120 days | Q92: BANNER HEALTH & AETNA | R92: 180 days | S92: Processed date | T92: 180 days | U92: Processed date | V92: 2026-03 March | W92: BH | AA92: 1 | AB92: 1426.25 | AC92: 0 | AD92: 0 | AE92: 46184 | AF92: 1426.25 | AG92: 142 | AH92: F4323 | AM92: O'NEIL, ROY | AN92: ASAP - DEER VALLEY | AO92: 46119
A93: =IFERROR(IF(INDEX([5]BH!$A$2:$A$33,MATCH($D93,[5]BH!$D$2:$D$33,0))="","",INDEX([5]BH!$A$2:$A$33,MATCH($D93,[5]BH!$D$2:$D$33,0))),"") -> Pending | B93: =IFERROR(IF(INDEX([5]BH!$B$2:$B$33,MATCH($D93,[5]BH!$D$2:$D$33,0))="","",INDEX([5]BH!$B$2:$B$33,MATCH($D93,[5]BH!$D$2:$D$33,0))),"") -> Requested Linda W. fax medical records to 480-499-8744 - TAT I have to send MR 08/18/2026 | C93: =IFERROR(IF(INDEX([5]BH!$C$2:$C$33,MATCH($D93,[5]BH!$D$2:$D$33,0))="","",INDEX([5]BH!$C$2:$C$33,MATCH($D93,[5]BH!$D$2:$D$33,0))),"") -> 46217 | D93: 559861642 | E93: HF554254508 | F93: 46161 | G93: Arizona Priority Care Plus | H93: Arizona Priority Care Plus | I93: No Payer | J93: 99494 x1; 99492 x1 | K93: =IFERROR(IF(INDEX([5]BH!$K$2:$K$33,MATCH($D93,[5]BH!$D$2:$D$33,0))="","",INDEX([5]BH!$K$2:$K$33,MATCH($D93,[5]BH!$D$2:$D$33,0))),"") -> 46247 | L93: =IF($O93="","",$O93-TODAY()) -> -83 | M93: =IF(AND(TRIM($A93)="Finalized",$K93<>""),"",IF($C93="","",$C93+365-TODAY())) -> 278 | N93: =IF(AND(TRIM($A93)="Finalized",$K93<>""),"",IF($C93="","",$C93+365-TODAY())) -> 278 | O93: =IF(AND(TRIM($A93)="Finalized",$K93<>""),"",DATE(2026,7,18)) -> 46221 | P93: 60 days | Q93: AZ PRIORITY CARE | R93: 365 days | S93: Processed date | T93: 365 days | U93: Processed date | V93: 2026-05 May | W93: BH | AA93: 1 | AB93: 1426.25 | AC93: 0 | AD93: 0 | AE93: 46217 | AF93: 1426.25 | AG93: 81 | AH93: F4320 | AM93: SARKAR, AWNIK | AN93: ASAP Peoria | AO93: 46181
A94: =IFERROR(IF(INDEX([3]ORTHO!$A$2:$A$16,MATCH($D94,[3]ORTHO!$D$2:$D$16,0))="","",INDEX([3]ORTHO!$A$2:$A$16,MATCH($D94,[3]ORTHO!$D$2:$D$16,0))),"") -> Pending | B94: =IFERROR(IF(INDEX([3]ORTHO!$B$2:$B$16,MATCH($D94,[3]ORTHO!$D$2:$D$16,0))="","",INDEX([3]ORTHO!$B$2:$B$16,MATCH($D94,[3]ORTHO!$D$2:$D$16,0))),"") -> secondary - Primary paid | C94: =IFERROR(IF(INDEX([3]ORTHO!$C$2:$C$16,MATCH($D94,[3]ORTHO!$D$2:$D$16,0))="","",INDEX([3]ORTHO!$C$2:$C$16,MATCH($D94,[3]ORTHO!$D$2:$D$16,0))),"") -> 46163 | D94: 553378154 | E94: HF518096784 | F94: 46101 | G94: Aetna Legacy | H94: Aetna Legacy | I94: No Payer | J94: 63047 x1 | K94: =IFERROR(IF(INDEX([3]ORTHO!$K$2:$K$16,MATCH($D94,[3]ORTHO!$D$2:$D$16,0))="","",INDEX([3]ORTHO!$K$2:$K$16,MATCH($D94,[3]ORTHO!$D$2:$D$16,0))),"") -> 46268 | L94: =IF($O94="","",$O94-TODAY()) -> -83 | M94: =IF(AND(TRIM($A94)="Finalized",$K94<>""),"",IF($C94="","",$C94+180-TODAY())) -> 39 | N94: =IF(AND(TRIM($A94)="Finalized",$K94<>""),"",IF($C94="","",$C94+180-TODAY())) -> 39 | O94: =IF(AND(TRIM($A94)="Finalized",$K94<>""),"",DATE(2026,7,18)) -> 46221 | P94: 120 days | Q94: AETNA | R94: 180 days | S94: Processed date | T94: 180 days | U94: Processed date | V94: 2026-03 March | W94: ORTHO | AA94: 1 | AB94: 7623.07 | AC94: 0 | AD94: 0 | AE94: 46163 | AF94: 7623.07 | AG94: 141 | AH94: M48062 | AM94: LEATHEM, JARRETT | AN94: Premier Endoscopy Center, LLC | AO94: 46105
A95: =IFERROR(IF(INDEX([4]BH!$A$2:$A$12,MATCH($D95,[4]BH!$D$2:$D$12,0))="","",INDEX([4]BH!$A$2:$A$12,MATCH($D95,[4]BH!$D$2:$D$12,0))),"") -> Denied | B95: =IFERROR(IF(INDEX([4]BH!$B$2:$B$12,MATCH($D95,[4]BH!$D$2:$D$12,0))="","",INDEX([4]BH!$B$2:$B$12,MATCH($D95,[4]BH!$D$2:$D$12,0))),"") -> Checking with our credentialing team - OON Provider Dr. Sarkar - DND No coverage | C95: =IFERROR(IF(INDEX([4]BH!$C$2:$C$12,MATCH($D95,[4]BH!$D$2:$D$12,0))="","",INDEX([4]BH!$C$2:$C$12,MATCH($D95,[4]BH!$D$2:$D$12,0))),"") -> 46157 | D95: 556564886 | E95: HF331718997 | F95: 46132 | G95: Blue Cross Blue Shield of Arizona (BCBS AZ) | H95: Blue Cross Blue Shield of Arizona (BCBS AZ) | I95: No Payer | J95: 99494 x1; 99493 x1 | K95: =IFERROR(IF(INDEX([4]BH!$K$2:$K$12,MATCH($D95,[4]BH!$D$2:$D$12,0))="","",INDEX([4]BH!$K$2:$K$12,MATCH($D95,[4]BH!$D$2:$D$12,0))),"") -> 46276 | L95: =IF($O95="","",$O95-TODAY()) -> -82 | M95: =IF(AND(TRIM($A95)="Finalized",$K95<>""),"",IF($F95="","",$F95+90-TODAY())) -> -82 | N95: =IF(AND(TRIM($A95)="Finalized",$K95<>""),"",IF($C95="","",$C95+365-TODAY())) -> 218 | O95: =IF(AND(TRIM($A95)="Finalized",$K95<>""),"",DATE(2026,7,19)) -> 46222 | P95: 90 days | Q95: BCBS | R95: 90 days | S95: Date of service | T95: 365 days | U95: Processed date | V95: 2026-04 April | W95: BH | AA95: 1 | AB95: 1372.91 | AC95: 0 | AD95: 0 | AE95: 46157 | AF95: 1372.91 | AG95: 110 | AH95: F4323 | AM95: SARKAR, AWNIK | AN95: ASAP Peoria | AO95: 46153
A96: =IFERROR(IF(INDEX([4]GAE!$A$2:$A$8,MATCH($D96,[4]GAE!$D$2:$D$8,0))="","",INDEX([4]GAE!$A$2:$A$8,MATCH($D96,[4]GAE!$D$2:$D$8,0))),"") -> Denied | B96: =IFERROR(IF(INDEX([4]GAE!$B$2:$B$8,MATCH($D96,[4]GAE!$D$2:$D$8,0))="","",INDEX([4]GAE!$B$2:$B$8,MATCH($D96,[4]GAE!$D$2:$D$8,0))),"") -> secondary - Added COB info, and resubmitted - Primary paid | C96: =IFERROR(IF(INDEX([4]GAE!$C$2:$C$8,MATCH($D96,[4]GAE!$D$2:$D$8,0))="","",INDEX([4]GAE!$C$2:$C$8,MATCH($D96,[4]GAE!$D$2:$D$8,0))),"") -> 46162 | D96: 558686710 | E96: HF330200116 | F96: 46132 | G96: Blue Cross Blue Shield of Arizona (BCBS AZ) | H96: Blue Cross Blue Shield of Arizona (BCBS AZ) | I96: Blue Cross Blue Shield of Arizona (BCBS AZ) | J96: 75774+26+XU x3; 36246+59+LT x1; 36245+59 x1; 36248+59 x1; 76937+26 x1; 37242 x1; 75710+26+XU+LT x1 | K96: =IFERROR(IF(INDEX([4]GAE!$K$2:$K$8,MATCH($D96,[4]GAE!$D$2:$D$8,0))="","",INDEX([4]GAE!$K$2:$K$8,MATCH($D96,[4]GAE!$D$2:$D$8,0))),"") -> 46278 | L96: =IF($O96="","",$O96-TODAY()) -> -82 | M96: =IF(AND(TRIM($A96)="Finalized",$K96<>""),"",IF($F96="","",$F96+90-TODAY())) -> -82 | N96: =IF(AND(TRIM($A96)="Finalized",$K96<>""),"",IF($C96="","",$C96+365-TODAY())) -> 223 | O96: =IF(AND(TRIM($A96)="Finalized",$K96<>""),"",DATE(2026,7,19)) -> 46222 | P96: 90 days | Q96: BCBS | R96: 90 days | S96: Date of service | T96: 365 days | U96: Processed date | V96: 2026-04 April | W96: GAE | X96: 26, 59 | Y96: XU, LT | Z96: LT | AA96: 3, 1 | AB96: 67599.91 | AC96: 66579.55 | AD96: 918.36 | AE96: 46162 | AF96: 102 | AG96: 110 | AH96: M1712 | AI96: I798 | AJ96: M25562 | AL96: 561534376 | AM96: HUNTER, DREW | AN96: Premier Endoscopy Center, LLC | AO96: 46152
A97: =IFERROR(IF(INDEX([4]DME!$A$2:$A$34,MATCH($D97,[4]DME!$D$2:$D$34,0))="","",INDEX([4]DME!$A$2:$A$34,MATCH($D97,[4]DME!$D$2:$D$34,0))),"") -> Under Review | B97: =IFERROR(IF(INDEX([4]DME!$B$2:$B$34,MATCH($D97,[4]DME!$D$2:$D$34,0))="","",INDEX([4]DME!$B$2:$B$34,MATCH($D97,[4]DME!$D$2:$D$34,0))),"") -> Call 800-636-2123 - DND A6010 Preferred Homecare is responsible for these services. Please submit the claim to Preferred Homecare for consideration | C97: =IFERROR(IF(INDEX([4]DME!$C$2:$C$34,MATCH($D97,[4]DME!$D$2:$D$34,0))="","",INDEX([4]DME!$C$2:$C$34,MATCH($D97,[4]DME!$D$2:$D$34,0))),"") -> 46141 | D97: 556833981 | E97: HF519300380 | F97: 46132 | G97: UnitedHealthcare Community Plan / Arizona Long Term Care | H97: UnitedHealthcare Community Plan / Arizona Long Term Care | I97: No Payer | J97: A6010+A1 x10 | K97: =IFERROR(IF(INDEX([4]DME!$K$2:$K$34,MATCH($D97,[4]DME!$D$2:$D$34,0))="","",INDEX([4]DME!$K$2:$K$34,MATCH($D97,[4]DME!$D$2:$D$34,0))),"") | L97: =IF($O97="","",$O97-TODAY()) -> -82 | M97: =IF(AND(TRIM($A97)="Finalized",$K97<>""),"",IF($C97="","",$C97+180-TODAY())) -> 17 | N97: =IF(AND(TRIM($A97)="Finalized",$K97<>""),"",IF($C97="","",$C97+365-TODAY())) -> 202 | O97: =IF(AND(TRIM($A97)="Finalized",$K97<>""),"",DATE(2026,7,19)) -> 46222 | P97: 90 days | Q97: UHC COMMUNITY | R97: 180 days | S97: Processed date | T97: 365 days | U97: Processed date | V97: 2026-04 April | W97: DME | X97: A1 | AA97: 10 | AB97: 2958.2 | AC97: 0 | AD97: 0 | AE97: 46141 | AF97: 2958.2 | AG97: 110 | AH97: G894 | AI97: M461 | AM97: ADLER, STEVEN | AN97: ASAP - DEER VALLEY | AO97: 46134
A98: =IFERROR(IF(INDEX([4]BH!$A$2:$A$12,MATCH($D98,[4]BH!$D$2:$D$12,0))="","",INDEX([4]BH!$A$2:$A$12,MATCH($D98,[4]BH!$D$2:$D$12,0))),"") -> Denied | B98: =IFERROR(IF(INDEX([4]BH!$B$2:$B$12,MATCH($D98,[4]BH!$D$2:$D$12,0))="","",INDEX([4]BH!$B$2:$B$12,MATCH($D98,[4]BH!$D$2:$D$12,0))),"") -> Added Date of Current Illness, claim note, and resubmitted - DND 99493 This non-payable code is for required reporting only. | C98: =IFERROR(IF(INDEX([4]BH!$C$2:$C$12,MATCH($D98,[4]BH!$D$2:$D$12,0))="","",INDEX([4]BH!$C$2:$C$12,MATCH($D98,[4]BH!$D$2:$D$12,0))),"") -> 46167 | D98: 556918462 | E98: HF341023592 | F98: 46134 | G98: Optum Care Medical Network of Arizona, Utah, & Washington (LifePrint) | H98: Optum Care Medical Network of Arizona, Utah, & Washington (LifePrint) | I98: No Payer | J98: 99494 x1; 99493 x1 | K98: =IFERROR(IF(INDEX([4]BH!$K$2:$K$12,MATCH($D98,[4]BH!$D$2:$D$12,0))="","",INDEX([4]BH!$K$2:$K$12,MATCH($D98,[4]BH!$D$2:$D$12,0))),"") -> 46265 | L98: =IF($O98="","",$O98-TODAY()) -> -80 | M98: =IF(AND(TRIM($A98)="Finalized",$K98<>""),"",IF($C98="","",$C98+365-TODAY())) -> 228 | N98: =IF(AND(TRIM($A98)="Finalized",$K98<>""),"",IF($C98="","",$C98+365-TODAY())) -> 228 | O98: =IF(AND(TRIM($A98)="Finalized",$K98<>""),"",DATE(2026,7,21)) -> 46224 | P98: 90 days | Q98: OPTUM | R98: 365 days | S98: Processed date | T98: 365 days | U98: Processed date | V98: 2026-04 April | W98: BH | AA98: 1 | AB98: 1372.91 | AC98: 0 | AD98: 0 | AE98: 46167 | AF98: 1372.91 | AG98: 108 | AH98: F332 | AI98: F411 | AM98: TURLEY, TODD | AN98: ASAP - Gilbert | AO98: 46153
A99: =IFERROR(IF(INDEX([4]ORTHO!$A$2:$A$21,MATCH($D99,[4]ORTHO!$D$2:$D$21,0))="","",INDEX([4]ORTHO!$A$2:$A$21,MATCH($D99,[4]ORTHO!$D$2:$D$21,0))),"") -> Denied | B99: =IFERROR(IF(INDEX([4]ORTHO!$B$2:$B$21,MATCH($D99,[4]ORTHO!$D$2:$D$21,0))="","",INDEX([4]ORTHO!$B$2:$B$21,MATCH($D99,[4]ORTHO!$D$2:$D$21,0))),"") -> Uploaded MR - ID 35635409 as per request - All CPT codes denied as no covered | C99: =IFERROR(IF(INDEX([4]ORTHO!$C$2:$C$21,MATCH($D99,[4]ORTHO!$D$2:$D$21,0))="","",INDEX([4]ORTHO!$C$2:$C$21,MATCH($D99,[4]ORTHO!$D$2:$D$21,0))),"") -> 46202 | D99: 563133469 | E99: HF538331188 | F99: 46135 | G99: Humana | H99: Humana | I99: No Payer | J99: 22551 x1; 22853 x1; 22845+59 x1; 22853+59 x1 | K99: =IFERROR(IF(INDEX([4]ORTHO!$K$2:$K$21,MATCH($D99,[4]ORTHO!$D$2:$D$21,0))="","",INDEX([4]ORTHO!$K$2:$K$21,MATCH($D99,[4]ORTHO!$D$2:$D$21,0))),"") -> 46279 | L99: =IF($O99="","",$O99-TODAY()) -> -79 | M99: =IF(AND(TRIM($A99)="Finalized",$K99<>""),"",IF($F99="","",$F99+90-TODAY())) -> -79 | N99: =IF(AND(TRIM($A99)="Finalized",$K99<>""),"",IF($C99="","",$C99+60-TODAY())) -> -42 | O99: =IF(AND(TRIM($A99)="Finalized",$K99<>""),"",DATE(2026,7,22)) -> 46225 | P99: 90 days | Q99: HUMANA COMMERCIAL | R99: 90 days | S99: Date of service | T99: 60 days | U99: Processed date | V99: 2026-04 April | W99: ORTHO | X99: 59 | AA99: 1 | AB99: 20158.46 | AC99: 0 | AD99: 0 | AE99: 46202 | AF99: 20158.46 | AG99: 107 | AH99: M5416 | AI99: M47816 | AM99: MAYURAN, VIKRAM | AN99: Banner Desert Medical Center | AO99: 46147
A100: =IFERROR(IF(INDEX([1]BH!$A$2:$A$17,MATCH($D100,[1]BH!$D$2:$D$17,0))="","",INDEX([1]BH!$A$2:$A$17,MATCH($D100,[1]BH!$D$2:$D$17,0))),"") -> Rejected | B100: =IFERROR(IF(INDEX([1]BH!$B$2:$B$17,MATCH($D100,[1]BH!$D$2:$D$17,0))="","",INDEX([1]BH!$B$2:$B$17,MATCH($D100,[1]BH!$D$2:$D$17,0))),"") -> Tfierro working on PT eligibility on dos | C100: =IFERROR(IF(INDEX([1]BH!$C$2:$C$17,MATCH($D100,[1]BH!$D$2:$D$17,0))="","",INDEX([1]BH!$C$2:$C$17,MATCH($D100,[1]BH!$D$2:$D$17,0))),"") -> 46070 | D100: 565238310 | E100: HF524312806 | F100: 46045 | G100: Medica Health Plan Solutions (Mayo Plan - CHI Health) | H100: Medica Health Plan Solutions (Mayo Plan - CHI Health) | I100: No Payer | J100: 99492 x1; 99494 x1 | K100: =IFERROR(IF(INDEX([1]BH!$K$2:$K$17,MATCH($D100,[1]BH!$D$2:$D$17,0))="","",INDEX([1]BH!$K$2:$K$17,MATCH($D100,[1]BH!$D$2:$D$17,0))),"") -> 46289 | L100: =IF($O100="","",$O100-TODAY()) -> -79 | M100: =IF(AND(TRIM($A100)="Finalized",$K100<>""),"",IF($C100="","",$C100+365-TODAY())) -> 131 | N100: =IF(AND(TRIM($A100)="Finalized",$K100<>""),"",IF($C100="","",$C100+365-TODAY())) -> 131 | O100: =IF(AND(TRIM($A100)="Finalized",$K100<>""),"",DATE(2026,7,22)) -> 46225 | P100: 180 days | Q100: MEDICA | R100: 365 days | S100: Processed date | T100: 365 days | U100: Processed date | V100: 2026-01 January | W100: BH | AA100: 1 | AB100: 1426.25 | AC100: 0 | AD100: 0 | AE100: 46070 | AF100: 1426.25 | AG100: 197 | AH100: F411 | AM100: MEARS, CHAD | AN100: ASAP - Gilbert | AO100: 46057
...
